kotlin version: 2.0.21
error message: org.jetbrains.kotlin.backend.common.BackendException: Backend Internal error: Exception during IR lowering
File being compiled: D:/Code/Kotlin/DATN/DATN/app/src/main/java/com/example/datn/data/repository/impl/TestRepositoryImpl.kt
The root cause java.lang.RuntimeException was thrown at: org.jetbrains.kotlin.backend.jvm.codegen.FunctionCodegen.generate(FunctionCodegen.kt:47)
	at org.jetbrains.kotlin.backend.common.CodegenUtil.reportBackendException(CodegenUtil.kt:253)
	at org.jetbrains.kotlin.backend.common.CodegenUtil.reportBackendException$default(CodegenUtil.kt:236)
	at org.jetbrains.kotlin.backend.common.phaser.PerformByIrFilePhase.invokeSequential(performByIrFile.kt:65)
	at org.jetbrains.kotlin.backend.common.phaser.PerformByIrFilePhase.invoke(performByIrFile.kt:52)
	at org.jetbrains.kotlin.backend.common.phaser.PerformByIrFilePhase.invoke(performByIrFile.kt:38)
	at org.jetbrains.kotlin.backend.common.phaser.NamedCompilerPhase.phaseBody(CompilerPhase.kt:166)
	at org.jetbrains.kotlin.backend.common.phaser.AbstractNamedCompilerPhase.invoke(CompilerPhase.kt:113)
	at org.jetbrains.kotlin.backend.common.phaser.CompositePhase.invoke(PhaseBuilders.kt:27)
	at org.jetbrains.kotlin.backend.common.phaser.CompositePhase.invoke(PhaseBuilders.kt:14)
	at org.jetbrains.kotlin.backend.common.phaser.NamedCompilerPhase.phaseBody(CompilerPhase.kt:166)
	at org.jetbrains.kotlin.backend.common.phaser.AbstractNamedCompilerPhase.invoke(CompilerPhase.kt:113)
	at org.jetbrains.kotlin.backend.common.phaser.CompilerPhaseKt.invokeToplevel(CompilerPhase.kt:62)
	at org.jetbrains.kotlin.backend.jvm.JvmIrCodegenFactory.invokeCodegen(JvmIrCodegenFactory.kt:371)
	at org.jetbrains.kotlin.codegen.CodegenFactory.generateModule(CodegenFactory.kt:47)
	at org.jetbrains.kotlin.backend.jvm.JvmIrCodegenFactory.generateModuleInFrontendIRMode(JvmIrCodegenFactory.kt:433)
	at org.jetbrains.kotlin.cli.jvm.compiler.pipeline.JvmCompilerPipelineKt.generateCodeFromIr(jvmCompilerPipeline.kt:246)
	at org.jetbrains.kotlin.cli.jvm.compiler.pipeline.JvmCompilerPipelineKt.compileModulesUsingFrontendIrAndLightTree(jvmCompilerPipeline.kt:142)
	at org.jetbrains.kotlin.cli.jvm.K2JVMCompiler.doExecute(K2JVMCompiler.kt:148)
	at org.jetbrains.kotlin.cli.jvm.K2JVMCompiler.doExecute(K2JVMCompiler.kt:43)
	at org.jetbrains.kotlin.cli.common.CLICompiler.execImpl(CLICompiler.kt:103)
	at org.jetbrains.kotlin.cli.common.CLICompiler.execImpl(CLICompiler.kt:49)
	at org.jetbrains.kotlin.cli.common.CLITool.exec(CLITool.kt:101)
	at org.jetbrains.kotlin.incremental.IncrementalJvmCompilerRunner.runCompiler(IncrementalJvmCompilerRunner.kt:464)
	at org.jetbrains.kotlin.incremental.IncrementalJvmCompilerRunner.runCompiler(IncrementalJvmCompilerRunner.kt:73)
	at org.jetbrains.kotlin.incremental.IncrementalCompilerRunner.doCompile(IncrementalCompilerRunner.kt:506)
	at org.jetbrains.kotlin.incremental.IncrementalCompilerRunner.compileImpl(IncrementalCompilerRunner.kt:423)
	at org.jetbrains.kotlin.incremental.IncrementalCompilerRunner.compileNonIncrementally(IncrementalCompilerRunner.kt:301)
	at org.jetbrains.kotlin.incremental.IncrementalCompilerRunner.compile(IncrementalCompilerRunner.kt:129)
	at org.jetbrains.kotlin.daemon.CompileServiceImplBase.execIncrementalCompiler(CompileServiceImpl.kt:675)
	at org.jetbrains.kotlin.daemon.CompileServiceImplBase.access$execIncrementalCompiler(CompileServiceImpl.kt:92)
	at org.jetbrains.kotlin.daemon.CompileServiceImpl.compile(CompileServiceImpl.kt:1660)
	at java.base/jdk.internal.reflect.DirectMethodHandleAccessor.invoke(Unknown Source)
	at java.base/java.lang.reflect.Method.invoke(Unknown Source)
	at java.rmi/sun.rmi.server.UnicastServerRef.dispatch(Unknown Source)
	at java.rmi/sun.rmi.transport.Transport$1.run(Unknown Source)
	at java.rmi/sun.rmi.transport.Transport$1.run(Unknown Source)
	at java.base/java.security.AccessController.doPrivileged(Unknown Source)
	at java.rmi/sun.rmi.transport.Transport.serviceCall(Unknown Source)
	at java.rmi/sun.rmi.transport.tcp.TCPTransport.handleMessages(Unknown Source)
	at java.rmi/sun.rmi.transport.tcp.TCPTransport$ConnectionHandler.run0(Unknown Source)
	at java.rmi/sun.rmi.transport.tcp.TCPTransport$ConnectionHandler.lambda$run$0(Unknown Source)
	at java.base/java.security.AccessController.doPrivileged(Unknown Source)
	at java.rmi/sun.rmi.transport.tcp.TCPTransport$ConnectionHandler.run(Unknown Source)
	at java.base/java.util.concurrent.ThreadPoolExecutor.runWorker(Unknown Source)
	at java.base/java.util.concurrent.ThreadPoolExecutor$Worker.run(Unknown Source)
	at java.base/java.lang.Thread.run(Unknown Source)
Caused by: java.lang.RuntimeException: Exception while generating code for:
FUN name:submitTestResult visibility:public modality:OPEN <> ($this:com.example.datn.data.repository.impl.TestRepositoryImpl, result:com.example.datn.domain.models.StudentTestResult, answers:kotlin.collections.Map<kotlin.String, kotlin.Any>) returnType:kotlinx.coroutines.flow.Flow<com.example.datn.core.utils.Resource<com.example.datn.domain.models.StudentTestResult>>
  overridden:
    public abstract fun submitTestResult (result: com.example.datn.domain.models.StudentTestResult, answers: kotlin.collections.Map<kotlin.String, kotlin.Any>): kotlinx.coroutines.flow.Flow<com.example.datn.core.utils.Resource<com.example.datn.domain.models.StudentTestResult>> declared in com.example.datn.domain.repository.ITestRepository
  $this: VALUE_PARAMETER name:<this> type:com.example.datn.data.repository.impl.TestRepositoryImpl
  VALUE_PARAMETER name:result index:0 type:com.example.datn.domain.models.StudentTestResult
  VALUE_PARAMETER name:answers index:1 type:kotlin.collections.Map<kotlin.String, kotlin.Any>
  BLOCK_BODY
    RETURN type=kotlin.Nothing from='public open fun submitTestResult (result: com.example.datn.domain.models.StudentTestResult, answers: kotlin.collections.Map<kotlin.String, kotlin.Any>): kotlinx.coroutines.flow.Flow<com.example.datn.core.utils.Resource<com.example.datn.domain.models.StudentTestResult>> declared in com.example.datn.data.repository.impl.TestRepositoryImpl'
      CALL 'public final fun flow <T> (block: @[ExtensionFunctionType] kotlin.coroutines.SuspendFunction1<kotlinx.coroutines.flow.FlowCollector<T of kotlinx.coroutines.flow.FlowKt.flow>, kotlin.Unit>): kotlinx.coroutines.flow.Flow<T of kotlinx.coroutines.flow.FlowKt.flow> declared in kotlinx.coroutines.flow.FlowKt' type=kotlinx.coroutines.flow.Flow<com.example.datn.core.utils.Resource<com.example.datn.domain.models.StudentTestResult>> origin=null
        <T>: com.example.datn.core.utils.Resource<com.example.datn.domain.models.StudentTestResult>
        block: BLOCK type=com.example.datn.data.repository.impl.TestRepositoryImpl.submitTestResult.<no name provided> origin=null
          CLASS SUSPEND_LAMBDA CLASS name:<no name provided> modality:FINAL visibility:public/*package*/ superTypes:[kotlin.coroutines.jvm.internal.SuspendLambda; kotlin.jvm.functions.Function2<kotlinx.coroutines.flow.FlowCollector<com.example.datn.core.utils.Resource<com.example.datn.domain.models.StudentTestResult>>, kotlin.coroutines.Continuation<kotlin.Unit>?, kotlin.Any?>]
            $this: VALUE_PARAMETER INSTANCE_RECEIVER name:<this> type:com.example.datn.data.repository.impl.TestRepositoryImpl.submitTestResult.<no name provided>
            FIELD name:label type:kotlin.Int visibility:public/*package*/
            FIELD FIELD_FOR_CAPTURED_VALUE name:L$0 type:kotlin.Any? visibility:private
            CONSTRUCTOR SUSPEND_LAMBDA visibility:public/*package*/ <> ($result:com.example.datn.domain.models.StudentTestResult, this$0:com.example.datn.data.repository.impl.TestRepositoryImpl, $answers:kotlin.collections.Map<kotlin.String, kotlin.Any>, $completion:kotlin.coroutines.Continuation<com.example.datn.data.repository.impl.TestRepositoryImpl.submitTestResult.<no name provided>>?) returnType:com.example.datn.data.repository.impl.TestRepositoryImpl.submitTestResult.<no name provided> [primary]
              VALUE_PARAMETER BOUND_VALUE_PARAMETER name:$result index:0 type:com.example.datn.domain.models.StudentTestResult
              VALUE_PARAMETER BOUND_RECEIVER_PARAMETER name:this$0 index:1 type:com.example.datn.data.repository.impl.TestRepositoryImpl
              VALUE_PARAMETER BOUND_VALUE_PARAMETER name:$answers index:2 type:kotlin.collections.Map<kotlin.String, kotlin.Any>
              VALUE_PARAMETER name:$completion index:3 type:kotlin.coroutines.Continuation<com.example.datn.data.repository.impl.TestRepositoryImpl.submitTestResult.<no name provided>>?
              BLOCK_BODY
                SET_FIELD 'FIELD FIELD_FOR_CAPTURED_VALUE name:$result type:com.example.datn.domain.models.StudentTestResult visibility:public/*package*/ [final] declared in com.example.datn.data.repository.impl.TestRepositoryImpl.submitTestResult.<no name provided>' type=kotlin.Unit origin=INITIALIZER_OF_FIELD_FOR_CAPTURED_VALUE
                  receiver: GET_VAR '<this>: com.example.datn.data.repository.impl.TestRepositoryImpl.submitTestResult.<no name provided> declared in com.example.datn.data.repository.impl.TestRepositoryImpl.submitTestResult.<no name provided>' type=com.example.datn.data.repository.impl.TestRepositoryImpl.submitTestResult.<no name provided> origin=null
                  value: GET_VAR '$result: com.example.datn.domain.models.StudentTestResult declared in com.example.datn.data.repository.impl.TestRepositoryImpl.submitTestResult.<no name provided>.<init>' type=com.example.datn.domain.models.StudentTestResult origin=null
                SET_FIELD 'FIELD FIELD_FOR_CAPTURED_VALUE name:this$0 type:com.example.datn.data.repository.impl.TestRepositoryImpl visibility:public/*package*/ [final] declared in com.example.datn.data.repository.impl.TestRepositoryImpl.submitTestResult.<no name provided>' type=kotlin.Unit origin=INITIALIZER_OF_FIELD_FOR_CAPTURED_VALUE
                  receiver: GET_VAR '<this>: com.example.datn.data.repository.impl.TestRepositoryImpl.submitTestResult.<no name provided> declared in com.example.datn.data.repository.impl.TestRepositoryImpl.submitTestResult.<no name provided>' type=com.example.datn.data.repository.impl.TestRepositoryImpl.submitTestResult.<no name provided> origin=null
                  value: GET_VAR 'this$0: com.example.datn.data.repository.impl.TestRepositoryImpl declared in com.example.datn.data.repository.impl.TestRepositoryImpl.submitTestResult.<no name provided>.<init>' type=com.example.datn.data.repository.impl.TestRepositoryImpl origin=null
                SET_FIELD 'FIELD FIELD_FOR_CAPTURED_VALUE name:$answers type:kotlin.collections.Map<kotlin.String, kotlin.Any> visibility:public/*package*/ [final] declared in com.example.datn.data.repository.impl.TestRepositoryImpl.submitTestResult.<no name provided>' type=kotlin.Unit origin=INITIALIZER_OF_FIELD_FOR_CAPTURED_VALUE
                  receiver: GET_VAR '<this>: com.example.datn.data.repository.impl.TestRepositoryImpl.submitTestResult.<no name provided> declared in com.example.datn.data.repository.impl.TestRepositoryImpl.submitTestResult.<no name provided>' type=com.example.datn.data.repository.impl.TestRepositoryImpl.submitTestResult.<no name provided> origin=null
                  value: GET_VAR '$answers: kotlin.collections.Map<kotlin.String, kotlin.Any> declared in com.example.datn.data.repository.impl.TestRepositoryImpl.submitTestResult.<no name provided>.<init>' type=kotlin.collections.Map<kotlin.String, kotlin.Any> origin=null
                DELEGATING_CONSTRUCTOR_CALL 'public constructor <init> (arity: kotlin.Int, $completion: kotlin.coroutines.Continuation<kotlin.Any?>?) declared in kotlin.coroutines.jvm.internal.SuspendLambda'
                  arity: CONST Int type=kotlin.Int value=2
                  $completion: GET_VAR '$completion: kotlin.coroutines.Continuation<com.example.datn.data.repository.impl.TestRepositoryImpl.submitTestResult.<no name provided>>? declared in com.example.datn.data.repository.impl.TestRepositoryImpl.submitTestResult.<no name provided>.<init>' type=kotlin.coroutines.Continuation<com.example.datn.data.repository.impl.TestRepositoryImpl.submitTestResult.<no name provided>>? origin=null
                BLOCK type=kotlin.Unit origin=null
            FUN name:invokeSuspend visibility:public modality:FINAL <> ($this:com.example.datn.data.repository.impl.TestRepositoryImpl.submitTestResult.<no name provided>, $result:kotlin.Result<kotlin.Any?>) returnType:kotlin.Any?
              overridden:
                protected abstract fun invokeSuspend ($result: kotlin.Result<kotlin.Any?>): kotlin.Any? declared in kotlin.coroutines.jvm.internal.SuspendLambda
              $this: VALUE_PARAMETER INSTANCE_RECEIVER name:<this> type:com.example.datn.data.repository.impl.TestRepositoryImpl.submitTestResult.<no name provided>
              VALUE_PARAMETER name:$result index:0 type:kotlin.Result<kotlin.Any?>
              BLOCK_BODY
                VAR name:$this$flow type:kotlinx.coroutines.flow.FlowCollector<com.example.datn.core.utils.Resource<com.example.datn.domain.models.StudentTestResult>> [val]
                  BLOCK type=kotlinx.coroutines.flow.FlowCollector<com.example.datn.core.utils.Resource<com.example.datn.domain.models.StudentTestResult>> origin=null
                    GET_FIELD 'FIELD FIELD_FOR_CAPTURED_VALUE name:L$0 type:kotlin.Any? visibility:private declared in com.example.datn.data.repository.impl.TestRepositoryImpl.submitTestResult.<no name provided>' type=kotlinx.coroutines.flow.FlowCollector<com.example.datn.core.utils.Resource<com.example.datn.domain.models.StudentTestResult>> origin=null
                      receiver: GET_VAR '<this>: com.example.datn.data.repository.impl.TestRepositoryImpl.submitTestResult.<no name provided> declared in com.example.datn.data.repository.impl.TestRepositoryImpl.submitTestResult.<no name provided>.invokeSuspend' type=com.example.datn.data.repository.impl.TestRepositoryImpl.submitTestResult.<no name provided> origin=null
                TRY type=kotlin.Unit
                  try: BLOCK type=kotlin.Unit origin=null
                    CALL 'public abstract fun emit (value: T of kotlinx.coroutines.flow.FlowCollector, $completion: kotlin.coroutines.Continuation<kotlin.Unit>): kotlin.Any? [suspend] declared in kotlinx.coroutines.flow.FlowCollector' type=kotlin.Unit origin=null
                      $this: GET_VAR 'val $this$flow: kotlinx.coroutines.flow.FlowCollector<com.example.datn.core.utils.Resource<com.example.datn.domain.models.StudentTestResult>> [val] declared in com.example.datn.data.repository.impl.TestRepositoryImpl.submitTestResult.<no name provided>.invokeSuspend' type=kotlinx.coroutines.flow.FlowCollector<com.example.datn.core.utils.Resource<com.example.datn.domain.models.StudentTestResult>> origin=null
                      value: CONSTRUCTOR_CALL 'public constructor <init> () [primary] declared in com.example.datn.core.utils.Resource.Loading' type=com.example.datn.core.utils.Resource.Loading<com.example.datn.domain.models.StudentTestResult> origin=null
                        <class: T>: com.example.datn.domain.models.StudentTestResult
                      $completion: GET_VAR '<this>: com.example.datn.data.repository.impl.TestRepositoryImpl.submitTestResult.<no name provided> declared in com.example.datn.data.repository.impl.TestRepositoryImpl.submitTestResult.<no name provided>.invokeSuspend' type=com.example.datn.data.repository.impl.TestRepositoryImpl.submitTestResult.<no name provided> origin=null
                    VAR name:withTimestamps type:com.example.datn.domain.models.StudentTestResult [val]
                      CALL 'public final fun copy$default ($this: com.example.datn.domain.models.StudentTestResult, id: kotlin.String?, studentId: kotlin.String?, testId: kotlin.String?, score: kotlin.Double, completionStatus: com.example.datn.domain.models.TestStatus?, submissionTime: java.time.Instant?, durationSeconds: kotlin.Long, createdAt: java.time.Instant?, updatedAt: java.time.Instant?, $mask0: kotlin.Int, $handler: kotlin.Any?): com.example.datn.domain.models.StudentTestResult declared in com.example.datn.domain.models.StudentTestResult' type=com.example.datn.domain.models.StudentTestResult origin=DEFAULT_DISPATCH_CALL
                        $this: GET_FIELD 'FIELD FIELD_FOR_CAPTURED_VALUE name:$result type:com.example.datn.domain.models.StudentTestResult visibility:public/*package*/ [final] declared in com.example.datn.data.repository.impl.TestRepositoryImpl.submitTestResult.<no name provided>' type=com.example.datn.domain.models.StudentTestResult origin=null
                          receiver: GET_VAR '<this>: com.example.datn.data.repository.impl.TestRepositoryImpl.submitTestResult.<no name provided> declared in com.example.datn.data.repository.impl.TestRepositoryImpl.submitTestResult.<no name provided>.invokeSuspend' type=com.example.datn.data.repository.impl.TestRepositoryImpl.submitTestResult.<no name provided> origin=null
                        id: COMPOSITE type=kotlin.String? origin=DEFAULT_VALUE
                          CONST Null type=kotlin.String? value=null
                        studentId: COMPOSITE type=kotlin.String? origin=DEFAULT_VALUE
                          CONST Null type=kotlin.String? value=null
                        testId: COMPOSITE type=kotlin.String? origin=DEFAULT_VALUE
                          CONST Null type=kotlin.String? value=null
                        score: COMPOSITE type=kotlin.Double origin=DEFAULT_VALUE
                          CONST Double type=kotlin.Double value=0.0
                        completionStatus: COMPOSITE type=com.example.datn.domain.models.TestStatus? origin=DEFAULT_VALUE
                          CONST Null type=com.example.datn.domain.models.TestStatus? value=null
                        submissionTime: BLOCK type=java.time.Instant origin=null
                          VAR IR_TEMPORARY_VARIABLE name:tmp0 type:kotlin.Any? [val]
                            WHEN type=@[FlexibleNullability] java.time.Instant? origin=IF
                              BRANCH
                                if: CALL 'public final fun EQEQ (arg0: kotlin.Any?, arg1: kotlin.Any?): kotlin.Boolean declared in kotlin.internal.ir' type=kotlin.Boolean origin=EQEQ
                                  arg0: CALL 'public open fun toEpochMilli (): kotlin.Long declared in java.time.Instant' type=kotlin.Long origin=null
                                    $this: CALL 'public final fun <get-submissionTime> (): java.time.Instant declared in com.example.datn.domain.models.StudentTestResult' type=java.time.Instant origin=GET_PROPERTY
                                      $this: GET_FIELD 'FIELD FIELD_FOR_CAPTURED_VALUE name:$result type:com.example.datn.domain.models.StudentTestResult visibility:public/*package*/ [final] declared in com.example.datn.data.repository.impl.TestRepositoryImpl.submitTestResult.<no name provided>' type=com.example.datn.domain.models.StudentTestResult origin=null
                                        receiver: GET_VAR '<this>: com.example.datn.data.repository.impl.TestRepositoryImpl.submitTestResult.<no name provided> declared in com.example.datn.data.repository.impl.TestRepositoryImpl.submitTestResult.<no name provided>.invokeSuspend' type=com.example.datn.data.repository.impl.TestRepositoryImpl.submitTestResult.<no name provided> origin=null
                                  arg1: CONST Long type=kotlin.Long value=0
                                then: CALL 'public open fun now (): @[FlexibleNullability] java.time.Instant? declared in java.time.Instant' type=@[FlexibleNullability] java.time.Instant? origin=null
                              BRANCH
                                if: CONST Boolean type=kotlin.Boolean value=true
                                then: CALL 'public final fun <get-submissionTime> (): java.time.Instant declared in com.example.datn.domain.models.StudentTestResult' type=java.time.Instant origin=GET_PROPERTY
                                  $this: GET_FIELD 'FIELD FIELD_FOR_CAPTURED_VALUE name:$result type:com.example.datn.domain.models.StudentTestResult visibility:public/*package*/ [final] declared in com.example.datn.data.repository.impl.TestRepositoryImpl.submitTestResult.<no name provided>' type=com.example.datn.domain.models.StudentTestResult origin=null
                                    receiver: GET_VAR '<this>: com.example.datn.data.repository.impl.TestRepositoryImpl.submitTestResult.<no name provided> declared in com.example.datn.data.repository.impl.TestRepositoryImpl.submitTestResult.<no name provided>.invokeSuspend' type=com.example.datn.data.repository.impl.TestRepositoryImpl.submitTestResult.<no name provided> origin=null
                          CALL 'public final fun checkNotNull (object: kotlin.Any?): kotlin.Unit declared in kotlin.jvm.internal.Intrinsics' type=kotlin.Unit origin=null
                            object: GET_VAR 'val tmp0: kotlin.Any? [val] declared in com.example.datn.data.repository.impl.TestRepositoryImpl.submitTestResult.<no name provided>.invokeSuspend' type=kotlin.Any? origin=null
                          GET_VAR 'val tmp0: kotlin.Any? [val] declared in com.example.datn.data.repository.impl.TestRepositoryImpl.submitTestResult.<no name provided>.invokeSuspend' type=kotlin.Any? origin=null
                        durationSeconds: COMPOSITE type=kotlin.Long origin=DEFAULT_VALUE
                          CONST Long type=kotlin.Long value=0
                        createdAt: BLOCK type=java.time.Instant origin=null
                          VAR IR_TEMPORARY_VARIABLE name:tmp1 type:kotlin.Any? [val]
                            WHEN type=@[FlexibleNullability] java.time.Instant? origin=IF
                              BRANCH
                                if: CALL 'public final fun EQEQ (arg0: kotlin.Any?, arg1: kotlin.Any?): kotlin.Boolean declared in kotlin.internal.ir' type=kotlin.Boolean origin=EQEQ
                                  arg0: CALL 'public open fun toEpochMilli (): kotlin.Long declared in java.time.Instant' type=kotlin.Long origin=null
                                    $this: CALL 'public final fun <get-createdAt> (): java.time.Instant declared in com.example.datn.domain.models.StudentTestResult' type=java.time.Instant origin=GET_PROPERTY
                                      $this: GET_FIELD 'FIELD FIELD_FOR_CAPTURED_VALUE name:$result type:com.example.datn.domain.models.StudentTestResult visibility:public/*package*/ [final] declared in com.example.datn.data.repository.impl.TestRepositoryImpl.submitTestResult.<no name provided>' type=com.example.datn.domain.models.StudentTestResult origin=null
                                        receiver: GET_VAR '<this>: com.example.datn.data.repository.impl.TestRepositoryImpl.submitTestResult.<no name provided> declared in com.example.datn.data.repository.impl.TestRepositoryImpl.submitTestResult.<no name provided>.invokeSuspend' type=com.example.datn.data.repository.impl.TestRepositoryImpl.submitTestResult.<no name provided> origin=null
                                  arg1: CONST Long type=kotlin.Long value=0
                                then: CALL 'public open fun now (): @[FlexibleNullability] java.time.Instant? declared in java.time.Instant' type=@[FlexibleNullability] java.time.Instant? origin=null
                              BRANCH
                                if: CONST Boolean type=kotlin.Boolean value=true
                                then: CALL 'public final fun <get-createdAt> (): java.time.Instant declared in com.example.datn.domain.models.StudentTestResult' type=java.time.Instant origin=GET_PROPERTY
                                  $this: GET_FIELD 'FIELD FIELD_FOR_CAPTURED_VALUE name:$result type:com.example.datn.domain.models.StudentTestResult visibility:public/*package*/ [final] declared in com.example.datn.data.repository.impl.TestRepositoryImpl.submitTestResult.<no name provided>' type=com.example.datn.domain.models.StudentTestResult origin=null
                                    receiver: GET_VAR '<this>: com.example.datn.data.repository.impl.TestRepositoryImpl.submitTestResult.<no name provided> declared in com.example.datn.data.repository.impl.TestRepositoryImpl.submitTestResult.<no name provided>.invokeSuspend' type=com.example.datn.data.repository.impl.TestRepositoryImpl.submitTestResult.<no name provided> origin=null
                          CALL 'public final fun checkNotNull (object: kotlin.Any?): kotlin.Unit declared in kotlin.jvm.internal.Intrinsics' type=kotlin.Unit origin=null
                            object: GET_VAR 'val tmp1: kotlin.Any? [val] declared in com.example.datn.data.repository.impl.TestRepositoryImpl.submitTestResult.<no name provided>.invokeSuspend' type=kotlin.Any? origin=null
                          GET_VAR 'val tmp1: kotlin.Any? [val] declared in com.example.datn.data.repository.impl.TestRepositoryImpl.submitTestResult.<no name provided>.invokeSuspend' type=kotlin.Any? origin=null
                        updatedAt: BLOCK type=java.time.Instant origin=null
                          VAR IR_TEMPORARY_VARIABLE name:tmp2 type:kotlin.Any? [val]
                            CALL 'public open fun now (): @[FlexibleNullability] java.time.Instant? declared in java.time.Instant' type=@[FlexibleNullability] java.time.Instant? origin=null
                          CALL 'public final fun checkNotNullExpressionValue (value: kotlin.Any?, expression: kotlin.String): kotlin.Unit declared in kotlin.jvm.internal.Intrinsics' type=kotlin.Unit origin=null
                            value: GET_VAR 'val tmp2: kotlin.Any? [val] declared in com.example.datn.data.repository.impl.TestRepositoryImpl.submitTestResult.<no name provided>.invokeSuspend' type=kotlin.Any? origin=null
                            expression: CONST String type=kotlin.String value="now(...)"
                          GET_VAR 'val tmp2: kotlin.Any? [val] declared in com.example.datn.data.repository.impl.TestRepositoryImpl.submitTestResult.<no name provided>.invokeSuspend' type=kotlin.Any? origin=null
                        $mask0: CONST Int type=kotlin.Int value=95
                        $handler: CONST Null type=kotlin.Any? value=null
                    BLOCK type=kotlin.Unit origin=WHEN
                      VAR name:remote type:com.example.datn.core.utils.Resource<com.example.datn.domain.models.StudentTestResult?> [val]
                        CALL 'public final fun submitTestResult (result: com.example.datn.domain.models.StudentTestResult, $completion: kotlin.coroutines.Continuation<com.example.datn.core.utils.Resource<com.example.datn.domain.models.StudentTestResult?>>): kotlin.Any? [suspend] declared in com.example.datn.data.remote.datasource.FirebaseDataSource' type=com.example.datn.core.utils.Resource<com.example.datn.domain.models.StudentTestResult?> origin=null
                          $this: CALL 'public final fun access$getFirebaseDataSource$p ($this: com.example.datn.data.repository.impl.TestRepositoryImpl): com.example.datn.data.remote.datasource.FirebaseDataSource declared in com.example.datn.data.repository.impl.TestRepositoryImpl' type=com.example.datn.data.remote.datasource.FirebaseDataSource origin=null
                            $this: GET_FIELD 'FIELD FIELD_FOR_CAPTURED_VALUE name:this$0 type:com.example.datn.data.repository.impl.TestRepositoryImpl visibility:public/*package*/ [final] declared in com.example.datn.data.repository.impl.TestRepositoryImpl.submitTestResult.<no name provided>' type=com.example.datn.data.repository.impl.TestRepositoryImpl origin=null
                              receiver: GET_VAR '<this>: com.example.datn.data.repository.impl.TestRepositoryImpl.submitTestResult.<no name provided> declared in com.example.datn.data.repository.impl.TestRepositoryImpl.submitTestResult.<no name provided>.invokeSuspend' type=com.example.datn.data.repository.impl.TestRepositoryImpl.submitTestResult.<no name provided> origin=null
                          result: GET_VAR 'val withTimestamps: com.example.datn.domain.models.StudentTestResult [val] declared in com.example.datn.data.repository.impl.TestRepositoryImpl.submitTestResult.<no name provided>.invokeSuspend' type=com.example.datn.domain.models.StudentTestResult origin=null
                          $completion: GET_VAR '<this>: com.example.datn.data.repository.impl.TestRepositoryImpl.submitTestResult.<no name provided> declared in com.example.datn.data.repository.impl.TestRepositoryImpl.submitTestResult.<no name provided>.invokeSuspend' type=com.example.datn.data.repository.impl.TestRepositoryImpl.submitTestResult.<no name provided> origin=null
                      WHEN type=kotlin.Unit origin=WHEN
                        BRANCH
                          if: TYPE_OP type=kotlin.Boolean origin=INSTANCEOF typeOperand=com.example.datn.core.utils.Resource.Success<com.example.datn.domain.models.StudentTestResult?>
                            GET_VAR 'val remote: com.example.datn.core.utils.Resource<com.example.datn.domain.models.StudentTestResult?> [val] declared in com.example.datn.data.repository.impl.TestRepositoryImpl.submitTestResult.<no name provided>.invokeSuspend' type=com.example.datn.core.utils.Resource<com.example.datn.domain.models.StudentTestResult?> origin=null
                          then: BLOCK type=kotlin.Unit origin=null
                            VAR name:saved type:com.example.datn.domain.models.StudentTestResult [val]
                              BLOCK type=com.example.datn.domain.models.StudentTestResult origin=FOLDED_ELVIS
                                WHEN type=com.example.datn.domain.models.StudentTestResult origin=FOLDED_ELVIS
                                  BRANCH
                                    if: COMPOSITE type=kotlin.Boolean origin=null
                                      VAR IR_TEMPORARY_VARIABLE name:tmp0_elvis_lhs type:com.example.datn.domain.models.StudentTestResult? [val]
                                        CALL 'public final fun <get-data> (): T of com.example.datn.core.utils.Resource.Success declared in com.example.datn.core.utils.Resource.Success' type=com.example.datn.domain.models.StudentTestResult? origin=GET_PROPERTY
                                          $this: TYPE_OP type=com.example.datn.core.utils.Resource.Success<com.example.datn.domain.models.StudentTestResult?> origin=IMPLICIT_CAST typeOperand=com.example.datn.core.utils.Resource.Success<com.example.datn.domain.models.StudentTestResult?>
                                            GET_VAR 'val remote: com.example.datn.core.utils.Resource<com.example.datn.domain.models.StudentTestResult?> [val] declared in com.example.datn.data.repository.impl.TestRepositoryImpl.submitTestResult.<no name provided>.invokeSuspend' type=com.example.datn.core.utils.Resource<com.example.datn.domain.models.StudentTestResult?> origin=null
                                      CALL 'public final fun not (): kotlin.Boolean [operator] declared in kotlin.Boolean' type=kotlin.Boolean origin=null
                                        $this: CALL 'public final fun EQEQ (arg0: kotlin.Any?, arg1: kotlin.Any?): kotlin.Boolean declared in kotlin.internal.ir' type=kotlin.Boolean origin=null
                                          arg0: GET_VAR 'val tmp0_elvis_lhs: com.example.datn.domain.models.StudentTestResult? [val] declared in com.example.datn.data.repository.impl.TestRepositoryImpl.submitTestResult.<no name provided>.invokeSuspend' type=com.example.datn.domain.models.StudentTestResult? origin=null
                                          arg1: CONST Null type=kotlin.Nothing? value=null
                                    then: GET_VAR 'val tmp0_elvis_lhs: com.example.datn.domain.models.StudentTestResult? [val] declared in com.example.datn.data.repository.impl.TestRepositoryImpl.submitTestResult.<no name provided>.invokeSuspend' type=com.example.datn.domain.models.StudentTestResult? origin=null
                                  BRANCH
                                    if: CONST Boolean type=kotlin.Boolean value=true
                                    then: GET_VAR 'val withTimestamps: com.example.datn.domain.models.StudentTestResult [val] declared in com.example.datn.data.repository.impl.TestRepositoryImpl.submitTestResult.<no name provided>.invokeSuspend' type=com.example.datn.domain.models.StudentTestResult origin=null
                            CALL 'public abstract fun insert (entity: com.example.datn.data.local.entities.StudentTestResultEntity, $completion: kotlin.coroutines.Continuation<kotlin.Unit>): kotlin.Any? [suspend,fake_override] declared in com.example.datn.data.local.dao.StudentTestResultDao' type=kotlin.Unit origin=null
                              $this: CALL 'public final fun access$getStudentTestResultDao$p ($this: com.example.datn.data.repository.impl.TestRepositoryImpl): com.example.datn.data.local.dao.StudentTestResultDao declared in com.example.datn.data.repository.impl.TestRepositoryImpl' type=com.example.datn.data.local.dao.StudentTestResultDao origin=null
                                $this: GET_FIELD 'FIELD FIELD_FOR_CAPTURED_VALUE name:this$0 type:com.example.datn.data.repository.impl.TestRepositoryImpl visibility:public/*package*/ [final] declared in com.example.datn.data.repository.impl.TestRepositoryImpl.submitTestResult.<no name provided>' type=com.example.datn.data.repository.impl.TestRepositoryImpl origin=null
                                  receiver: GET_VAR '<this>: com.example.datn.data.repository.impl.TestRepositoryImpl.submitTestResult.<no name provided> declared in com.example.datn.data.repository.impl.TestRepositoryImpl.submitTestResult.<no name provided>.invokeSuspend' type=com.example.datn.data.repository.impl.TestRepositoryImpl.submitTestResult.<no name provided> origin=null
                              entity: CALL 'public final fun toEntity (): com.example.datn.data.local.entities.StudentTestResultEntity declared in com.example.datn.data.mapper.StudentTestResultMapperKt' type=com.example.datn.data.local.entities.StudentTestResultEntity origin=null
                                $receiver: GET_VAR 'val saved: com.example.datn.domain.models.StudentTestResult [val] declared in com.example.datn.data.repository.impl.TestRepositoryImpl.submitTestResult.<no name provided>.invokeSuspend' type=com.example.datn.domain.models.StudentTestResult origin=null
                              $completion: GET_VAR '<this>: com.example.datn.data.repository.impl.TestRepositoryImpl.submitTestResult.<no name provided> declared in com.example.datn.data.repository.impl.TestRepositoryImpl.submitTestResult.<no name provided>.invokeSuspend' type=com.example.datn.data.repository.impl.TestRepositoryImpl.submitTestResult.<no name provided> origin=null
                            COMPOSITE type=kotlin.Unit origin=null
                              TRY type=kotlin.Int
                                try: BLOCK type=kotlin.Int origin=null
                                  VAR name:questions type:kotlin.collections.List<com.example.datn.data.local.entities.TestQuestionEntity> [val]
                                    CALL 'public abstract fun getQuestionsByTest (testId: kotlin.String, $completion: kotlin.coroutines.Continuation<kotlin.collections.List<com.example.datn.data.local.entities.TestQuestionEntity>>): kotlin.Any? [suspend] declared in com.example.datn.data.local.dao.TestQuestionDao' type=kotlin.collections.List<com.example.datn.data.local.entities.TestQuestionEntity> origin=null
                                      $this: CALL 'public final fun access$getTestQuestionDao$p ($this: com.example.datn.data.repository.impl.TestRepositoryImpl): com.example.datn.data.local.dao.TestQuestionDao declared in com.example.datn.data.repository.impl.TestRepositoryImpl' type=com.example.datn.data.local.dao.TestQuestionDao origin=null
                                        $this: GET_FIELD 'FIELD FIELD_FOR_CAPTURED_VALUE name:this$0 type:com.example.datn.data.repository.impl.TestRepositoryImpl visibility:public/*package*/ [final] declared in com.example.datn.data.repository.impl.TestRepositoryImpl.submitTestResult.<no name provided>' type=com.example.datn.data.repository.impl.TestRepositoryImpl origin=null
                                          receiver: GET_VAR '<this>: com.example.datn.data.repository.impl.TestRepositoryImpl.submitTestResult.<no name provided> declared in com.example.datn.data.repository.impl.TestRepositoryImpl.submitTestResult.<no name provided>.invokeSuspend' type=com.example.datn.data.repository.impl.TestRepositoryImpl.submitTestResult.<no name provided> origin=null
                                      testId: CALL 'public final fun <get-testId> (): kotlin.String declared in com.example.datn.domain.models.StudentTestResult' type=kotlin.String origin=GET_PROPERTY
                                        $this: GET_VAR 'val saved: com.example.datn.domain.models.StudentTestResult [val] declared in com.example.datn.data.repository.impl.TestRepositoryImpl.submitTestResult.<no name provided>.invokeSuspend' type=com.example.datn.domain.models.StudentTestResult origin=null
                                      $completion: GET_VAR '<this>: com.example.datn.data.repository.impl.TestRepositoryImpl.submitTestResult.<no name provided> declared in com.example.datn.data.repository.impl.TestRepositoryImpl.submitTestResult.<no name provided>.invokeSuspend' type=com.example.datn.data.repository.impl.TestRepositoryImpl.submitTestResult.<no name provided> origin=null
                                  VAR name:studentAnswers type:kotlin.collections.MutableList<com.example.datn.domain.models.StudentTestAnswer> [val]
                                    CALL 'public final fun mutableListOf <T> (): kotlin.collections.MutableList<T of kotlin.collections.CollectionsKt.mutableListOf> [inline] declared in kotlin.collections.CollectionsKt' type=kotlin.collections.MutableList<com.example.datn.domain.models.StudentTestAnswer> origin=null
                                      <T>: com.example.datn.domain.models.StudentTestAnswer
                                  CALL 'public final fun forEach <T> (action: kotlin.Function1<T of kotlin.collections.CollectionsKt.forEach, kotlin.Unit>): kotlin.Unit [inline] declared in kotlin.collections.CollectionsKt' type=kotlin.Unit origin=null
                                    <T>: com.example.datn.data.local.entities.TestQuestionEntity
                                    $receiver: GET_VAR 'val questions: kotlin.collections.List<com.example.datn.data.local.entities.TestQuestionEntity> [val] declared in com.example.datn.data.repository.impl.TestRepositoryImpl.submitTestResult.<no name provided>.invokeSuspend' type=kotlin.collections.List<com.example.datn.data.local.entities.TestQuestionEntity> origin=null
                                    action: BLOCK type=kotlin.Function1<com.example.datn.data.local.entities.TestQuestionEntity, kotlin.Unit> origin=LAMBDA
                                      COMPOSITE type=kotlin.Unit origin=null
                                      FUNCTION_REFERENCE 'private final fun invokeSuspend$lambda$1 ($answers: kotlin.collections.Map<kotlin.String, kotlin.Any>, this$0: com.example.datn.data.repository.impl.TestRepositoryImpl, $saved: com.example.datn.domain.models.StudentTestResult, $studentAnswers: kotlin.collections.MutableList<com.example.datn.domain.models.StudentTestAnswer>, questionEntity: com.example.datn.data.local.entities.TestQuestionEntity): kotlin.Unit declared in com.example.datn.data.repository.impl.TestRepositoryImpl.submitTestResult.<no name provided>' type=kotlin.Function1<com.example.datn.data.local.entities.TestQuestionEntity, kotlin.Unit> origin=INLINE_LAMBDA reflectionTarget=null
                                        $answers: GET_FIELD 'FIELD FIELD_FOR_CAPTURED_VALUE name:$answers type:kotlin.collections.Map<kotlin.String, kotlin.Any> visibility:public/*package*/ [final] declared in com.example.datn.data.repository.impl.TestRepositoryImpl.submitTestResult.<no name provided>' type=kotlin.collections.Map<kotlin.String, kotlin.Any> origin=null
                                          receiver: GET_VAR '<this>: com.example.datn.data.repository.impl.TestRepositoryImpl.submitTestResult.<no name provided> declared in com.example.datn.data.repository.impl.TestRepositoryImpl.submitTestResult.<no name provided>.invokeSuspend' type=com.example.datn.data.repository.impl.TestRepositoryImpl.submitTestResult.<no name provided> origin=null
                                        this$0: GET_FIELD 'FIELD FIELD_FOR_CAPTURED_VALUE name:this$0 type:com.example.datn.data.repository.impl.TestRepositoryImpl visibility:public/*package*/ [final] declared in com.example.datn.data.repository.impl.TestRepositoryImpl.submitTestResult.<no name provided>' type=com.example.datn.data.repository.impl.TestRepositoryImpl origin=null
                                          receiver: GET_VAR '<this>: com.example.datn.data.repository.impl.TestRepositoryImpl.submitTestResult.<no name provided> declared in com.example.datn.data.repository.impl.TestRepositoryImpl.submitTestResult.<no name provided>.invokeSuspend' type=com.example.datn.data.repository.impl.TestRepositoryImpl.submitTestResult.<no name provided> origin=null
                                        $saved: GET_VAR 'val saved: com.example.datn.domain.models.StudentTestResult [val] declared in com.example.datn.data.repository.impl.TestRepositoryImpl.submitTestResult.<no name provided>.invokeSuspend' type=com.example.datn.domain.models.StudentTestResult origin=null
                                        $studentAnswers: GET_VAR 'val studentAnswers: kotlin.collections.MutableList<com.example.datn.domain.models.StudentTestAnswer> [val] declared in com.example.datn.data.repository.impl.TestRepositoryImpl.submitTestResult.<no name provided>.invokeSuspend' type=kotlin.collections.MutableList<com.example.datn.domain.models.StudentTestAnswer> origin=null
                                  CALL 'public abstract fun insertAll (answers: kotlin.collections.List<com.example.datn.data.local.entities.StudentTestAnswerEntity>, $completion: kotlin.coroutines.Continuation<kotlin.Unit>): kotlin.Any? [suspend] declared in com.example.datn.data.local.dao.StudentTestAnswerDao' type=kotlin.Unit origin=null
                                    $this: CALL 'public final fun access$getStudentTestAnswerDao$p ($this: com.example.datn.data.repository.impl.TestRepositoryImpl): com.example.datn.data.local.dao.StudentTestAnswerDao declared in com.example.datn.data.repository.impl.TestRepositoryImpl' type=com.example.datn.data.local.dao.StudentTestAnswerDao origin=null
                                      $this: GET_FIELD 'FIELD FIELD_FOR_CAPTURED_VALUE name:this$0 type:com.example.datn.data.repository.impl.TestRepositoryImpl visibility:public/*package*/ [final] declared in com.example.datn.data.repository.impl.TestRepositoryImpl.submitTestResult.<no name provided>' type=com.example.datn.data.repository.impl.TestRepositoryImpl origin=null
                                        receiver: GET_VAR '<this>: com.example.datn.data.repository.impl.TestRepositoryImpl.submitTestResult.<no name provided> declared in com.example.datn.data.repository.impl.TestRepositoryImpl.submitTestResult.<no name provided>.invokeSuspend' type=com.example.datn.data.repository.impl.TestRepositoryImpl.submitTestResult.<no name provided> origin=null
                                    answers: CALL 'public final fun map <T, R> (transform: kotlin.Function1<T of kotlin.collections.CollectionsKt.map, R of kotlin.collections.CollectionsKt.map>): kotlin.collections.List<R of kotlin.collections.CollectionsKt.map> [inline] declared in kotlin.collections.CollectionsKt' type=kotlin.collections.List<com.example.datn.data.local.entities.StudentTestAnswerEntity> origin=null
                                      <T>: com.example.datn.domain.models.StudentTestAnswer
                                      <R>: com.example.datn.data.local.entities.StudentTestAnswerEntity
                                      $receiver: GET_VAR 'val studentAnswers: kotlin.collections.MutableList<com.example.datn.domain.models.StudentTestAnswer> [val] declared in com.example.datn.data.repository.impl.TestRepositoryImpl.submitTestResult.<no name provided>.invokeSuspend' type=kotlin.collections.MutableList<com.example.datn.domain.models.StudentTestAnswer> origin=null
                                      transform: BLOCK type=kotlin.Function1<com.example.datn.domain.models.StudentTestAnswer, com.example.datn.data.local.entities.StudentTestAnswerEntity> origin=LAMBDA
                                        COMPOSITE type=kotlin.Unit origin=null
                                        FUNCTION_REFERENCE 'private final fun invokeSuspend$lambda$2 (it: com.example.datn.domain.models.StudentTestAnswer): com.example.datn.data.local.entities.StudentTestAnswerEntity declared in com.example.datn.data.repository.impl.TestRepositoryImpl.submitTestResult.<no name provided>' type=kotlin.Function1<com.example.datn.domain.models.StudentTestAnswer, com.example.datn.data.local.entities.StudentTestAnswerEntity> origin=INLINE_LAMBDA reflectionTarget=null
                                    $completion: GET_VAR '<this>: com.example.datn.data.repository.impl.TestRepositoryImpl.submitTestResult.<no name provided> declared in com.example.datn.data.repository.impl.TestRepositoryImpl.submitTestResult.<no name provided>.invokeSuspend' type=com.example.datn.data.repository.impl.TestRepositoryImpl.submitTestResult.<no name provided> origin=null
                                  TRY type=kotlin.Int
                                    try: BLOCK type=kotlin.Int origin=null
                                      COMPOSITE type=kotlin.Unit origin=null
                                        CALL 'public final fun saveStudentAnswers (answers: kotlin.collections.List<com.example.datn.domain.models.StudentTestAnswer>, $completion: kotlin.coroutines.Continuation<com.example.datn.core.utils.Resource<kotlin.Boolean>>): kotlin.Any? [suspend] declared in com.example.datn.data.remote.datasource.FirebaseDataSource' type=com.example.datn.core.utils.Resource<kotlin.Boolean> origin=null
                                          $this: CALL 'public final fun access$getFirebaseDataSource$p ($this: com.example.datn.data.repository.impl.TestRepositoryImpl): com.example.datn.data.remote.datasource.FirebaseDataSource declared in com.example.datn.data.repository.impl.TestRepositoryImpl' type=com.example.datn.data.remote.datasource.FirebaseDataSource origin=null
                                            $this: GET_FIELD 'FIELD FIELD_FOR_CAPTURED_VALUE name:this$0 type:com.example.datn.data.repository.impl.TestRepositoryImpl visibility:public/*package*/ [final] declared in com.example.datn.data.repository.impl.TestRepositoryImpl.submitTestResult.<no name provided>' type=com.example.datn.data.repository.impl.TestRepositoryImpl origin=null
                                              receiver: GET_VAR '<this>: com.example.datn.data.repository.impl.TestRepositoryImpl.submitTestResult.<no name provided> declared in com.example.datn.data.repository.impl.TestRepositoryImpl.submitTestResult.<no name provided>.invokeSuspend' type=com.example.datn.data.repository.impl.TestRepositoryImpl.submitTestResult.<no name provided> origin=null
                                          answers: GET_VAR 'val studentAnswers: kotlin.collections.MutableList<com.example.datn.domain.models.StudentTestAnswer> [val] declared in com.example.datn.data.repository.impl.TestRepositoryImpl.submitTestResult.<no name provided>.invokeSuspend' type=kotlin.collections.MutableList<com.example.datn.domain.models.StudentTestAnswer> origin=null
                                          $completion: GET_VAR '<this>: com.example.datn.data.repository.impl.TestRepositoryImpl.submitTestResult.<no name provided> declared in com.example.datn.data.repository.impl.TestRepositoryImpl.submitTestResult.<no name provided>.invokeSuspend' type=com.example.datn.data.repository.impl.TestRepositoryImpl.submitTestResult.<no name provided> origin=null
                                        COMPOSITE type=kotlin.Unit origin=null
                                      CALL 'public open fun d (p0: @[EnhancedNullability] kotlin.String?, p1: @[EnhancedNullability] kotlin.String): kotlin.Int declared in android.util.Log' type=kotlin.Int origin=null
                                        p0: CONST String type=kotlin.String value="TestRepository"
                                        p1: STRING_CONCATENATION type=kotlin.String
                                          CONST String type=kotlin.String value="Synced "
                                          CALL 'public abstract fun <get-size> (): kotlin.Int [fake_override] declared in kotlin.collections.MutableList' type=kotlin.Int origin=GET_PROPERTY
                                            $this: GET_VAR 'val studentAnswers: kotlin.collections.MutableList<com.example.datn.domain.models.StudentTestAnswer> [val] declared in com.example.datn.data.repository.impl.TestRepositoryImpl.submitTestResult.<no name provided>.invokeSuspend' type=kotlin.collections.MutableList<com.example.datn.domain.models.StudentTestAnswer> origin=null
                                          CONST String type=kotlin.String value=" answers to Firebase"
                                    CATCH parameter=val e: java.lang.Exception [val] declared in com.example.datn.data.repository.impl.TestRepositoryImpl.submitTestResult.<no name provided>.invokeSuspend
                                      VAR CATCH_PARAMETER name:e type:java.lang.Exception [val]
                                      BLOCK type=kotlin.Int origin=null
                                        CALL 'public open fun e (p0: @[EnhancedNullability] kotlin.String?, p1: @[EnhancedNullability] kotlin.String): kotlin.Int declared in android.util.Log' type=kotlin.Int origin=null
                                          p0: CONST String type=kotlin.String value="TestRepository"
                                          p1: STRING_CONCATENATION type=kotlin.String
                                            CONST String type=kotlin.String value="Error syncing to Firebase: "
                                            CALL 'public open fun <get-message> (): kotlin.String? [fake_override] declared in java.lang.Exception' type=kotlin.String? origin=GET_PROPERTY
                                              $this: GET_VAR 'val e: java.lang.Exception [val] declared in com.example.datn.data.repository.impl.TestRepositoryImpl.submitTestResult.<no name provided>.invokeSuspend' type=java.lang.Exception origin=null
                                CATCH parameter=val e: java.lang.Exception [val] declared in com.example.datn.data.repository.impl.TestRepositoryImpl.submitTestResult.<no name provided>.invokeSuspend
                                  VAR CATCH_PARAMETER name:e type:java.lang.Exception [val]
                                  BLOCK type=kotlin.Int origin=null
                                    CALL 'public open fun e (p0: @[EnhancedNullability] kotlin.String?, p1: @[EnhancedNullability] kotlin.String): kotlin.Int declared in android.util.Log' type=kotlin.Int origin=null
                                      p0: CONST String type=kotlin.String value="TestRepository"
                                      p1: STRING_CONCATENATION type=kotlin.String
                                        CONST String type=kotlin.String value="Error saving answers: "
                                        CALL 'public open fun <get-message> (): kotlin.String? [fake_override] declared in java.lang.Exception' type=kotlin.String? origin=GET_PROPERTY
                                          $this: GET_VAR 'val e: java.lang.Exception [val] declared in com.example.datn.data.repository.impl.TestRepositoryImpl.submitTestResult.<no name provided>.invokeSuspend' type=java.lang.Exception origin=null
                              COMPOSITE type=kotlin.Unit origin=null
                            CALL 'public abstract fun emit (value: T of kotlinx.coroutines.flow.FlowCollector, $completion: kotlin.coroutines.Continuation<kotlin.Unit>): kotlin.Any? [suspend] declared in kotlinx.coroutines.flow.FlowCollector' type=kotlin.Unit origin=null
                              $this: GET_VAR 'val $this$flow: kotlinx.coroutines.flow.FlowCollector<com.example.datn.core.utils.Resource<com.example.datn.domain.models.StudentTestResult>> [val] declared in com.example.datn.data.repository.impl.TestRepositoryImpl.submitTestResult.<no name provided>.invokeSuspend' type=kotlinx.coroutines.flow.FlowCollector<com.example.datn.core.utils.Resource<com.example.datn.domain.models.StudentTestResult>> origin=null
                              value: CONSTRUCTOR_CALL 'public constructor <init> (data: T of com.example.datn.core.utils.Resource.Success) [primary] declared in com.example.datn.core.utils.Resource.Success' type=com.example.datn.core.utils.Resource.Success<com.example.datn.domain.models.StudentTestResult> origin=null
                                <class: T>: com.example.datn.domain.models.StudentTestResult
                                data: GET_VAR 'val saved: com.example.datn.domain.models.StudentTestResult [val] declared in com.example.datn.data.repository.impl.TestRepositoryImpl.submitTestResult.<no name provided>.invokeSuspend' type=com.example.datn.domain.models.StudentTestResult origin=null
                              $completion: GET_VAR '<this>: com.example.datn.data.repository.impl.TestRepositoryImpl.submitTestResult.<no name provided> declared in com.example.datn.data.repository.impl.TestRepositoryImpl.submitTestResult.<no name provided>.invokeSuspend' type=com.example.datn.data.repository.impl.TestRepositoryImpl.submitTestResult.<no name provided> origin=null
                        BRANCH
                          if: TYPE_OP type=kotlin.Boolean origin=INSTANCEOF typeOperand=com.example.datn.core.utils.Resource.Error<com.example.datn.domain.models.StudentTestResult?>
                            GET_VAR 'val remote: com.example.datn.core.utils.Resource<com.example.datn.domain.models.StudentTestResult?> [val] declared in com.example.datn.data.repository.impl.TestRepositoryImpl.submitTestResult.<no name provided>.invokeSuspend' type=com.example.datn.core.utils.Resource<com.example.datn.domain.models.StudentTestResult?> origin=null
                          then: CALL 'public abstract fun emit (value: T of kotlinx.coroutines.flow.FlowCollector, $completion: kotlin.coroutines.Continuation<kotlin.Unit>): kotlin.Any? [suspend] declared in kotlinx.coroutines.flow.FlowCollector' type=kotlin.Unit origin=null
                            $this: GET_VAR 'val $this$flow: kotlinx.coroutines.flow.FlowCollector<com.example.datn.core.utils.Resource<com.example.datn.domain.models.StudentTestResult>> [val] declared in com.example.datn.data.repository.impl.TestRepositoryImpl.submitTestResult.<no name provided>.invokeSuspend' type=kotlinx.coroutines.flow.FlowCollector<com.example.datn.core.utils.Resource<com.example.datn.domain.models.StudentTestResult>> origin=null
                            value: CONSTRUCTOR_CALL 'public constructor <init> (message: kotlin.String) [primary] declared in com.example.datn.core.utils.Resource.Error' type=com.example.datn.core.utils.Resource.Error<com.example.datn.domain.models.StudentTestResult> origin=null
                              <class: T>: com.example.datn.domain.models.StudentTestResult
                              message: CALL 'public final fun <get-message> (): kotlin.String declared in com.example.datn.core.utils.Resource.Error' type=kotlin.String origin=GET_PROPERTY
                                $this: TYPE_OP type=com.example.datn.core.utils.Resource.Error<com.example.datn.domain.models.StudentTestResult?> origin=IMPLICIT_CAST typeOperand=com.example.datn.core.utils.Resource.Error<com.example.datn.domain.models.StudentTestResult?>
                                  GET_VAR 'val remote: com.example.datn.core.utils.Resource<com.example.datn.domain.models.StudentTestResult?> [val] declared in com.example.datn.data.repository.impl.TestRepositoryImpl.submitTestResult.<no name provided>.invokeSuspend' type=com.example.datn.core.utils.Resource<com.example.datn.domain.models.StudentTestResult?> origin=null
                            $completion: GET_VAR '<this>: com.example.datn.data.repository.impl.TestRepositoryImpl.submitTestResult.<no name provided> declared in com.example.datn.data.repository.impl.TestRepositoryImpl.submitTestResult.<no name provided>.invokeSuspend' type=com.example.datn.data.repository.impl.TestRepositoryImpl.submitTestResult.<no name provided> origin=null
                        BRANCH
                          if: TYPE_OP type=kotlin.Boolean origin=INSTANCEOF typeOperand=com.example.datn.core.utils.Resource.Loading<com.example.datn.domain.models.StudentTestResult?>
                            GET_VAR 'val remote: com.example.datn.core.utils.Resource<com.example.datn.domain.models.StudentTestResult?> [val] declared in com.example.datn.data.repository.impl.TestRepositoryImpl.submitTestResult.<no name provided>.invokeSuspend' type=com.example.datn.core.utils.Resource<com.example.datn.domain.models.StudentTestResult?> origin=null
                          then: CALL 'public abstract fun emit (value: T of kotlinx.coroutines.flow.FlowCollector, $completion: kotlin.coroutines.Continuation<kotlin.Unit>): kotlin.Any? [suspend] declared in kotlinx.coroutines.flow.FlowCollector' type=kotlin.Unit origin=null
                            $this: GET_VAR 'val $this$flow: kotlinx.coroutines.flow.FlowCollector<com.example.datn.core.utils.Resource<com.example.datn.domain.models.StudentTestResult>> [val] declared in com.example.datn.data.repository.impl.TestRepositoryImpl.submitTestResult.<no name provided>.invokeSuspend' type=kotlinx.coroutines.flow.FlowCollector<com.example.datn.core.utils.Resource<com.example.datn.domain.models.StudentTestResult>> origin=null
                            value: CONSTRUCTOR_CALL 'public constructor <init> () [primary] declared in com.example.datn.core.utils.Resource.Loading' type=com.example.datn.core.utils.Resource.Loading<com.example.datn.domain.models.StudentTestResult> origin=null
                              <class: T>: com.example.datn.domain.models.StudentTestResult
                            $completion: GET_VAR '<this>: com.example.datn.data.repository.impl.TestRepositoryImpl.submitTestResult.<no name provided> declared in com.example.datn.data.repository.impl.TestRepositoryImpl.submitTestResult.<no name provided>.invokeSuspend' type=com.example.datn.data.repository.impl.TestRepositoryImpl.submitTestResult.<no name provided> origin=null
                        BRANCH
                          if: CONST Boolean type=kotlin.Boolean value=true
                          then: BLOCK type=kotlin.Nothing origin=null
                            CALL 'public final fun noWhenBranchMatchedException (): kotlin.Nothing declared in kotlin.internal.ir' type=kotlin.Nothing origin=null
                            CALL 'public final fun throwKotlinNothingValueException (): kotlin.Nothing declared in kotlin.jvm.internal.Intrinsics' type=kotlin.Nothing origin=null
                  CATCH parameter=val e: java.lang.Exception [val] declared in com.example.datn.data.repository.impl.TestRepositoryImpl.submitTestResult.<no name provided>.invokeSuspend
                    VAR CATCH_PARAMETER name:e type:java.lang.Exception [val]
                    BLOCK type=kotlin.Unit origin=null
                      CALL 'public abstract fun emit (value: T of kotlinx.coroutines.flow.FlowCollector, $completion: kotlin.coroutines.Continuation<kotlin.Unit>): kotlin.Any? [suspend] declared in kotlinx.coroutines.flow.FlowCollector' type=kotlin.Unit origin=null
                        $this: GET_VAR 'val $this$flow: kotlinx.coroutines.flow.FlowCollector<com.example.datn.core.utils.Resource<com.example.datn.domain.models.StudentTestResult>> [val] declared in com.example.datn.data.repository.impl.TestRepositoryImpl.submitTestResult.<no name provided>.invokeSuspend' type=kotlinx.coroutines.flow.FlowCollector<com.example.datn.core.utils.Resource<com.example.datn.domain.models.StudentTestResult>> origin=null
                        value: CONSTRUCTOR_CALL 'public constructor <init> (message: kotlin.String) [primary] declared in com.example.datn.core.utils.Resource.Error' type=com.example.datn.core.utils.Resource.Error<com.example.datn.domain.models.StudentTestResult> origin=null
                          <class: T>: com.example.datn.domain.models.StudentTestResult
                          message: STRING_CONCATENATION type=kotlin.String
                            CONST String type=kotlin.String value="Li khi np bi kim tra: "
                            CALL 'public open fun <get-message> (): kotlin.String? [fake_override] declared in java.lang.Exception' type=kotlin.String? origin=GET_PROPERTY
                              $this: GET_VAR 'val e: java.lang.Exception [val] declared in com.example.datn.data.repository.impl.TestRepositoryImpl.submitTestResult.<no name provided>.invokeSuspend' type=java.lang.Exception origin=null
                        $completion: GET_VAR '<this>: com.example.datn.data.repository.impl.TestRepositoryImpl.submitTestResult.<no name provided> declared in com.example.datn.data.repository.impl.TestRepositoryImpl.submitTestResult.<no name provided>.invokeSuspend' type=com.example.datn.data.repository.impl.TestRepositoryImpl.submitTestResult.<no name provided> origin=null
            FUN name:create visibility:public modality:FINAL <> ($this:com.example.datn.data.repository.impl.TestRepositoryImpl.submitTestResult.<no name provided>, value:kotlin.Any?, $completion:kotlin.coroutines.Continuation<kotlin.Nothing>) returnType:kotlin.coroutines.Continuation<kotlin.Unit>
              overridden:
                public open fun create (value: kotlin.Any?, $completion: kotlin.coroutines.Continuation<kotlin.Nothing>): kotlin.coroutines.Continuation<kotlin.Unit> declared in kotlin.coroutines.jvm.internal.SuspendLambda
              $this: VALUE_PARAMETER INSTANCE_RECEIVER name:<this> type:com.example.datn.data.repository.impl.TestRepositoryImpl.submitTestResult.<no name provided>
              VALUE_PARAMETER name:value index:0 type:kotlin.Any?
              VALUE_PARAMETER name:$completion index:1 type:kotlin.coroutines.Continuation<kotlin.Nothing>
              BLOCK_BODY
                VAR IR_TEMPORARY_VARIABLE name:tmp0_result type:com.example.datn.data.repository.impl.TestRepositoryImpl.submitTestResult.<no name provided> [val]
                  CONSTRUCTOR_CALL 'public/*package*/ constructor <init> ($result: com.example.datn.domain.models.StudentTestResult, this$0: com.example.datn.data.repository.impl.TestRepositoryImpl, $answers: kotlin.collections.Map<kotlin.String, kotlin.Any>, $completion: kotlin.coroutines.Continuation<com.example.datn.data.repository.impl.TestRepositoryImpl.submitTestResult.<no name provided>>?) [primary] declared in com.example.datn.data.repository.impl.TestRepositoryImpl.submitTestResult.<no name provided>' type=com.example.datn.data.repository.impl.TestRepositoryImpl.submitTestResult.<no name provided> origin=null
                    $result: GET_FIELD 'FIELD FIELD_FOR_CAPTURED_VALUE name:$result type:com.example.datn.domain.models.StudentTestResult visibility:public/*package*/ [final] declared in com.example.datn.data.repository.impl.TestRepositoryImpl.submitTestResult.<no name provided>' type=com.example.datn.domain.models.StudentTestResult origin=null
                      receiver: GET_VAR '<this>: com.example.datn.data.repository.impl.TestRepositoryImpl.submitTestResult.<no name provided> declared in com.example.datn.data.repository.impl.TestRepositoryImpl.submitTestResult.<no name provided>.create' type=com.example.datn.data.repository.impl.TestRepositoryImpl.submitTestResult.<no name provided> origin=null
                    this$0: GET_FIELD 'FIELD FIELD_FOR_CAPTURED_VALUE name:this$0 type:com.example.datn.data.repository.impl.TestRepositoryImpl visibility:public/*package*/ [final] declared in com.example.datn.data.repository.impl.TestRepositoryImpl.submitTestResult.<no name provided>' type=com.example.datn.data.repository.impl.TestRepositoryImpl origin=null
                      receiver: GET_VAR '<this>: com.example.datn.data.repository.impl.TestRepositoryImpl.submitTestResult.<no name provided> declared in com.example.datn.data.repository.impl.TestRepositoryImpl.submitTestResult.<no name provided>.create' type=com.example.datn.data.repository.impl.TestRepositoryImpl.submitTestResult.<no name provided> origin=null
                    $answers: GET_FIELD 'FIELD FIELD_FOR_CAPTURED_VALUE name:$answers type:kotlin.collections.Map<kotlin.String, kotlin.Any> visibility:public/*package*/ [final] declared in com.example.datn.data.repository.impl.TestRepositoryImpl.submitTestResult.<no name provided>' type=kotlin.collections.Map<kotlin.String, kotlin.Any> origin=null
                      receiver: GET_VAR '<this>: com.example.datn.data.repository.impl.TestRepositoryImpl.submitTestResult.<no name provided> declared in com.example.datn.data.repository.impl.TestRepositoryImpl.submitTestResult.<no name provided>.create' type=com.example.datn.data.repository.impl.TestRepositoryImpl.submitTestResult.<no name provided> origin=null
                    $completion: GET_VAR '$completion: kotlin.coroutines.Continuation<kotlin.Nothing> declared in com.example.datn.data.repository.impl.TestRepositoryImpl.submitTestResult.<no name provided>.create' type=kotlin.coroutines.Continuation<kotlin.Nothing> origin=null
                SET_FIELD 'FIELD FIELD_FOR_CAPTURED_VALUE name:L$0 type:kotlin.Any? visibility:private declared in com.example.datn.data.repository.impl.TestRepositoryImpl.submitTestResult.<no name provided>' type=kotlin.Unit origin=null
                  receiver: GET_VAR 'val tmp0_result: com.example.datn.data.repository.impl.TestRepositoryImpl.submitTestResult.<no name provided> [val] declared in com.example.datn.data.repository.impl.TestRepositoryImpl.submitTestResult.<no name provided>.create' type=com.example.datn.data.repository.impl.TestRepositoryImpl.submitTestResult.<no name provided> origin=null
                  value: GET_VAR 'value: kotlin.Any? declared in com.example.datn.data.repository.impl.TestRepositoryImpl.submitTestResult.<no name provided>.create' type=kotlin.Any? origin=null
                RETURN type=kotlin.Nothing from='public final fun create (value: kotlin.Any?, $completion: kotlin.coroutines.Continuation<kotlin.Nothing>): kotlin.coroutines.Continuation<kotlin.Unit> declared in com.example.datn.data.repository.impl.TestRepositoryImpl.submitTestResult.<no name provided>'
                  GET_VAR 'val tmp0_result: com.example.datn.data.repository.impl.TestRepositoryImpl.submitTestResult.<no name provided> [val] declared in com.example.datn.data.repository.impl.TestRepositoryImpl.submitTestResult.<no name provided>.create' type=com.example.datn.data.repository.impl.TestRepositoryImpl.submitTestResult.<no name provided> origin=null
            FUN name:invoke visibility:public modality:FINAL <> ($this:com.example.datn.data.repository.impl.TestRepositoryImpl.submitTestResult.<no name provided>, p1:kotlinx.coroutines.flow.FlowCollector<com.example.datn.core.utils.Resource<com.example.datn.domain.models.StudentTestResult>>, p2:kotlin.coroutines.Continuation<kotlin.Unit>?) returnType:kotlin.Any?
              overridden:
                public abstract fun invoke (p1: P1 of kotlin.jvm.functions.Function2, p2: P2 of kotlin.jvm.functions.Function2): R of kotlin.jvm.functions.Function2 declared in kotlin.jvm.functions.Function2
              $this: VALUE_PARAMETER INSTANCE_RECEIVER name:<this> type:com.example.datn.data.repository.impl.TestRepositoryImpl.submitTestResult.<no name provided>
              VALUE_PARAMETER name:p1 index:0 type:kotlinx.coroutines.flow.FlowCollector<com.example.datn.core.utils.Resource<com.example.datn.domain.models.StudentTestResult>>
              VALUE_PARAMETER name:p2 index:1 type:kotlin.coroutines.Continuation<kotlin.Unit>?
              BLOCK_BODY
                RETURN type=kotlin.Nothing from='public final fun invoke (p1: kotlinx.coroutines.flow.FlowCollector<com.example.datn.core.utils.Resource<com.example.datn.domain.models.StudentTestResult>>, p2: kotlin.coroutines.Continuation<kotlin.Unit>?): kotlin.Any? declared in com.example.datn.data.repository.impl.TestRepositoryImpl.submitTestResult.<no name provided>'
                  CALL 'public final fun invokeSuspend ($result: kotlin.Result<kotlin.Any?>): kotlin.Any? declared in com.example.datn.data.repository.impl.TestRepositoryImpl.submitTestResult.<no name provided>' type=kotlin.Any? origin=null
                    $this: TYPE_OP type=com.example.datn.data.repository.impl.TestRepositoryImpl.submitTestResult.<no name provided> origin=IMPLICIT_CAST typeOperand=com.example.datn.data.repository.impl.TestRepositoryImpl.submitTestResult.<no name provided>
                      CALL 'public final fun create (value: kotlin.Any?, $completion: kotlin.coroutines.Continuation<kotlin.Nothing>): kotlin.coroutines.Continuation<kotlin.Unit> declared in com.example.datn.data.repository.impl.TestRepositoryImpl.submitTestResult.<no name provided>' type=kotlin.coroutines.Continuation<kotlin.Unit> origin=null
                        $this: GET_VAR '<this>: com.example.datn.data.repository.impl.TestRepositoryImpl.submitTestResult.<no name provided> declared in com.example.datn.data.repository.impl.TestRepositoryImpl.submitTestResult.<no name provided>.invoke' type=com.example.datn.data.repository.impl.TestRepositoryImpl.submitTestResult.<no name provided> origin=null
                        value: GET_VAR 'p1: kotlinx.coroutines.flow.FlowCollector<com.example.datn.core.utils.Resource<com.example.datn.domain.models.StudentTestResult>> declared in com.example.datn.data.repository.impl.TestRepositoryImpl.submitTestResult.<no name provided>.invoke' type=kotlinx.coroutines.flow.FlowCollector<com.example.datn.core.utils.Resource<com.example.datn.domain.models.StudentTestResult>> origin=null
                        $completion: GET_VAR 'p2: kotlin.coroutines.Continuation<kotlin.Unit>? declared in com.example.datn.data.repository.impl.TestRepositoryImpl.submitTestResult.<no name provided>.invoke' type=kotlin.coroutines.Continuation<kotlin.Unit>? origin=null
                    $result: CALL 'public final fun <unsafe-coerce> <T, R> (v: T of kotlin.jvm.internal.<unsafe-coerce>): R of kotlin.jvm.internal.<unsafe-coerce> declared in kotlin.jvm.internal' type=kotlin.Result<kotlin.Any?> origin=null
                      <T>: kotlin.Any?
                      <R>: kotlin.Result<kotlin.Any?>
                      v: GET_FIELD 'FIELD FIELD_FOR_OBJECT_INSTANCE name:INSTANCE type:kotlin.Unit visibility:public [final,static] declared in kotlin.Unit' type=kotlin.Unit origin=null
            FIELD FIELD_FOR_CAPTURED_VALUE name:$result type:com.example.datn.domain.models.StudentTestResult visibility:public/*package*/ [final]
            FIELD FIELD_FOR_CAPTURED_VALUE name:this$0 type:com.example.datn.data.repository.impl.TestRepositoryImpl visibility:public/*package*/ [final]
            FIELD FIELD_FOR_CAPTURED_VALUE name:$answers type:kotlin.collections.Map<kotlin.String, kotlin.Any> visibility:public/*package*/ [final]
            FUN INLINE_LAMBDA name:invokeSuspend$lambda$1$lambda$0 visibility:private modality:FINAL <> (optionEntity:com.example.datn.data.local.entities.TestOptionEntity) returnType:com.example.datn.domain.models.TestOption
              VALUE_PARAMETER name:optionEntity index:0 type:com.example.datn.data.local.entities.TestOptionEntity
              BLOCK_BODY
                VAR name:$i$a$-map-TestRepositoryImpl$submitTestResult$1$1$options$1 type:kotlin.Int [val]
                  CONST Int type=kotlin.Int value=0
                RETURN type=kotlin.Nothing from='private final fun invokeSuspend$lambda$1$lambda$0 (optionEntity: com.example.datn.data.local.entities.TestOptionEntity): com.example.datn.domain.models.TestOption declared in com.example.datn.data.repository.impl.TestRepositoryImpl.submitTestResult.<no name provided>'
                  CALL 'public final fun toDomain (): com.example.datn.domain.models.TestOption declared in com.example.datn.data.mapper.TestOptionMapperKt' type=com.example.datn.domain.models.TestOption origin=null
                    $receiver: GET_VAR 'optionEntity: com.example.datn.data.local.entities.TestOptionEntity declared in com.example.datn.data.repository.impl.TestRepositoryImpl.submitTestResult.<no name provided>.invokeSuspend$lambda$1$lambda$0' type=com.example.datn.data.local.entities.TestOptionEntity origin=null
            FUN INLINE_LAMBDA name:invokeSuspend$lambda$1 visibility:private modality:FINAL <> ($answers:kotlin.collections.Map<kotlin.String, kotlin.Any>, this$0:com.example.datn.data.repository.impl.TestRepositoryImpl, $saved:com.example.datn.domain.models.StudentTestResult, $studentAnswers:kotlin.collections.MutableList<com.example.datn.domain.models.StudentTestAnswer>, questionEntity:com.example.datn.data.local.entities.TestQuestionEntity) returnType:kotlin.Unit
              VALUE_PARAMETER BOUND_VALUE_PARAMETER name:$answers index:0 type:kotlin.collections.Map<kotlin.String, kotlin.Any>
              VALUE_PARAMETER BOUND_VALUE_PARAMETER name:this$0 index:1 type:com.example.datn.data.repository.impl.TestRepositoryImpl
              VALUE_PARAMETER BOUND_VALUE_PARAMETER name:$saved index:2 type:com.example.datn.domain.models.StudentTestResult
              VALUE_PARAMETER BOUND_VALUE_PARAMETER name:$studentAnswers index:3 type:kotlin.collections.MutableList<com.example.datn.domain.models.StudentTestAnswer>
              VALUE_PARAMETER name:questionEntity index:4 type:com.example.datn.data.local.entities.TestQuestionEntity
              BLOCK_BODY
                VAR name:$i$a$-forEach-TestRepositoryImpl$submitTestResult$1$1 type:kotlin.Int [val]
                  CONST Int type=kotlin.Int value=0
                VAR name:question type:com.example.datn.domain.models.TestQuestion [val]
                  CALL 'public final fun toDomain (): com.example.datn.domain.models.TestQuestion declared in com.example.datn.data.mapper.TestQuestionMapperKt' type=com.example.datn.domain.models.TestQuestion origin=null
                    $receiver: GET_VAR 'questionEntity: com.example.datn.data.local.entities.TestQuestionEntity declared in com.example.datn.data.repository.impl.TestRepositoryImpl.submitTestResult.<no name provided>.invokeSuspend$lambda$1' type=com.example.datn.data.local.entities.TestQuestionEntity origin=null
                VAR name:answerValue type:kotlin.Any? [val]
                  CALL 'public abstract fun get (key: K of kotlin.collections.Map): V of kotlin.collections.Map? [operator] declared in kotlin.collections.Map' type=kotlin.Any? origin=GET_ARRAY_ELEMENT
                    $this: GET_VAR '$answers: kotlin.collections.Map<kotlin.String, kotlin.Any> declared in com.example.datn.data.repository.impl.TestRepositoryImpl.submitTestResult.<no name provided>.invokeSuspend$lambda$1' type=kotlin.collections.Map<kotlin.String, kotlin.Any> origin=null
                    key: CALL 'public final fun <get-id> (): kotlin.String declared in com.example.datn.domain.models.TestQuestion' type=kotlin.String origin=GET_PROPERTY
                      $this: GET_VAR 'val question: com.example.datn.domain.models.TestQuestion [val] declared in com.example.datn.data.repository.impl.TestRepositoryImpl.submitTestResult.<no name provided>.invokeSuspend$lambda$1' type=com.example.datn.domain.models.TestQuestion origin=null
                WHEN type=kotlin.Unit origin=IF
                  BRANCH
                    if: CALL 'public final fun not (): kotlin.Boolean [operator] declared in kotlin.Boolean' type=kotlin.Boolean origin=EXCLEQ
                      $this: CALL 'public final fun EQEQ (arg0: kotlin.Any?, arg1: kotlin.Any?): kotlin.Boolean declared in kotlin.internal.ir' type=kotlin.Boolean origin=EXCLEQ
                        arg0: GET_VAR 'val answerValue: kotlin.Any? [val] declared in com.example.datn.data.repository.impl.TestRepositoryImpl.submitTestResult.<no name provided>.invokeSuspend$lambda$1' type=kotlin.Any? origin=null
                        arg1: CONST Null type=kotlin.Nothing? value=null
                    then: COMPOSITE type=kotlin.Unit origin=null
                      BLOCK type=kotlin.Boolean origin=null
                        VAR name:options type:kotlin.collections.List<com.example.datn.domain.models.TestOption> [val]
                          CALL 'public final fun map <T, R> (transform: kotlin.Function1<T of kotlin.collections.CollectionsKt.map, R of kotlin.collections.CollectionsKt.map>): kotlin.collections.List<R of kotlin.collections.CollectionsKt.map> [inline] declared in kotlin.collections.CollectionsKt' type=kotlin.collections.List<com.example.datn.domain.models.TestOption> origin=null
                            <T>: com.example.datn.data.local.entities.TestOptionEntity
                            <R>: com.example.datn.domain.models.TestOption
                            $receiver: CALL 'public abstract fun getOptionsByQuestion (testQuestionId: kotlin.String, $completion: kotlin.coroutines.Continuation<kotlin.collections.List<com.example.datn.data.local.entities.TestOptionEntity>>): kotlin.Any? [suspend] declared in com.example.datn.data.local.dao.TestOptionDao' type=kotlin.collections.List<com.example.datn.data.local.entities.TestOptionEntity> origin=null
                              $this: CALL 'public final fun access$getTestOptionDao$p ($this: com.example.datn.data.repository.impl.TestRepositoryImpl): com.example.datn.data.local.dao.TestOptionDao declared in com.example.datn.data.repository.impl.TestRepositoryImpl' type=com.example.datn.data.local.dao.TestOptionDao origin=null
                                $this: GET_VAR 'this$0: com.example.datn.data.repository.impl.TestRepositoryImpl declared in com.example.datn.data.repository.impl.TestRepositoryImpl.submitTestResult.<no name provided>.invokeSuspend$lambda$1' type=com.example.datn.data.repository.impl.TestRepositoryImpl origin=null
                              testQuestionId: CALL 'public final fun <get-id> (): kotlin.String declared in com.example.datn.domain.models.TestQuestion' type=kotlin.String origin=GET_PROPERTY
                                $this: GET_VAR 'val question: com.example.datn.domain.models.TestQuestion [val] declared in com.example.datn.data.repository.impl.TestRepositoryImpl.submitTestResult.<no name provided>.invokeSuspend$lambda$1' type=com.example.datn.domain.models.TestQuestion origin=null
                              $completion: COMPOSITE type=kotlin.coroutines.Continuation<kotlin.collections.List<com.example.datn.data.local.entities.TestOptionEntity>> origin=FAKE_CONTINUATION
                            transform: BLOCK type=kotlin.Function1<com.example.datn.data.local.entities.TestOptionEntity, com.example.datn.domain.models.TestOption> origin=LAMBDA
                              COMPOSITE type=kotlin.Unit origin=null
                              FUNCTION_REFERENCE 'private final fun invokeSuspend$lambda$1$lambda$0 (optionEntity: com.example.datn.data.local.entities.TestOptionEntity): com.example.datn.domain.models.TestOption declared in com.example.datn.data.repository.impl.TestRepositoryImpl.submitTestResult.<no name provided>' type=kotlin.Function1<com.example.datn.data.local.entities.TestOptionEntity, com.example.datn.domain.models.TestOption> origin=INLINE_LAMBDA reflectionTarget=null
                        VAR IR_TEMPORARY_VARIABLE name:<destruct> type:kotlin.Pair<kotlin.Boolean, kotlin.Double> [val]
                          CALL 'public final fun access$gradeAnswer ($this: com.example.datn.data.repository.impl.TestRepositoryImpl, question: com.example.datn.domain.models.TestQuestion, options: kotlin.collections.List<com.example.datn.domain.models.TestOption>, answer: kotlin.Any): kotlin.Pair<kotlin.Boolean, kotlin.Double> declared in com.example.datn.data.repository.impl.TestRepositoryImpl' type=kotlin.Pair<kotlin.Boolean, kotlin.Double> origin=null
                            $this: GET_VAR 'this$0: com.example.datn.data.repository.impl.TestRepositoryImpl declared in com.example.datn.data.repository.impl.TestRepositoryImpl.submitTestResult.<no name provided>.invokeSuspend$lambda$1' type=com.example.datn.data.repository.impl.TestRepositoryImpl origin=null
                            question: GET_VAR 'val question: com.example.datn.domain.models.TestQuestion [val] declared in com.example.datn.data.repository.impl.TestRepositoryImpl.submitTestResult.<no name provided>.invokeSuspend$lambda$1' type=com.example.datn.domain.models.TestQuestion origin=null
                            options: GET_VAR 'val options: kotlin.collections.List<com.example.datn.domain.models.TestOption> [val] declared in com.example.datn.data.repository.impl.TestRepositoryImpl.submitTestResult.<no name provided>.invokeSuspend$lambda$1' type=kotlin.collections.List<com.example.datn.domain.models.TestOption> origin=null
                            answer: GET_VAR 'val answerValue: kotlin.Any? [val] declared in com.example.datn.data.repository.impl.TestRepositoryImpl.submitTestResult.<no name provided>.invokeSuspend$lambda$1' type=kotlin.Any? origin=null
                        VAR name:isCorrect type:kotlin.Boolean [val]
                          CALL 'public final fun component1 (): A of kotlin.Pair [operator] declared in kotlin.Pair' type=kotlin.Boolean origin=COMPONENT_N(index=1)
                            $this: GET_VAR 'val <destruct>: kotlin.Pair<kotlin.Boolean, kotlin.Double> [val] declared in com.example.datn.data.repository.impl.TestRepositoryImpl.submitTestResult.<no name provided>.invokeSuspend$lambda$1' type=kotlin.Pair<kotlin.Boolean, kotlin.Double> origin=null
                        VAR name:earnedScore type:kotlin.Double [val]
                          CALL 'public final fun component2 (): B of kotlin.Pair [operator] declared in kotlin.Pair' type=kotlin.Double origin=COMPONENT_N(index=2)
                            $this: GET_VAR 'val <destruct>: kotlin.Pair<kotlin.Boolean, kotlin.Double> [val] declared in com.example.datn.data.repository.impl.TestRepositoryImpl.submitTestResult.<no name provided>.invokeSuspend$lambda$1' type=kotlin.Pair<kotlin.Boolean, kotlin.Double> origin=null
                        VAR name:answerString type:kotlin.String [val]
                          BLOCK type=kotlin.String origin=WHEN
                            VAR IR_TEMPORARY_VARIABLE name:tmp0_subject type:kotlin.Any? [val]
                              GET_VAR 'val answerValue: kotlin.Any? [val] declared in com.example.datn.data.repository.impl.TestRepositoryImpl.submitTestResult.<no name provided>.invokeSuspend$lambda$1' type=kotlin.Any? origin=null
                            WHEN type=kotlin.String origin=WHEN
                              BRANCH
                                if: TYPE_OP type=kotlin.Boolean origin=INSTANCEOF typeOperand=kotlin.String
                                  GET_VAR 'val tmp0_subject: kotlin.Any? [val] declared in com.example.datn.data.repository.impl.TestRepositoryImpl.submitTestResult.<no name provided>.invokeSuspend$lambda$1' type=kotlin.Any? origin=null
                                then: TYPE_OP type=kotlin.String origin=IMPLICIT_CAST typeOperand=kotlin.String
                                  GET_VAR 'val answerValue: kotlin.Any? [val] declared in com.example.datn.data.repository.impl.TestRepositoryImpl.submitTestResult.<no name provided>.invokeSuspend$lambda$1' type=kotlin.Any? origin=null
                              BRANCH
                                if: TYPE_OP type=kotlin.Boolean origin=INSTANCEOF typeOperand=kotlin.collections.List<*>
                                  GET_VAR 'val tmp0_subject: kotlin.Any? [val] declared in com.example.datn.data.repository.impl.TestRepositoryImpl.submitTestResult.<no name provided>.invokeSuspend$lambda$1' type=kotlin.Any? origin=null
                                then: CALL 'public final fun joinToString$default <T> (separator: kotlin.CharSequence?, prefix: kotlin.CharSequence?, postfix: kotlin.CharSequence?, limit: kotlin.Int, truncated: kotlin.CharSequence?, transform: kotlin.Function1<T of kotlin.collections.CollectionsKt.joinToString$default, kotlin.CharSequence>?, $mask0: kotlin.Int, $handler: kotlin.Any?): kotlin.String declared in kotlin.collections.CollectionsKt' type=kotlin.String origin=DEFAULT_DISPATCH_CALL
                                  <T>: kotlin.Any?
                                  $receiver: TYPE_OP type=kotlin.collections.List<*> origin=IMPLICIT_CAST typeOperand=kotlin.collections.List<*>
                                    GET_VAR 'val answerValue: kotlin.Any? [val] declared in com.example.datn.data.repository.impl.TestRepositoryImpl.submitTestResult.<no name provided>.invokeSuspend$lambda$1' type=kotlin.Any? origin=null
                                  separator: CONST String type=kotlin.String value=","
                                  prefix: COMPOSITE type=kotlin.CharSequence? origin=DEFAULT_VALUE
                                    CONST Null type=kotlin.CharSequence? value=null
                                  postfix: COMPOSITE type=kotlin.CharSequence? origin=DEFAULT_VALUE
                                    CONST Null type=kotlin.CharSequence? value=null
                                  limit: COMPOSITE type=kotlin.Int origin=DEFAULT_VALUE
                                    CONST Int type=kotlin.Int value=0
                                  truncated: COMPOSITE type=kotlin.CharSequence? origin=DEFAULT_VALUE
                                    CONST Null type=kotlin.CharSequence? value=null
                                  transform: COMPOSITE type=kotlin.Function1<T of kotlin.collections.CollectionsKt.joinToString$default, kotlin.CharSequence>? origin=DEFAULT_VALUE
                                    CONST Null type=kotlin.Function1<T of kotlin.collections.CollectionsKt.joinToString$default, kotlin.CharSequence>? value=null
                                  $mask0: CONST Int type=kotlin.Int value=62
                                  $handler: CONST Null type=kotlin.Any? value=null
                              BRANCH
                                if: CONST Boolean type=kotlin.Boolean value=true
                                then: CALL 'public open fun toString (): kotlin.String declared in kotlin.Any' type=kotlin.String origin=null
                                  $this: GET_VAR 'val answerValue: kotlin.Any? [val] declared in com.example.datn.data.repository.impl.TestRepositoryImpl.submitTestResult.<no name provided>.invokeSuspend$lambda$1' type=kotlin.Any? origin=null
                        VAR name:studentAnswer type:com.example.datn.domain.models.StudentTestAnswer [val]
                          CONSTRUCTOR_CALL 'public constructor <init> (id: kotlin.String, resultId: kotlin.String, questionId: kotlin.String, answer: kotlin.String, isCorrect: kotlin.Boolean, earnedScore: kotlin.Double, createdAt: java.time.Instant, updatedAt: java.time.Instant) [primary] declared in com.example.datn.domain.models.StudentTestAnswer' type=com.example.datn.domain.models.StudentTestAnswer origin=null
                            id: BLOCK type=kotlin.String origin=null
                              VAR IR_TEMPORARY_VARIABLE name:tmp0 type:kotlin.Any? [val]
                                CALL 'public open fun toString (): @[EnhancedNullability] kotlin.String declared in java.util.UUID' type=@[EnhancedNullability] kotlin.String origin=null
                                  $this: CALL 'public open fun randomUUID (): @[FlexibleNullability] java.util.UUID? declared in java.util.UUID' type=@[FlexibleNullability] java.util.UUID? origin=null
                              CALL 'public final fun checkNotNullExpressionValue (value: kotlin.Any?, expression: kotlin.String): kotlin.Unit declared in kotlin.jvm.internal.Intrinsics' type=kotlin.Unit origin=null
                                value: GET_VAR 'val tmp0: kotlin.Any? [val] declared in com.example.datn.data.repository.impl.TestRepositoryImpl.submitTestResult.<no name provided>.invokeSuspend$lambda$1' type=kotlin.Any? origin=null
                                expression: CONST String type=kotlin.String value="toString(...)"
                              GET_VAR 'val tmp0: kotlin.Any? [val] declared in com.example.datn.data.repository.impl.TestRepositoryImpl.submitTestResult.<no name provided>.invokeSuspend$lambda$1' type=kotlin.Any? origin=null
                            resultId: CALL 'public final fun <get-id> (): kotlin.String declared in com.example.datn.domain.models.StudentTestResult' type=kotlin.String origin=GET_PROPERTY
                              $this: GET_VAR '$saved: com.example.datn.domain.models.StudentTestResult declared in com.example.datn.data.repository.impl.TestRepositoryImpl.submitTestResult.<no name provided>.invokeSuspend$lambda$1' type=com.example.datn.domain.models.StudentTestResult origin=null
                            questionId: CALL 'public final fun <get-id> (): kotlin.String declared in com.example.datn.domain.models.TestQuestion' type=kotlin.String origin=GET_PROPERTY
                              $this: GET_VAR 'val question: com.example.datn.domain.models.TestQuestion [val] declared in com.example.datn.data.repository.impl.TestRepositoryImpl.submitTestResult.<no name provided>.invokeSuspend$lambda$1' type=com.example.datn.domain.models.TestQuestion origin=null
                            answer: GET_VAR 'val answerString: kotlin.String [val] declared in com.example.datn.data.repository.impl.TestRepositoryImpl.submitTestResult.<no name provided>.invokeSuspend$lambda$1' type=kotlin.String origin=null
                            isCorrect: GET_VAR 'val isCorrect: kotlin.Boolean [val] declared in com.example.datn.data.repository.impl.TestRepositoryImpl.submitTestResult.<no name provided>.invokeSuspend$lambda$1' type=kotlin.Boolean origin=null
                            earnedScore: GET_VAR 'val earnedScore: kotlin.Double [val] declared in com.example.datn.data.repository.impl.TestRepositoryImpl.submitTestResult.<no name provided>.invokeSuspend$lambda$1' type=kotlin.Double origin=null
                            createdAt: BLOCK type=java.time.Instant origin=null
                              VAR IR_TEMPORARY_VARIABLE name:tmp1 type:kotlin.Any? [val]
                                CALL 'public open fun now (): @[FlexibleNullability] java.time.Instant? declared in java.time.Instant' type=@[FlexibleNullability] java.time.Instant? origin=null
                              CALL 'public final fun checkNotNullExpressionValue (value: kotlin.Any?, expression: kotlin.String): kotlin.Unit declared in kotlin.jvm.internal.Intrinsics' type=kotlin.Unit origin=null
                                value: GET_VAR 'val tmp1: kotlin.Any? [val] declared in com.example.datn.data.repository.impl.TestRepositoryImpl.submitTestResult.<no name provided>.invokeSuspend$lambda$1' type=kotlin.Any? origin=null
                                expression: CONST String type=kotlin.String value="now(...)"
                              GET_VAR 'val tmp1: kotlin.Any? [val] declared in com.example.datn.data.repository.impl.TestRepositoryImpl.submitTestResult.<no name provided>.invokeSuspend$lambda$1' type=kotlin.Any? origin=null
                            updatedAt: BLOCK type=java.time.Instant origin=null
                              VAR IR_TEMPORARY_VARIABLE name:tmp2 type:kotlin.Any? [val]
                                CALL 'public open fun now (): @[FlexibleNullability] java.time.Instant? declared in java.time.Instant' type=@[FlexibleNullability] java.time.Instant? origin=null
                              CALL 'public final fun checkNotNullExpressionValue (value: kotlin.Any?, expression: kotlin.String): kotlin.Unit declared in kotlin.jvm.internal.Intrinsics' type=kotlin.Unit origin=null
                                value: GET_VAR 'val tmp2: kotlin.Any? [val] declared in com.example.datn.data.repository.impl.TestRepositoryImpl.submitTestResult.<no name provided>.invokeSuspend$lambda$1' type=kotlin.Any? origin=null
                                expression: CONST String type=kotlin.String value="now(...)"
                              GET_VAR 'val tmp2: kotlin.Any? [val] declared in com.example.datn.data.repository.impl.TestRepositoryImpl.submitTestResult.<no name provided>.invokeSuspend$lambda$1' type=kotlin.Any? origin=null
                        COMPOSITE type=kotlin.Unit origin=null
                          CALL 'public open fun d (p0: @[EnhancedNullability] kotlin.String?, p1: @[EnhancedNullability] kotlin.String): kotlin.Int declared in android.util.Log' type=kotlin.Int origin=null
                            p0: CONST String type=kotlin.String value="TestRepository"
                            p1: CALL 'public final fun trimIndent (): kotlin.String declared in kotlin.text.StringsKt' type=kotlin.String origin=null
                              $receiver: STRING_CONCATENATION type=kotlin.String
                                CONST String type=kotlin.String value="\n                                    [SAVE ANSWER]\n                                    Question: "
                                CALL 'public final fun <get-content> (): kotlin.String declared in com.example.datn.domain.models.TestQuestion' type=kotlin.String origin=GET_PROPERTY
                                  $this: GET_VAR 'val question: com.example.datn.domain.models.TestQuestion [val] declared in com.example.datn.data.repository.impl.TestRepositoryImpl.submitTestResult.<no name provided>.invokeSuspend$lambda$1' type=com.example.datn.domain.models.TestQuestion origin=null
                                CONST String type=kotlin.String value="\n                                    AnswerString: "
                                GET_VAR 'val answerString: kotlin.String [val] declared in com.example.datn.data.repository.impl.TestRepositoryImpl.submitTestResult.<no name provided>.invokeSuspend$lambda$1' type=kotlin.String origin=null
                                CONST String type=kotlin.String value="\n                                    isCorrect: "
                                GET_VAR 'val isCorrect: kotlin.Boolean [val] declared in com.example.datn.data.repository.impl.TestRepositoryImpl.submitTestResult.<no name provided>.invokeSuspend$lambda$1' type=kotlin.Boolean origin=null
                                CONST String type=kotlin.String value="\n                                    earnedScore: "
                                GET_VAR 'val earnedScore: kotlin.Double [val] declared in com.example.datn.data.repository.impl.TestRepositoryImpl.submitTestResult.<no name provided>.invokeSuspend$lambda$1' type=kotlin.Double origin=null
                                CONST String type=kotlin.String value="\n                                "
                          COMPOSITE type=kotlin.Unit origin=null
                        CALL 'public abstract fun add (element: E of kotlin.collections.MutableList): kotlin.Boolean declared in kotlin.collections.MutableList' type=kotlin.Boolean origin=null
                          $this: GET_VAR '$studentAnswers: kotlin.collections.MutableList<com.example.datn.domain.models.StudentTestAnswer> declared in com.example.datn.data.repository.impl.TestRepositoryImpl.submitTestResult.<no name provided>.invokeSuspend$lambda$1' type=kotlin.collections.MutableList<com.example.datn.domain.models.StudentTestAnswer> origin=null
                          element: GET_VAR 'val studentAnswer: com.example.datn.domain.models.StudentTestAnswer [val] declared in com.example.datn.data.repository.impl.TestRepositoryImpl.submitTestResult.<no name provided>.invokeSuspend$lambda$1' type=com.example.datn.domain.models.StudentTestAnswer origin=null
                      COMPOSITE type=kotlin.Unit origin=null
            FUN INLINE_LAMBDA name:invokeSuspend$lambda$2 visibility:private modality:FINAL <> (it:com.example.datn.domain.models.StudentTestAnswer) returnType:com.example.datn.data.local.entities.StudentTestAnswerEntity
              VALUE_PARAMETER name:it index:0 type:com.example.datn.domain.models.StudentTestAnswer
              BLOCK_BODY
                VAR name:$i$a$-map-TestRepositoryImpl$submitTestResult$1$2 type:kotlin.Int [val]
                  CONST Int type=kotlin.Int value=0
                RETURN type=kotlin.Nothing from='private final fun invokeSuspend$lambda$2 (it: com.example.datn.domain.models.StudentTestAnswer): com.example.datn.data.local.entities.StudentTestAnswerEntity declared in com.example.datn.data.repository.impl.TestRepositoryImpl.submitTestResult.<no name provided>'
                  CALL 'public final fun toEntity (): com.example.datn.data.local.entities.StudentTestAnswerEntity declared in com.example.datn.data.local.entities.StudentTestAnswerEntityKt' type=com.example.datn.data.local.entities.StudentTestAnswerEntity origin=null
                    $receiver: GET_VAR 'it: com.example.datn.domain.models.StudentTestAnswer declared in com.example.datn.data.repository.impl.TestRepositoryImpl.submitTestResult.<no name provided>.invokeSuspend$lambda$2' type=com.example.datn.domain.models.StudentTestAnswer origin=null
            FUN BRIDGE name:invoke visibility:public modality:OPEN <> ($this:com.example.datn.data.repository.impl.TestRepositoryImpl.submitTestResult.<no name provided>, p1:kotlin.Any?, p2:kotlin.Any?) returnType:kotlin.Any?
              $this: VALUE_PARAMETER INSTANCE_RECEIVER name:<this> type:com.example.datn.data.repository.impl.TestRepositoryImpl.submitTestResult.<no name provided>
              VALUE_PARAMETER BRIDGE name:p1 index:0 type:kotlin.Any?
              VALUE_PARAMETER BRIDGE name:p2 index:1 type:kotlin.Any?
              EXPRESSION_BODY
                RETURN type=kotlin.Nothing from='public open fun invoke (p1: kotlin.Any?, p2: kotlin.Any?): kotlin.Any? declared in com.example.datn.data.repository.impl.TestRepositoryImpl.submitTestResult.<no name provided>'
                  CALL 'public final fun invoke (p1: kotlinx.coroutines.flow.FlowCollector<com.example.datn.core.utils.Resource<com.example.datn.domain.models.StudentTestResult>>, p2: kotlin.coroutines.Continuation<kotlin.Unit>?): kotlin.Any? declared in com.example.datn.data.repository.impl.TestRepositoryImpl.submitTestResult.<no name provided>' type=kotlin.Any? origin=BRIDGE_DELEGATION
                    $this: GET_VAR '<this>: com.example.datn.data.repository.impl.TestRepositoryImpl.submitTestResult.<no name provided> declared in com.example.datn.data.repository.impl.TestRepositoryImpl.submitTestResult.<no name provided>.invoke' type=com.example.datn.data.repository.impl.TestRepositoryImpl.submitTestResult.<no name provided> origin=null
                    p1: TYPE_OP type=kotlinx.coroutines.flow.FlowCollector<*> origin=IMPLICIT_CAST typeOperand=kotlinx.coroutines.flow.FlowCollector<*>
                      GET_VAR 'p1: kotlin.Any? declared in com.example.datn.data.repository.impl.TestRepositoryImpl.submitTestResult.<no name provided>.invoke' type=kotlin.Any? origin=null
                    p2: TYPE_OP type=kotlin.coroutines.Continuation<*> origin=IMPLICIT_CAST typeOperand=kotlin.coroutines.Continuation<*>
                      GET_VAR 'p2: kotlin.Any? declared in com.example.datn.data.repository.impl.TestRepositoryImpl.submitTestResult.<no name provided>.invoke' type=kotlin.Any? origin=null
          CONSTRUCTOR_CALL 'public/*package*/ constructor <init> ($result: com.example.datn.domain.models.StudentTestResult, this$0: com.example.datn.data.repository.impl.TestRepositoryImpl, $answers: kotlin.collections.Map<kotlin.String, kotlin.Any>, $completion: kotlin.coroutines.Continuation<com.example.datn.data.repository.impl.TestRepositoryImpl.submitTestResult.<no name provided>>?) [primary] declared in com.example.datn.data.repository.impl.TestRepositoryImpl.submitTestResult.<no name provided>' type=com.example.datn.data.repository.impl.TestRepositoryImpl.submitTestResult.<no name provided> origin=null
            $result: GET_VAR 'result: com.example.datn.domain.models.StudentTestResult declared in com.example.datn.data.repository.impl.TestRepositoryImpl.submitTestResult' type=com.example.datn.domain.models.StudentTestResult origin=null
            this$0: GET_VAR '<this>: com.example.datn.data.repository.impl.TestRepositoryImpl declared in com.example.datn.data.repository.impl.TestRepositoryImpl.submitTestResult' type=com.example.datn.data.repository.impl.TestRepositoryImpl origin=null
            $answers: GET_VAR 'answers: kotlin.collections.Map<kotlin.String, kotlin.Any> declared in com.example.datn.data.repository.impl.TestRepositoryImpl.submitTestResult' type=kotlin.collections.Map<kotlin.String, kotlin.Any> origin=null
            $completion: CONST Null type=kotlin.Nothing? value=null

	at org.jetbrains.kotlin.backend.jvm.codegen.FunctionCodegen.generate(FunctionCodegen.kt:47)
	at org.jetbrains.kotlin.backend.jvm.codegen.FunctionCodegen.generate$default(FunctionCodegen.kt:40)
	at org.jetbrains.kotlin.backend.jvm.codegen.ClassCodegen.generateMethodNode(ClassCodegen.kt:406)
	at org.jetbrains.kotlin.backend.jvm.codegen.ClassCodegen.generateMethod(ClassCodegen.kt:423)
	at org.jetbrains.kotlin.backend.jvm.codegen.ClassCodegen.generate(ClassCodegen.kt:168)
	at org.jetbrains.kotlin.backend.jvm.FileCodegen.lower(JvmPhases.kt:39)
	at org.jetbrains.kotlin.backend.common.phaser.PhaseFactoriesKt.createFilePhase$lambda$4(PhaseFactories.kt:71)
	at org.jetbrains.kotlin.backend.common.phaser.PhaseBuildersKt$createSimpleNamedCompilerPhase$1.phaseBody(PhaseBuilders.kt:69)
	at org.jetbrains.kotlin.backend.common.phaser.SimpleNamedCompilerPhase.phaseBody(CompilerPhase.kt:226)
	at org.jetbrains.kotlin.backend.common.phaser.AbstractNamedCompilerPhase.invoke(CompilerPhase.kt:113)
	at org.jetbrains.kotlin.backend.common.phaser.PerformByIrFilePhase.invokeSequential(performByIrFile.kt:62)
	... 43 more
Caused by: org.jetbrains.kotlin.codegen.CompilationException: Back-end (JVM) Internal error: Couldn't transform method node:
invokeSuspend (Ljava/lang/Object;)Ljava/lang/Object;:
    // annotable parameter count: 1 (visible)
    // annotable parameter count: 1 (invisible)
    TRYCATCHBLOCK L0 L1 L2 java/lang/Exception
    TRYCATCHBLOCK L3 L4 L2 java/lang/Exception
    TRYCATCHBLOCK L5 L6 L7 java/lang/Exception
    TRYCATCHBLOCK L8 L9 L7 java/lang/Exception
    TRYCATCHBLOCK L10 L11 L7 java/lang/Exception
    TRYCATCHBLOCK L12 L1 L7 java/lang/Exception
    TRYCATCHBLOCK L3 L13 L7 java/lang/Exception
    TRYCATCHBLOCK L14 L15 L16 java/lang/Exception
    TRYCATCHBLOCK L17 L18 L16 java/lang/Exception
    TRYCATCHBLOCK L19 L20 L16 java/lang/Exception
    TRYCATCHBLOCK L21 L6 L16 java/lang/Exception
    TRYCATCHBLOCK L8 L9 L16 java/lang/Exception
    TRYCATCHBLOCK L10 L11 L16 java/lang/Exception
    TRYCATCHBLOCK L12 L1 L16 java/lang/Exception
    TRYCATCHBLOCK L3 L22 L16 java/lang/Exception
    TRYCATCHBLOCK L23 L24 L16 java/lang/Exception
    TRYCATCHBLOCK L25 L26 L16 java/lang/Exception
    TRYCATCHBLOCK L27 L28 L16 java/lang/Exception
   L29
    INVOKESTATIC kotlin/coroutines/intrinsics/IntrinsicsKt.getCOROUTINE_SUSPENDED ()Ljava/lang/Object;
   L30
    LINENUMBER 252 L30
    ASTORE 35
    ALOAD 0
    GETFIELD com/example/datn/data/repository/impl/TestRepositoryImpl$submitTestResult$1.label : I
    TABLESWITCH
      0: L31
      1: L32
      2: L33
      3: L34
      4: L35
      5: L36
      6: L37
      7: L38
      8: L39
      9: L40
      10: L41
      11: L42
      default: L43
   L31
    ALOAD 1
    INVOKESTATIC kotlin/ResultKt.throwOnFailure (Ljava/lang/Object;)V
   L44
    ALOAD 0
    GETFIELD com/example/datn/data/repository/impl/TestRepositoryImpl$submitTestResult$1.L$0 : Ljava/lang/Object;
    CHECKCAST kotlinx/coroutines/flow/FlowCollector
    ASTORE 2
   L45
   L46
    LINENUMBER 253 L46
   L47
   L14
    NOP
   L48
    LINENUMBER 254 L48
    ALOAD 2
    NEW com/example/datn/core/utils/Resource$Loading
    DUP
    INVOKESPECIAL com/example/datn/core/utils/Resource$Loading.<init> ()V
    ALOAD 0
    CHECKCAST kotlin/coroutines/Continuation
    ALOAD 0
    ALOAD 2
    PUTFIELD com/example/datn/data/repository/impl/TestRepositoryImpl$submitTestResult$1.L$0 : Ljava/lang/Object;
    ALOAD 0
    ICONST_1
    PUTFIELD com/example/datn/data/repository/impl/TestRepositoryImpl$submitTestResult$1.label : I
    INVOKEINTERFACE kotlinx/coroutines/flow/FlowCollector.emit (Ljava/lang/Object;Lkotlin/coroutines/Continuation;)Ljava/lang/Object; (itf)
   L15
    DUP
    ALOAD 35
    IF_ACMPNE L49
   L50
    LINENUMBER 252 L50
    ALOAD 35
    ARETURN
   L32
    ALOAD 0
    GETFIELD com/example/datn/data/repository/impl/TestRepositoryImpl$submitTestResult$1.L$0 : Ljava/lang/Object;
    CHECKCAST kotlinx/coroutines/flow/FlowCollector
    ASTORE 2
   L51
   L17
    NOP
    ALOAD 1
    INVOKESTATIC kotlin/ResultKt.throwOnFailure (Ljava/lang/Object;)V
    ALOAD 1
   L49
    LINENUMBER 255 L49
    POP
   L52
    ALOAD 0
    GETFIELD com/example/datn/data/repository/impl/TestRepositoryImpl$submitTestResult$1.$result : Lcom/example/datn/domain/models/StudentTestResult;
    ACONST_NULL
    ACONST_NULL
    ACONST_NULL
    DCONST_0
    ACONST_NULL
   L53
    LINENUMBER 256 L53
    ALOAD 0
    GETFIELD com/example/datn/data/repository/impl/TestRepositoryImpl$submitTestResult$1.$result : Lcom/example/datn/domain/models/StudentTestResult;
    INVOKEVIRTUAL com/example/datn/domain/models/StudentTestResult.getSubmissionTime ()Ljava/time/Instant;
    INVOKEVIRTUAL java/time/Instant.toEpochMilli ()J
    LCONST_0
    LCMP
    IFNE L54
    INVOKESTATIC java/time/Instant.now ()Ljava/time/Instant;
    GOTO L55
   L54
    ALOAD 0
    GETFIELD com/example/datn/data/repository/impl/TestRepositoryImpl$submitTestResult$1.$result : Lcom/example/datn/domain/models/StudentTestResult;
    INVOKEVIRTUAL com/example/datn/domain/models/StudentTestResult.getSubmissionTime ()Ljava/time/Instant;
   L55
    ASTORE 4
   L56
    ALOAD 4
    INVOKESTATIC kotlin/jvm/internal/Intrinsics.checkNotNull (Ljava/lang/Object;)V
    ALOAD 4
   L57
    CHECKCAST java/time/Instant
   L58
    LINENUMBER 255 L58
    LCONST_0
   L59
    LINENUMBER 257 L59
    ALOAD 0
    GETFIELD com/example/datn/data/repository/impl/TestRepositoryImpl$submitTestResult$1.$result : Lcom/example/datn/domain/models/StudentTestResult;
    INVOKEVIRTUAL com/example/datn/domain/models/StudentTestResult.getCreatedAt ()Ljava/time/Instant;
    INVOKEVIRTUAL java/time/Instant.toEpochMilli ()J
    LCONST_0
    LCMP
    IFNE L60
    INVOKESTATIC java/time/Instant.now ()Ljava/time/Instant;
    GOTO L61
   L60
    ALOAD 0
    GETFIELD com/example/datn/data/repository/impl/TestRepositoryImpl$submitTestResult$1.$result : Lcom/example/datn/domain/models/StudentTestResult;
    INVOKEVIRTUAL com/example/datn/domain/models/StudentTestResult.getCreatedAt ()Ljava/time/Instant;
   L61
    ASTORE 4
   L62
    ALOAD 4
    INVOKESTATIC kotlin/jvm/internal/Intrinsics.checkNotNull (Ljava/lang/Object;)V
    ALOAD 4
   L63
    CHECKCAST java/time/Instant
   L64
    LINENUMBER 258 L64
    INVOKESTATIC java/time/Instant.now ()Ljava/time/Instant;
    ASTORE 4
   L65
    ALOAD 4
    LDC "now(...)"
    INVOKESTATIC kotlin/jvm/internal/Intrinsics.checkNotNullExpressionValue (Ljava/lang/Object;Ljava/lang/String;)V
    ALOAD 4
   L66
    CHECKCAST java/time/Instant
   L67
    LINENUMBER 255 L67
    BIPUSH 95
    ACONST_NULL
    INVOKESTATIC com/example/datn/domain/models/StudentTestResult.copy$default (Lcom/example/datn/domain/models/StudentTestResult;Ljava/lang/String;Ljava/lang/String;Ljava/lang/String;DLcom/example/datn/domain/models/TestStatus;Ljava/time/Instant;JLjava/time/Instant;Ljava/time/Instant;ILjava/lang/Object;)Lcom/example/datn/domain/models/StudentTestResult;
    ASTORE 3
   L68
   L69
    LINENUMBER 260 L69
    ALOAD 0
    GETFIELD com/example/datn/data/repository/impl/TestRepositoryImpl$submitTestResult$1.this$0 : Lcom/example/datn/data/repository/impl/TestRepositoryImpl;
    INVOKESTATIC com/example/datn/data/repository/impl/TestRepositoryImpl.access$getFirebaseDataSource$p (Lcom/example/datn/data/repository/impl/TestRepositoryImpl;)Lcom/example/datn/data/remote/datasource/FirebaseDataSource;
    ALOAD 3
    ALOAD 0
    CHECKCAST kotlin/coroutines/Continuation
    ALOAD 0
    ALOAD 2
    PUTFIELD com/example/datn/data/repository/impl/TestRepositoryImpl$submitTestResult$1.L$0 : Ljava/lang/Object;
    ALOAD 0
    ALOAD 3
    PUTFIELD com/example/datn/data/repository/impl/TestRepositoryImpl$submitTestResult$1.L$1 : Ljava/lang/Object;
    ALOAD 0
    ICONST_2
    PUTFIELD com/example/datn/data/repository/impl/TestRepositoryImpl$submitTestResult$1.label : I
    INVOKEVIRTUAL com/example/datn/data/remote/datasource/FirebaseDataSource.submitTestResult (Lcom/example/datn/domain/models/StudentTestResult;Lkotlin/coroutines/Continuation;)Ljava/lang/Object;
   L18
    DUP
    ALOAD 35
    IF_ACMPNE L70
   L71
    LINENUMBER 252 L71
    ALOAD 35
    ARETURN
   L33
    ALOAD 0
    GETFIELD com/example/datn/data/repository/impl/TestRepositoryImpl$submitTestResult$1.L$1 : Ljava/lang/Object;
    CHECKCAST com/example/datn/domain/models/StudentTestResult
    ASTORE 3
   L72
    ALOAD 0
    GETFIELD com/example/datn/data/repository/impl/TestRepositoryImpl$submitTestResult$1.L$0 : Ljava/lang/Object;
    CHECKCAST kotlinx/coroutines/flow/FlowCollector
    ASTORE 2
   L73
   L19
    NOP
    ALOAD 1
    INVOKESTATIC kotlin/ResultKt.throwOnFailure (Ljava/lang/Object;)V
    ALOAD 1
   L70
    CHECKCAST com/example/datn/core/utils/Resource
    ASTORE 4
   L74
    NOP
   L75
    LINENUMBER 261 L75
    ALOAD 4
    INSTANCEOF com/example/datn/core/utils/Resource$Success
    IFEQ L76
   L77
    LINENUMBER 262 L77
    ALOAD 4
    CHECKCAST com/example/datn/core/utils/Resource$Success
    INVOKEVIRTUAL com/example/datn/core/utils/Resource$Success.getData ()Ljava/lang/Object;
    CHECKCAST com/example/datn/domain/models/StudentTestResult
    ASTORE 6
   L78
    ALOAD 6
    IFNULL L79
    ALOAD 6
    GOTO L80
   L79
    NOP
    ALOAD 3
   L80
   L81
    ASTORE 5
   L82
   L83
    LINENUMBER 263 L83
    ALOAD 0
    GETFIELD com/example/datn/data/repository/impl/TestRepositoryImpl$submitTestResult$1.this$0 : Lcom/example/datn/data/repository/impl/TestRepositoryImpl;
    INVOKESTATIC com/example/datn/data/repository/impl/TestRepositoryImpl.access$getStudentTestResultDao$p (Lcom/example/datn/data/repository/impl/TestRepositoryImpl;)Lcom/example/datn/data/local/dao/StudentTestResultDao;
    ALOAD 5
    INVOKESTATIC com/example/datn/data/mapper/StudentTestResultMapperKt.toEntity (Lcom/example/datn/domain/models/StudentTestResult;)Lcom/example/datn/data/local/entities/StudentTestResultEntity;
    ALOAD 0
    CHECKCAST kotlin/coroutines/Continuation
    ALOAD 0
    ALOAD 2
    PUTFIELD com/example/datn/data/repository/impl/TestRepositoryImpl$submitTestResult$1.L$0 : Ljava/lang/Object;
    ALOAD 0
    ALOAD 5
    PUTFIELD com/example/datn/data/repository/impl/TestRepositoryImpl$submitTestResult$1.L$1 : Ljava/lang/Object;
    ALOAD 0
    ICONST_3
    PUTFIELD com/example/datn/data/repository/impl/TestRepositoryImpl$submitTestResult$1.label : I
    INVOKEINTERFACE com/example/datn/data/local/dao/StudentTestResultDao.insert (Ljava/lang/Object;Lkotlin/coroutines/Continuation;)Ljava/lang/Object; (itf)
   L20
    DUP
    ALOAD 35
    IF_ACMPNE L84
   L85
    LINENUMBER 252 L85
    ALOAD 35
    ARETURN
   L34
    ALOAD 0
    GETFIELD com/example/datn/data/repository/impl/TestRepositoryImpl$submitTestResult$1.L$1 : Ljava/lang/Object;
    CHECKCAST com/example/datn/domain/models/StudentTestResult
    ASTORE 5
   L86
    ALOAD 0
    GETFIELD com/example/datn/data/repository/impl/TestRepositoryImpl$submitTestResult$1.L$0 : Ljava/lang/Object;
    CHECKCAST kotlinx/coroutines/flow/FlowCollector
    ASTORE 2
   L87
   L21
    NOP
    ALOAD 1
    INVOKESTATIC kotlin/ResultKt.throwOnFailure (Ljava/lang/Object;)V
    ALOAD 1
   L84
    LINENUMBER 266 L84
    POP
   L88
   L89
   L5
    NOP
   L90
    LINENUMBER 268 L90
    ALOAD 0
    GETFIELD com/example/datn/data/repository/impl/TestRepositoryImpl$submitTestResult$1.this$0 : Lcom/example/datn/data/repository/impl/TestRepositoryImpl;
    INVOKESTATIC com/example/datn/data/repository/impl/TestRepositoryImpl.access$getTestQuestionDao$p (Lcom/example/datn/data/repository/impl/TestRepositoryImpl;)Lcom/example/datn/data/local/dao/TestQuestionDao;
    ALOAD 5
    INVOKEVIRTUAL com/example/datn/domain/models/StudentTestResult.getTestId ()Ljava/lang/String;
    ALOAD 0
    CHECKCAST kotlin/coroutines/Continuation
    ALOAD 0
    ALOAD 2
    PUTFIELD com/example/datn/data/repository/impl/TestRepositoryImpl$submitTestResult$1.L$0 : Ljava/lang/Object;
    ALOAD 0
    ALOAD 5
    PUTFIELD com/example/datn/data/repository/impl/TestRepositoryImpl$submitTestResult$1.L$1 : Ljava/lang/Object;
    ALOAD 0
    ICONST_4
    PUTFIELD com/example/datn/data/repository/impl/TestRepositoryImpl$submitTestResult$1.label : I
    INVOKEINTERFACE com/example/datn/data/local/dao/TestQuestionDao.getQuestionsByTest (Ljava/lang/String;Lkotlin/coroutines/Continuation;)Ljava/lang/Object; (itf)
   L6
    DUP
    ALOAD 35
    IF_ACMPNE L91
   L92
    LINENUMBER 252 L92
    ALOAD 35
    ARETURN
   L35
    ALOAD 0
    GETFIELD com/example/datn/data/repository/impl/TestRepositoryImpl$submitTestResult$1.L$1 : Ljava/lang/Object;
    CHECKCAST com/example/datn/domain/models/StudentTestResult
    ASTORE 5
   L93
    ALOAD 0
    GETFIELD com/example/datn/data/repository/impl/TestRepositoryImpl$submitTestResult$1.L$0 : Ljava/lang/Object;
    CHECKCAST kotlinx/coroutines/flow/FlowCollector
    ASTORE 2
   L94
   L8
    NOP
    ALOAD 1
    INVOKESTATIC kotlin/ResultKt.throwOnFailure (Ljava/lang/Object;)V
    ALOAD 1
   L91
    CHECKCAST java/util/List
    ASTORE 6
   L95
   L96
    LINENUMBER 269 L96
    NOP
   L97
    NEW java/util/ArrayList
    DUP
    INVOKESPECIAL java/util/ArrayList.<init> ()V
    CHECKCAST java/util/List
    NOP
    GOTO L98
   L99
   L98
   L100
    LINENUMBER 269 L100
    ASTORE 7
   L101
   L102
    LINENUMBER 271 L102
    ALOAD 6
    CHECKCAST java/lang/Iterable
    ASTORE 8
    ALOAD 0
    GETFIELD com/example/datn/data/repository/impl/TestRepositoryImpl$submitTestResult$1.$answers : Ljava/util/Map;
    ASTORE 9
    ALOAD 0
    GETFIELD com/example/datn/data/repository/impl/TestRepositoryImpl$submitTestResult$1.this$0 : Lcom/example/datn/data/repository/impl/TestRepositoryImpl;
    ASTORE 10
    NOP
   L103
    ICONST_0
    ISTORE 11
   L104
    LINENUMBER 662 L104
    ALOAD 8
    INVOKEINTERFACE java/lang/Iterable.iterator ()Ljava/util/Iterator; (itf)
    ASTORE 12
   L105
    ALOAD 12
    INVOKEINTERFACE java/util/Iterator.hasNext ()Z (itf)
    IFEQ L106
    ALOAD 12
    INVOKEINTERFACE java/util/Iterator.next ()Ljava/lang/Object; (itf)
    ASTORE 13
   L107
    ALOAD 13
    CHECKCAST com/example/datn/data/local/entities/TestQuestionEntity
    ASTORE 14
   L108
    ICONST_0
    ISTORE 15
   L109
    LINENUMBER 272 L109
    ALOAD 14
    INVOKESTATIC com/example/datn/data/mapper/TestQuestionMapperKt.toDomain (Lcom/example/datn/data/local/entities/TestQuestionEntity;)Lcom/example/datn/domain/models/TestQuestion;
    ASTORE 16
   L110
    LINENUMBER 273 L110
    ALOAD 9
    ALOAD 16
    INVOKEVIRTUAL com/example/datn/domain/models/TestQuestion.getId ()Ljava/lang/String;
    INVOKEINTERFACE java/util/Map.get (Ljava/lang/Object;)Ljava/lang/Object; (itf)
    ASTORE 17
   L111
    LINENUMBER 275 L111
    ALOAD 17
    IFNULL L112
   L113
    LINENUMBER 277 L113
    ALOAD 10
    INVOKESTATIC com/example/datn/data/repository/impl/TestRepositoryImpl.access$getTestOptionDao$p (Lcom/example/datn/data/repository/impl/TestRepositoryImpl;)Lcom/example/datn/data/local/dao/TestOptionDao;
    ALOAD 16
    INVOKEVIRTUAL com/example/datn/domain/models/TestQuestion.getId ()Ljava/lang/String;
    ALOAD 0
    ALOAD 0
    ALOAD 2
    PUTFIELD com/example/datn/data/repository/impl/TestRepositoryImpl$submitTestResult$1.L$0 : Ljava/lang/Object;
    ALOAD 0
    ALOAD 5
    PUTFIELD com/example/datn/data/repository/impl/TestRepositoryImpl$submitTestResult$1.L$1 : Ljava/lang/Object;
    ALOAD 0
    ALOAD 7
    PUTFIELD com/example/datn/data/repository/impl/TestRepositoryImpl$submitTestResult$1.L$2 : Ljava/lang/Object;
    ALOAD 0
    ALOAD 9
    PUTFIELD com/example/datn/data/repository/impl/TestRepositoryImpl$submitTestResult$1.L$3 : Ljava/lang/Object;
    ALOAD 0
    ALOAD 10
    PUTFIELD com/example/datn/data/repository/impl/TestRepositoryImpl$submitTestResult$1.L$4 : Ljava/lang/Object;
    ALOAD 0
    ALOAD 12
    PUTFIELD com/example/datn/data/repository/impl/TestRepositoryImpl$submitTestResult$1.L$5 : Ljava/lang/Object;
    ALOAD 0
    ALOAD 16
    PUTFIELD com/example/datn/data/repository/impl/TestRepositoryImpl$submitTestResult$1.L$6 : Ljava/lang/Object;
    ALOAD 0
    ALOAD 17
    PUTFIELD com/example/datn/data/repository/impl/TestRepositoryImpl$submitTestResult$1.L$7 : Ljava/lang/Object;
    ALOAD 0
    ICONST_5
    PUTFIELD com/example/datn/data/repository/impl/TestRepositoryImpl$submitTestResult$1.label : I
    INVOKEINTERFACE com/example/datn/data/local/dao/TestOptionDao.getOptionsByQuestion (Ljava/lang/String;Lkotlin/coroutines/Continuation;)Ljava/lang/Object; (itf)
   L9
    DUP
    ALOAD 35
    IF_ACMPNE L114
   L115
    LINENUMBER 252 L115
    ALOAD 35
    ARETURN
   L36
    ICONST_0
    ISTORE 11
   L116
    ICONST_0
    ISTORE 15
   L117
    ALOAD 0
    GETFIELD com/example/datn/data/repository/impl/TestRepositoryImpl$submitTestResult$1.L$7 : Ljava/lang/Object;
    ASTORE 17
   L118
    ALOAD 0
    GETFIELD com/example/datn/data/repository/impl/TestRepositoryImpl$submitTestResult$1.L$6 : Ljava/lang/Object;
    CHECKCAST com/example/datn/domain/models/TestQuestion
    ASTORE 16
   L119
    ALOAD 0
    GETFIELD com/example/datn/data/repository/impl/TestRepositoryImpl$submitTestResult$1.L$5 : Ljava/lang/Object;
    CHECKCAST java/util/Iterator
    ASTORE 12
    ALOAD 0
    GETFIELD com/example/datn/data/repository/impl/TestRepositoryImpl$submitTestResult$1.L$4 : Ljava/lang/Object;
    CHECKCAST com/example/datn/data/repository/impl/TestRepositoryImpl
    ASTORE 10
    ALOAD 0
    GETFIELD com/example/datn/data/repository/impl/TestRepositoryImpl$submitTestResult$1.L$3 : Ljava/lang/Object;
    CHECKCAST java/util/Map
    ASTORE 9
    ALOAD 0
    GETFIELD com/example/datn/data/repository/impl/TestRepositoryImpl$submitTestResult$1.L$2 : Ljava/lang/Object;
    CHECKCAST java/util/List
    ASTORE 7
   L120
    ALOAD 0
    GETFIELD com/example/datn/data/repository/impl/TestRepositoryImpl$submitTestResult$1.L$1 : Ljava/lang/Object;
    CHECKCAST com/example/datn/domain/models/StudentTestResult
    ASTORE 5
   L121
    ALOAD 0
    GETFIELD com/example/datn/data/repository/impl/TestRepositoryImpl$submitTestResult$1.L$0 : Ljava/lang/Object;
    CHECKCAST kotlinx/coroutines/flow/FlowCollector
    ASTORE 2
   L122
   L10
    NOP
    ALOAD 1
    INVOKESTATIC kotlin/ResultKt.throwOnFailure (Ljava/lang/Object;)V
    ALOAD 1
   L114
    CHECKCAST java/lang/Iterable
    ASTORE 18
   L123
    LINENUMBER 278 L123
    NOP
   L124
    ICONST_0
    ISTORE 19
   L125
    LINENUMBER 663 L125
    ALOAD 18
    ASTORE 20
    NEW java/util/ArrayList
    DUP
    ALOAD 18
    BIPUSH 10
    INVOKESTATIC kotlin/collections/CollectionsKt.collectionSizeOrDefault (Ljava/lang/Iterable;I)I
    INVOKESPECIAL java/util/ArrayList.<init> (I)V
    CHECKCAST java/util/Collection
    ASTORE 21
   L126
    ICONST_0
    ISTORE 22
   L127
    LINENUMBER 664 L127
    ALOAD 20
    INVOKEINTERFACE java/lang/Iterable.iterator ()Ljava/util/Iterator; (itf)
    ASTORE 23
   L128
    ALOAD 23
    INVOKEINTERFACE java/util/Iterator.hasNext ()Z (itf)
    IFEQ L129
    ALOAD 23
    INVOKEINTERFACE java/util/Iterator.next ()Ljava/lang/Object; (itf)
    ASTORE 24
   L130
    LINENUMBER 665 L130
    ALOAD 21
    ALOAD 24
    CHECKCAST com/example/datn/data/local/entities/TestOptionEntity
    ASTORE 25
    ASTORE 26
   L131
    ICONST_0
    ISTORE 27
   L132
    LINENUMBER 279 L132
    ALOAD 25
    INVOKESTATIC com/example/datn/data/mapper/TestOptionMapperKt.toDomain (Lcom/example/datn/data/local/entities/TestOptionEntity;)Lcom/example/datn/domain/models/TestOption;
    NOP
    GOTO L133
   L133
    ASTORE 28
    ALOAD 26
    ALOAD 28
   L134
    LINENUMBER 665 L134
    INVOKEINTERFACE java/util/Collection.add (Ljava/lang/Object;)Z (itf)
    POP
   L135
    GOTO L128
   L129
    LINENUMBER 666 L129
    ALOAD 21
   L136
    CHECKCAST java/util/List
   L137
    LINENUMBER 663 L137
    NOP
    GOTO L138
   L138
   L139
    LINENUMBER 278 L139
   L140
    LINENUMBER 277 L140
    ASTORE 29
   L141
    LINENUMBER 283 L141
    ALOAD 10
    ALOAD 16
    ALOAD 29
    ALOAD 17
    INVOKESTATIC com/example/datn/data/repository/impl/TestRepositoryImpl.access$gradeAnswer (Lcom/example/datn/data/repository/impl/TestRepositoryImpl;Lcom/example/datn/domain/models/TestQuestion;Ljava/util/List;Ljava/lang/Object;)Lkotlin/Pair;
    ASTORE 18
   L142
    ALOAD 18
    INVOKEVIRTUAL kotlin/Pair.component1 ()Ljava/lang/Object;
    CHECKCAST java/lang/Boolean
    INVOKEVIRTUAL java/lang/Boolean.booleanValue ()Z
    ISTORE 19
   L143
    ALOAD 18
    INVOKEVIRTUAL kotlin/Pair.component2 ()Ljava/lang/Object;
    CHECKCAST java/lang/Number
    INVOKEVIRTUAL java/lang/Number.doubleValue ()D
    DSTORE 30
   L144
    LINENUMBER 286 L144
    ALOAD 17
    ASTORE 23
   L145
    NOP
   L146
    LINENUMBER 287 L146
    ALOAD 23
    INSTANCEOF java/lang/String
    IFEQ L147
    ALOAD 17
    CHECKCAST java/lang/String
    GOTO L148
   L147
    LINENUMBER 288 L147
    ALOAD 23
    INSTANCEOF java/util/List
    IFEQ L149
    ALOAD 17
    CHECKCAST java/lang/Iterable
    LDC ","
    CHECKCAST java/lang/CharSequence
    ACONST_NULL
    ACONST_NULL
    ICONST_0
    ACONST_NULL
    ACONST_NULL
    BIPUSH 62
    ACONST_NULL
    INVOKESTATIC kotlin/collections/CollectionsKt.joinToString$default (Ljava/lang/Iterable;Ljava/lang/CharSequence;Ljava/lang/CharSequence;Ljava/lang/CharSequence;ILjava/lang/CharSequence;Lkotlin/jvm/functions/Function1;ILjava/lang/Object;)Ljava/lang/String;
    GOTO L148
   L149
    LINENUMBER 289 L149
    ALOAD 17
    INVOKEVIRTUAL java/lang/Object.toString ()Ljava/lang/String;
   L148
    LINENUMBER 286 L148
    ASTORE 22
   L150
    LINENUMBER 293 L150
    NEW com/example/datn/domain/models/StudentTestAnswer
    DUP
   L151
    LINENUMBER 294 L151
    INVOKESTATIC java/util/UUID.randomUUID ()Ljava/util/UUID;
    INVOKEVIRTUAL java/util/UUID.toString ()Ljava/lang/String;
    ASTORE 24
   L152
    ALOAD 24
    LDC "toString(...)"
    INVOKESTATIC kotlin/jvm/internal/Intrinsics.checkNotNullExpressionValue (Ljava/lang/Object;Ljava/lang/String;)V
    ALOAD 24
   L153
    CHECKCAST java/lang/String
   L154
    LINENUMBER 295 L154
    ALOAD 5
    INVOKEVIRTUAL com/example/datn/domain/models/StudentTestResult.getId ()Ljava/lang/String;
   L155
    LINENUMBER 296 L155
    ALOAD 16
    INVOKEVIRTUAL com/example/datn/domain/models/TestQuestion.getId ()Ljava/lang/String;
   L156
    LINENUMBER 297 L156
    ALOAD 22
   L157
    LINENUMBER 298 L157
    ILOAD 19
    IFEQ L158
    ICONST_1
    GOTO L159
   L158
    ICONST_0
   L159
   L160
    LINENUMBER 299 L160
    DLOAD 30
   L161
    LINENUMBER 300 L161
    INVOKESTATIC java/time/Instant.now ()Ljava/time/Instant;
    ASTORE 24
   L162
    ALOAD 24
    LDC "now(...)"
    INVOKESTATIC kotlin/jvm/internal/Intrinsics.checkNotNullExpressionValue (Ljava/lang/Object;Ljava/lang/String;)V
    ALOAD 24
   L163
    CHECKCAST java/time/Instant
   L164
    LINENUMBER 301 L164
    INVOKESTATIC java/time/Instant.now ()Ljava/time/Instant;
    ASTORE 24
   L165
    ALOAD 24
    LDC "now(...)"
    INVOKESTATIC kotlin/jvm/internal/Intrinsics.checkNotNullExpressionValue (Ljava/lang/Object;Ljava/lang/String;)V
    ALOAD 24
   L166
    CHECKCAST java/time/Instant
   L167
    LINENUMBER 293 L167
    INVOKESPECIAL com/example/datn/domain/models/StudentTestAnswer.<init> (Ljava/lang/String;Ljava/lang/String;Ljava/lang/String;Ljava/lang/String;ZDLjava/time/Instant;Ljava/time/Instant;)V
    ASTORE 23
   L168
    LINENUMBER 304 L168
    LDC "TestRepository"
   L169
    LINENUMBER 306 L169
    ALOAD 16
    INVOKEVIRTUAL com/example/datn/domain/models/TestQuestion.getContent ()Ljava/lang/String;
   L170
    LINENUMBER 307 L170
    ALOAD 22
   L171
    LINENUMBER 308 L171
    ILOAD 19
    IFEQ L172
    ICONST_1
    GOTO L173
   L172
    ICONST_0
   L173
   L174
    LINENUMBER 309 L174
    DLOAD 30
    INVOKEDYNAMIC makeConcatWithConstants(Ljava/lang/String;Ljava/lang/String;ZD)Ljava/lang/String; [
      // handle kind 0x6 : INVOKESTATIC
      java/lang/invoke/StringConcatFactory.makeConcatWithConstants(Ljava/lang/invoke/MethodHandles$Lookup;Ljava/lang/String;Ljava/lang/invoke/MethodType;Ljava/lang/String;[Ljava/lang/Object;)Ljava/lang/invoke/CallSite;
      // arguments:
      "\n                                    [SAVE ANSWER]\n                                    Question: \u0001\n                                    AnswerString: \u0001\n                                    isCorrect: \u0001\n                                    earnedScore: \u0001\n                                "
    ]
   L175
    LINENUMBER 310 L175
    INVOKESTATIC kotlin/text/StringsKt.trimIndent (Ljava/lang/String;)Ljava/lang/String;
   L176
    LINENUMBER 304 L176
    INVOKESTATIC android/util/Log.d (Ljava/lang/String;Ljava/lang/String;)I
    POP
   L177
    LINENUMBER 312 L177
    ALOAD 7
    ALOAD 23
    INVOKEINTERFACE java/util/List.add (Ljava/lang/Object;)Z (itf)
   L178
    POP
   L112
    LINENUMBER 314 L112
    NOP
    NOP
    GOTO L179
   L180
   L181
   L179
   L182
    LINENUMBER 662 L182
   L183
    GOTO L105
   L106
    LINENUMBER 667 L106
    NOP
    GOTO L184
   L185
   L186
   L184
   L187
    LINENUMBER 317 L187
    ALOAD 0
    GETFIELD com/example/datn/data/repository/impl/TestRepositoryImpl$submitTestResult$1.this$0 : Lcom/example/datn/data/repository/impl/TestRepositoryImpl;
    INVOKESTATIC com/example/datn/data/repository/impl/TestRepositoryImpl.access$getStudentTestAnswerDao$p (Lcom/example/datn/data/repository/impl/TestRepositoryImpl;)Lcom/example/datn/data/local/dao/StudentTestAnswerDao;
    ALOAD 7
    CHECKCAST java/lang/Iterable
    ASTORE 8
    ASTORE 32
    NOP
   L188
    ICONST_0
    ISTORE 9
   L189
    LINENUMBER 668 L189
    ALOAD 8
    ASTORE 10
    NEW java/util/ArrayList
    DUP
    ALOAD 8
    BIPUSH 10
    INVOKESTATIC kotlin/collections/CollectionsKt.collectionSizeOrDefault (Ljava/lang/Iterable;I)I
    INVOKESPECIAL java/util/ArrayList.<init> (I)V
    CHECKCAST java/util/Collection
    ASTORE 11
   L190
    ICONST_0
    ISTORE 12
   L191
    LINENUMBER 669 L191
    ALOAD 10
    INVOKEINTERFACE java/lang/Iterable.iterator ()Ljava/util/Iterator; (itf)
    ASTORE 13
   L192
    ALOAD 13
    INVOKEINTERFACE java/util/Iterator.hasNext ()Z (itf)
    IFEQ L193
    ALOAD 13
    INVOKEINTERFACE java/util/Iterator.next ()Ljava/lang/Object; (itf)
    ASTORE 14
   L194
    LINENUMBER 670 L194
    ALOAD 11
    ALOAD 14
    CHECKCAST com/example/datn/domain/models/StudentTestAnswer
    ASTORE 15
    ASTORE 33
   L195
    ICONST_0
    ISTORE 16
   L196
    LINENUMBER 317 L196
    ALOAD 15
    INVOKESTATIC com/example/datn/data/local/entities/StudentTestAnswerEntityKt.toEntity (Lcom/example/datn/domain/models/StudentTestAnswer;)Lcom/example/datn/data/local/entities/StudentTestAnswerEntity;
    NOP
    GOTO L197
   L198
   L199
   L197
    ASTORE 34
    ALOAD 33
    ALOAD 34
   L200
    LINENUMBER 670 L200
    INVOKEINTERFACE java/util/Collection.add (Ljava/lang/Object;)Z (itf)
    POP
   L201
    GOTO L192
   L193
    LINENUMBER 671 L193
    ALOAD 11
   L202
    CHECKCAST java/util/List
   L203
    LINENUMBER 668 L203
    NOP
    GOTO L204
   L205
   L206
   L204
    ASTORE 33
    ALOAD 32
    ALOAD 33
    ALOAD 0
    CHECKCAST kotlin/coroutines/Continuation
   L207
    LINENUMBER 317 L207
    ALOAD 0
    ALOAD 2
    PUTFIELD com/example/datn/data/repository/impl/TestRepositoryImpl$submitTestResult$1.L$0 : Ljava/lang/Object;
    ALOAD 0
    ALOAD 5
    PUTFIELD com/example/datn/data/repository/impl/TestRepositoryImpl$submitTestResult$1.L$1 : Ljava/lang/Object;
    ALOAD 0
    ALOAD 7
    PUTFIELD com/example/datn/data/repository/impl/TestRepositoryImpl$submitTestResult$1.L$2 : Ljava/lang/Object;
    ALOAD 0
    ACONST_NULL
    PUTFIELD com/example/datn/data/repository/impl/TestRepositoryImpl$submitTestResult$1.L$3 : Ljava/lang/Object;
    ALOAD 0
    ACONST_NULL
    PUTFIELD com/example/datn/data/repository/impl/TestRepositoryImpl$submitTestResult$1.L$4 : Ljava/lang/Object;
    ALOAD 0
    ACONST_NULL
    PUTFIELD com/example/datn/data/repository/impl/TestRepositoryImpl$submitTestResult$1.L$5 : Ljava/lang/Object;
    ALOAD 0
    ACONST_NULL
    PUTFIELD com/example/datn/data/repository/impl/TestRepositoryImpl$submitTestResult$1.L$6 : Ljava/lang/Object;
    ALOAD 0
    ACONST_NULL
    PUTFIELD com/example/datn/data/repository/impl/TestRepositoryImpl$submitTestResult$1.L$7 : Ljava/lang/Object;
    ALOAD 0
    BIPUSH 6
    PUTFIELD com/example/datn/data/repository/impl/TestRepositoryImpl$submitTestResult$1.label : I
    INVOKEINTERFACE com/example/datn/data/local/dao/StudentTestAnswerDao.insertAll (Ljava/util/List;Lkotlin/coroutines/Continuation;)Ljava/lang/Object; (itf)
   L11
    DUP
    ALOAD 35
    IF_ACMPNE L208
   L209
    LINENUMBER 252 L209
    ALOAD 35
    ARETURN
   L37
    ALOAD 0
    GETFIELD com/example/datn/data/repository/impl/TestRepositoryImpl$submitTestResult$1.L$2 : Ljava/lang/Object;
    CHECKCAST java/util/List
    ASTORE 7
   L210
    ALOAD 0
    GETFIELD com/example/datn/data/repository/impl/TestRepositoryImpl$submitTestResult$1.L$1 : Ljava/lang/Object;
    CHECKCAST com/example/datn/domain/models/StudentTestResult
    ASTORE 5
   L211
    ALOAD 0
    GETFIELD com/example/datn/data/repository/impl/TestRepositoryImpl$submitTestResult$1.L$0 : Ljava/lang/Object;
    CHECKCAST kotlinx/coroutines/flow/FlowCollector
    ASTORE 2
   L212
   L12
    NOP
    ALOAD 1
    INVOKESTATIC kotlin/ResultKt.throwOnFailure (Ljava/lang/Object;)V
    ALOAD 1
   L208
    LINENUMBER 320 L208
    POP
   L213
   L214
   L0
    NOP
   L215
    LINENUMBER 321 L215
    ALOAD 0
    GETFIELD com/example/datn/data/repository/impl/TestRepositoryImpl$submitTestResult$1.this$0 : Lcom/example/datn/data/repository/impl/TestRepositoryImpl;
    INVOKESTATIC com/example/datn/data/repository/impl/TestRepositoryImpl.access$getFirebaseDataSource$p (Lcom/example/datn/data/repository/impl/TestRepositoryImpl;)Lcom/example/datn/data/remote/datasource/FirebaseDataSource;
    ALOAD 7
    ALOAD 0
    CHECKCAST kotlin/coroutines/Continuation
    ALOAD 0
    ALOAD 2
    PUTFIELD com/example/datn/data/repository/impl/TestRepositoryImpl$submitTestResult$1.L$0 : Ljava/lang/Object;
    ALOAD 0
    ALOAD 5
    PUTFIELD com/example/datn/data/repository/impl/TestRepositoryImpl$submitTestResult$1.L$1 : Ljava/lang/Object;
    ALOAD 0
    ALOAD 7
    PUTFIELD com/example/datn/data/repository/impl/TestRepositoryImpl$submitTestResult$1.L$2 : Ljava/lang/Object;
    ALOAD 0
    BIPUSH 7
    PUTFIELD com/example/datn/data/repository/impl/TestRepositoryImpl$submitTestResult$1.label : I
    INVOKEVIRTUAL com/example/datn/data/remote/datasource/FirebaseDataSource.saveStudentAnswers (Ljava/util/List;Lkotlin/coroutines/Continuation;)Ljava/lang/Object;
   L1
    DUP
    ALOAD 35
    IF_ACMPNE L216
   L217
    LINENUMBER 252 L217
    ALOAD 35
    ARETURN
   L38
    ALOAD 0
    GETFIELD com/example/datn/data/repository/impl/TestRepositoryImpl$submitTestResult$1.L$2 : Ljava/lang/Object;
    CHECKCAST java/util/List
    ASTORE 7
   L218
    ALOAD 0
    GETFIELD com/example/datn/data/repository/impl/TestRepositoryImpl$submitTestResult$1.L$1 : Ljava/lang/Object;
    CHECKCAST com/example/datn/domain/models/StudentTestResult
    ASTORE 5
   L219
    ALOAD 0
    GETFIELD com/example/datn/data/repository/impl/TestRepositoryImpl$submitTestResult$1.L$0 : Ljava/lang/Object;
    CHECKCAST kotlinx/coroutines/flow/FlowCollector
    ASTORE 2
   L220
   L3
    NOP
    ALOAD 1
    INVOKESTATIC kotlin/ResultKt.throwOnFailure (Ljava/lang/Object;)V
    ALOAD 1
   L216
    LINENUMBER 322 L216
    POP
   L221
    LDC "TestRepository"
    ALOAD 7
    INVOKEINTERFACE java/util/List.size ()I (itf)
    INVOKEDYNAMIC makeConcatWithConstants(I)Ljava/lang/String; [
      // handle kind 0x6 : INVOKESTATIC
      java/lang/invoke/StringConcatFactory.makeConcatWithConstants(Ljava/lang/invoke/MethodHandles$Lookup;Ljava/lang/String;Ljava/lang/invoke/MethodType;Ljava/lang/String;[Ljava/lang/Object;)Ljava/lang/invoke/CallSite;
      // arguments:
      "Synced \u0001 answers to Firebase"
    ]
    INVOKESTATIC android/util/Log.d (Ljava/lang/String;Ljava/lang/String;)I
    ISTORE 8
   L4
    GOTO L222
   L2
   L223
    LINENUMBER 323 L223
    ASTORE 9
   L224
   L225
    LINENUMBER 324 L225
    LDC "TestRepository"
    ALOAD 9
    INVOKEVIRTUAL java/lang/Exception.getMessage ()Ljava/lang/String;
    INVOKEDYNAMIC makeConcatWithConstants(Ljava/lang/String;)Ljava/lang/String; [
      // handle kind 0x6 : INVOKESTATIC
      java/lang/invoke/StringConcatFactory.makeConcatWithConstants(Ljava/lang/invoke/MethodHandles$Lookup;Ljava/lang/String;Ljava/lang/invoke/MethodType;Ljava/lang/String;[Ljava/lang/Object;)Ljava/lang/invoke/CallSite;
      // arguments:
      "Error syncing to Firebase: \u0001"
    ]
    INVOKESTATIC android/util/Log.e (Ljava/lang/String;Ljava/lang/String;)I
    ISTORE 8
   L226
   L222
    ILOAD 8
   L227
    ISTORE 6
   L13
    GOTO L228
   L7
   L229
    LINENUMBER 327 L229
    ASTORE 7
   L230
   L231
    LINENUMBER 329 L231
    LDC "TestRepository"
    ALOAD 7
    INVOKEVIRTUAL java/lang/Exception.getMessage ()Ljava/lang/String;
    INVOKEDYNAMIC makeConcatWithConstants(Ljava/lang/String;)Ljava/lang/String; [
      // handle kind 0x6 : INVOKESTATIC
      java/lang/invoke/StringConcatFactory.makeConcatWithConstants(Ljava/lang/invoke/MethodHandles$Lookup;Ljava/lang/String;Ljava/lang/invoke/MethodType;Ljava/lang/String;[Ljava/lang/Object;)Ljava/lang/invoke/CallSite;
      // arguments:
      "Error saving answers: \u0001"
    ]
    INVOKESTATIC android/util/Log.e (Ljava/lang/String;Ljava/lang/String;)I
    ISTORE 6
   L232
   L228
   L233
    LINENUMBER 333 L233
    ALOAD 2
    NEW com/example/datn/core/utils/Resource$Success
    DUP
    ALOAD 5
    INVOKESPECIAL com/example/datn/core/utils/Resource$Success.<init> (Ljava/lang/Object;)V
    ALOAD 0
    CHECKCAST kotlin/coroutines/Continuation
    ALOAD 0
    ALOAD 2
    PUTFIELD com/example/datn/data/repository/impl/TestRepositoryImpl$submitTestResult$1.L$0 : Ljava/lang/Object;
    ALOAD 0
    ACONST_NULL
    PUTFIELD com/example/datn/data/repository/impl/TestRepositoryImpl$submitTestResult$1.L$1 : Ljava/lang/Object;
    ALOAD 0
    ACONST_NULL
    PUTFIELD com/example/datn/data/repository/impl/TestRepositoryImpl$submitTestResult$1.L$2 : Ljava/lang/Object;
    ALOAD 0
    ACONST_NULL
    PUTFIELD com/example/datn/data/repository/impl/TestRepositoryImpl$submitTestResult$1.L$3 : Ljava/lang/Object;
    ALOAD 0
    ACONST_NULL
    PUTFIELD com/example/datn/data/repository/impl/TestRepositoryImpl$submitTestResult$1.L$4 : Ljava/lang/Object;
    ALOAD 0
    ACONST_NULL
    PUTFIELD com/example/datn/data/repository/impl/TestRepositoryImpl$submitTestResult$1.L$5 : Ljava/lang/Object;
    ALOAD 0
    ACONST_NULL
    PUTFIELD com/example/datn/data/repository/impl/TestRepositoryImpl$submitTestResult$1.L$6 : Ljava/lang/Object;
    ALOAD 0
    ACONST_NULL
    PUTFIELD com/example/datn/data/repository/impl/TestRepositoryImpl$submitTestResult$1.L$7 : Ljava/lang/Object;
    ALOAD 0
    BIPUSH 8
    PUTFIELD com/example/datn/data/repository/impl/TestRepositoryImpl$submitTestResult$1.label : I
    INVOKEINTERFACE kotlinx/coroutines/flow/FlowCollector.emit (Ljava/lang/Object;Lkotlin/coroutines/Continuation;)Ljava/lang/Object; (itf)
   L22
    DUP
    ALOAD 35
    IF_ACMPNE L234
   L235
    LINENUMBER 252 L235
    ALOAD 35
    ARETURN
   L39
    ALOAD 0
    GETFIELD com/example/datn/data/repository/impl/TestRepositoryImpl$submitTestResult$1.L$0 : Ljava/lang/Object;
    CHECKCAST kotlinx/coroutines/flow/FlowCollector
    ASTORE 2
   L236
   L23
    NOP
    ALOAD 1
    INVOKESTATIC kotlin/ResultKt.throwOnFailure (Ljava/lang/Object;)V
    ALOAD 1
   L234
    LINENUMBER 333 L234
    POP
   L237
    GOTO L238
   L76
   L239
    LINENUMBER 335 L239
    ALOAD 4
    INSTANCEOF com/example/datn/core/utils/Resource$Error
    IFEQ L240
    ALOAD 2
    NEW com/example/datn/core/utils/Resource$Error
    DUP
    ALOAD 4
    CHECKCAST com/example/datn/core/utils/Resource$Error
    INVOKEVIRTUAL com/example/datn/core/utils/Resource$Error.getMessage ()Ljava/lang/String;
    INVOKESPECIAL com/example/datn/core/utils/Resource$Error.<init> (Ljava/lang/String;)V
    ALOAD 0
    CHECKCAST kotlin/coroutines/Continuation
    ALOAD 0
    ALOAD 2
    PUTFIELD com/example/datn/data/repository/impl/TestRepositoryImpl$submitTestResult$1.L$0 : Ljava/lang/Object;
    ALOAD 0
    ACONST_NULL
    PUTFIELD com/example/datn/data/repository/impl/TestRepositoryImpl$submitTestResult$1.L$1 : Ljava/lang/Object;
    ALOAD 0
    BIPUSH 9
    PUTFIELD com/example/datn/data/repository/impl/TestRepositoryImpl$submitTestResult$1.label : I
    INVOKEINTERFACE kotlinx/coroutines/flow/FlowCollector.emit (Ljava/lang/Object;Lkotlin/coroutines/Continuation;)Ljava/lang/Object; (itf)
   L24
    DUP
    ALOAD 35
    IF_ACMPNE L241
   L242
    LINENUMBER 252 L242
    ALOAD 35
    ARETURN
   L40
    ALOAD 0
    GETFIELD com/example/datn/data/repository/impl/TestRepositoryImpl$submitTestResult$1.L$0 : Ljava/lang/Object;
    CHECKCAST kotlinx/coroutines/flow/FlowCollector
    ASTORE 2
   L243
   L25
    NOP
    ALOAD 1
    INVOKESTATIC kotlin/ResultKt.throwOnFailure (Ljava/lang/Object;)V
    ALOAD 1
   L241
    LINENUMBER 335 L241
    POP
    GOTO L238
   L240
   L244
    LINENUMBER 336 L244
    ALOAD 4
    INSTANCEOF com/example/datn/core/utils/Resource$Loading
    IFEQ L245
    ALOAD 2
    NEW com/example/datn/core/utils/Resource$Loading
    DUP
    INVOKESPECIAL com/example/datn/core/utils/Resource$Loading.<init> ()V
    ALOAD 0
    CHECKCAST kotlin/coroutines/Continuation
    ALOAD 0
    ALOAD 2
    PUTFIELD com/example/datn/data/repository/impl/TestRepositoryImpl$submitTestResult$1.L$0 : Ljava/lang/Object;
    ALOAD 0
    ACONST_NULL
    PUTFIELD com/example/datn/data/repository/impl/TestRepositoryImpl$submitTestResult$1.L$1 : Ljava/lang/Object;
    ALOAD 0
    BIPUSH 10
    PUTFIELD com/example/datn/data/repository/impl/TestRepositoryImpl$submitTestResult$1.label : I
    INVOKEINTERFACE kotlinx/coroutines/flow/FlowCollector.emit (Ljava/lang/Object;Lkotlin/coroutines/Continuation;)Ljava/lang/Object; (itf)
   L26
    DUP
    ALOAD 35
    IF_ACMPNE L246
   L247
    LINENUMBER 252 L247
    ALOAD 35
    ARETURN
   L41
    ALOAD 0
    GETFIELD com/example/datn/data/repository/impl/TestRepositoryImpl$submitTestResult$1.L$0 : Ljava/lang/Object;
    CHECKCAST kotlinx/coroutines/flow/FlowCollector
    ASTORE 2
   L248
   L27
    NOP
    ALOAD 1
    INVOKESTATIC kotlin/ResultKt.throwOnFailure (Ljava/lang/Object;)V
    ALOAD 1
   L246
    LINENUMBER 336 L246
    POP
    GOTO L238
   L245
   L249
    LINENUMBER 260 L249
    NEW kotlin/NoWhenBranchMatchedException
    DUP
    INVOKESPECIAL kotlin/NoWhenBranchMatchedException.<init> ()V
    ATHROW
   L250
   L238
   L251
   L252
   L28
    GOTO L253
   L16
   L254
    LINENUMBER 338 L254
    ASTORE 3
   L255
   L256
    LINENUMBER 339 L256
    ALOAD 2
    NEW com/example/datn/core/utils/Resource$Error
    DUP
    ALOAD 3
    INVOKEVIRTUAL java/lang/Exception.getMessage ()Ljava/lang/String;
    INVOKEDYNAMIC makeConcatWithConstants(Ljava/lang/String;)Ljava/lang/String; [
      // handle kind 0x6 : INVOKESTATIC
      java/lang/invoke/StringConcatFactory.makeConcatWithConstants(Ljava/lang/invoke/MethodHandles$Lookup;Ljava/lang/String;Ljava/lang/invoke/MethodType;Ljava/lang/String;[Ljava/lang/Object;)Ljava/lang/invoke/CallSite;
      // arguments:
      "L\u1ed7i khi n\u1ed9p b\u00e0i ki\u1ec3m tra: \u0001"
    ]
    INVOKESPECIAL com/example/datn/core/utils/Resource$Error.<init> (Ljava/lang/String;)V
    ALOAD 0
    CHECKCAST kotlin/coroutines/Continuation
    ALOAD 0
    ACONST_NULL
    PUTFIELD com/example/datn/data/repository/impl/TestRepositoryImpl$submitTestResult$1.L$0 : Ljava/lang/Object;
    ALOAD 0
    ACONST_NULL
    PUTFIELD com/example/datn/data/repository/impl/TestRepositoryImpl$submitTestResult$1.L$1 : Ljava/lang/Object;
    ALOAD 0
    ACONST_NULL
    PUTFIELD com/example/datn/data/repository/impl/TestRepositoryImpl$submitTestResult$1.L$2 : Ljava/lang/Object;
    ALOAD 0
    ACONST_NULL
    PUTFIELD com/example/datn/data/repository/impl/TestRepositoryImpl$submitTestResult$1.L$3 : Ljava/lang/Object;
    ALOAD 0
    ACONST_NULL
    PUTFIELD com/example/datn/data/repository/impl/TestRepositoryImpl$submitTestResult$1.L$4 : Ljava/lang/Object;
    ALOAD 0
    ACONST_NULL
    PUTFIELD com/example/datn/data/repository/impl/TestRepositoryImpl$submitTestResult$1.L$5 : Ljava/lang/Object;
    ALOAD 0
    ACONST_NULL
    PUTFIELD com/example/datn/data/repository/impl/TestRepositoryImpl$submitTestResult$1.L$6 : Ljava/lang/Object;
    ALOAD 0
    ACONST_NULL
    PUTFIELD com/example/datn/data/repository/impl/TestRepositoryImpl$submitTestResult$1.L$7 : Ljava/lang/Object;
    ALOAD 0
    BIPUSH 11
    PUTFIELD com/example/datn/data/repository/impl/TestRepositoryImpl$submitTestResult$1.label : I
    INVOKEINTERFACE kotlinx/coroutines/flow/FlowCollector.emit (Ljava/lang/Object;Lkotlin/coroutines/Continuation;)Ljava/lang/Object; (itf)
   L257
    DUP
    ALOAD 35
    IF_ACMPNE L258
   L259
    LINENUMBER 252 L259
    ALOAD 35
    ARETURN
   L42
   L260
    NOP
    ALOAD 1
    INVOKESTATIC kotlin/ResultKt.throwOnFailure (Ljava/lang/Object;)V
    ALOAD 1
   L258
    LINENUMBER 341 L258
    POP
   L261
   L253
   L262
    NOP
    GETSTATIC kotlin/Unit.INSTANCE : Lkotlin/Unit;
    ARETURN
   L263
   L43
    LINENUMBER 252 L43
    NEW java/lang/IllegalStateException
    DUP
    LDC "call to 'resume' before 'invoke' with coroutine"
    INVOKESPECIAL java/lang/IllegalStateException.<init> (Ljava/lang/String;)V
    ATHROW
    RETURN
   L264
    LOCALVARIABLE $this$flow Lkotlinx/coroutines/flow/FlowCollector; L45 L32 2
    LOCALVARIABLE $this$flow Lkotlinx/coroutines/flow/FlowCollector; L51 L33 2
    LOCALVARIABLE $this$flow Lkotlinx/coroutines/flow/FlowCollector; L73 L34 2
    LOCALVARIABLE $this$flow Lkotlinx/coroutines/flow/FlowCollector; L87 L35 2
    LOCALVARIABLE $this$flow Lkotlinx/coroutines/flow/FlowCollector; L94 L99 2
    LOCALVARIABLE $this$flow Lkotlinx/coroutines/flow/FlowCollector; L99 L36 2
    LOCALVARIABLE $this$flow Lkotlinx/coroutines/flow/FlowCollector; L122 L180 2
    LOCALVARIABLE $this$flow Lkotlinx/coroutines/flow/FlowCollector; L181 L185 2
    LOCALVARIABLE $this$flow Lkotlinx/coroutines/flow/FlowCollector; L186 L37 2
    LOCALVARIABLE $this$flow Lkotlinx/coroutines/flow/FlowCollector; L212 L38 2
    LOCALVARIABLE $this$flow Lkotlinx/coroutines/flow/FlowCollector; L220 L39 2
    LOCALVARIABLE $this$flow Lkotlinx/coroutines/flow/FlowCollector; L236 L40 2
    LOCALVARIABLE $this$flow Lkotlinx/coroutines/flow/FlowCollector; L243 L41 2
    LOCALVARIABLE $this$flow Lkotlinx/coroutines/flow/FlowCollector; L248 L250 2
    LOCALVARIABLE $this$flow Lkotlinx/coroutines/flow/FlowCollector; L250 L28 2
    LOCALVARIABLE $this$flow Lkotlinx/coroutines/flow/FlowCollector; L16 L257 2
    LOCALVARIABLE withTimestamps Lcom/example/datn/domain/models/StudentTestResult; L68 L33 3
    LOCALVARIABLE withTimestamps Lcom/example/datn/domain/models/StudentTestResult; L72 L79 3
    LOCALVARIABLE withTimestamps Lcom/example/datn/domain/models/StudentTestResult; L79 L80 3
    LOCALVARIABLE e Ljava/lang/Exception; L255 L257 3
    LOCALVARIABLE remote Lcom/example/datn/core/utils/Resource; L74 L78 4
    LOCALVARIABLE remote Lcom/example/datn/core/utils/Resource; L76 L24 4
    LOCALVARIABLE remote Lcom/example/datn/core/utils/Resource; L240 L26 4
    LOCALVARIABLE saved Lcom/example/datn/domain/models/StudentTestResult; L82 L34 5
    LOCALVARIABLE saved Lcom/example/datn/domain/models/StudentTestResult; L86 L35 5
    LOCALVARIABLE saved Lcom/example/datn/domain/models/StudentTestResult; L93 L99 5
    LOCALVARIABLE saved Lcom/example/datn/domain/models/StudentTestResult; L99 L36 5
    LOCALVARIABLE saved Lcom/example/datn/domain/models/StudentTestResult; L121 L180 5
    LOCALVARIABLE saved Lcom/example/datn/domain/models/StudentTestResult; L181 L185 5
    LOCALVARIABLE saved Lcom/example/datn/domain/models/StudentTestResult; L186 L37 5
    LOCALVARIABLE saved Lcom/example/datn/domain/models/StudentTestResult; L211 L38 5
    LOCALVARIABLE saved Lcom/example/datn/domain/models/StudentTestResult; L219 L22 5
    LOCALVARIABLE questions Ljava/util/List; L95 L99 6
    LOCALVARIABLE questions Ljava/util/List; L99 L103 6
    LOCALVARIABLE studentAnswers Ljava/util/List; L101 L36 7
    LOCALVARIABLE studentAnswers Ljava/util/List; L120 L180 7
    LOCALVARIABLE studentAnswers Ljava/util/List; L181 L185 7
    LOCALVARIABLE studentAnswers Ljava/util/List; L186 L37 7
    LOCALVARIABLE studentAnswers Ljava/util/List; L210 L38 7
    LOCALVARIABLE studentAnswers Ljava/util/List; L218 L4 7
    LOCALVARIABLE e Ljava/lang/Exception; L230 L232 7
    LOCALVARIABLE $this$forEach\1 Ljava/lang/Iterable; L103 L105 8
    LOCALVARIABLE $this$map\6 Ljava/lang/Iterable; L188 L190 8
    LOCALVARIABLE e Ljava/lang/Exception; L224 L226 9
    LOCALVARIABLE $this$mapTo\7 Ljava/lang/Iterable; L190 L192 10
    LOCALVARIABLE destination\7 Ljava/util/Collection; L190 L202 11
    LOCALVARIABLE element\1 Ljava/lang/Object; L107 L108 13
    LOCALVARIABLE questionEntity\2 Lcom/example/datn/data/local/entities/TestQuestionEntity; L108 L110 14
    LOCALVARIABLE item\7 Ljava/lang/Object; L194 L201 14
    LOCALVARIABLE it\8 Lcom/example/datn/domain/models/StudentTestAnswer; L195 L199 15
    LOCALVARIABLE question\2 Lcom/example/datn/domain/models/TestQuestion; L110 L36 16
    LOCALVARIABLE question\2 Lcom/example/datn/domain/models/TestQuestion; L119 L170 16
    LOCALVARIABLE answerValue\2 Ljava/lang/Object; L111 L36 17
    LOCALVARIABLE answerValue\2 Ljava/lang/Object; L118 L147 17
    LOCALVARIABLE answerValue\2 Ljava/lang/Object; L147 L149 17
    LOCALVARIABLE answerValue\2 Ljava/lang/Object; L149 L148 17
    LOCALVARIABLE $this$map\3 Ljava/lang/Iterable; L123 L126 18
    LOCALVARIABLE isCorrect\2 Z L143 L172 19
    LOCALVARIABLE $this$mapTo\4 Ljava/lang/Iterable; L126 L128 20
    LOCALVARIABLE destination\4 Ljava/util/Collection; L126 L136 21
    LOCALVARIABLE answerString\2 Ljava/lang/String; L150 L171 22
    LOCALVARIABLE studentAnswer\2 Lcom/example/datn/domain/models/StudentTestAnswer; L168 L178 23
    LOCALVARIABLE item\4 Ljava/lang/Object; L130 L135 24
    LOCALVARIABLE optionEntity\5 Lcom/example/datn/data/local/entities/TestOptionEntity; L131 L133 25
    LOCALVARIABLE options\2 Ljava/util/List; L141 L142 29
    LOCALVARIABLE earnedScore\2 D L144 L178 30
    LOCALVARIABLE $i$a$-map-TestRepositoryImpl$submitTestResult$1$1$options$1\5\665\2 I L132 L133 27
    LOCALVARIABLE $i$f$mapTo\4\663 I L127 L136 22
    LOCALVARIABLE $i$f$map\3\278 I L125 L138 19
    LOCALVARIABLE $i$a$-forEach-TestRepositoryImpl$submitTestResult$1$1\2\662\0 I L109 L36 15
    LOCALVARIABLE $i$f$forEach\1\271 I L104 L36 11
    LOCALVARIABLE $i$a$-map-TestRepositoryImpl$submitTestResult$1$2\8\670\0 I L196 L199 16
    LOCALVARIABLE $i$f$mapTo\7\668 I L191 L202 12
    LOCALVARIABLE $i$f$map\6\317 I L189 L206 9
    LOCALVARIABLE this Lcom/example/datn/data/repository/impl/TestRepositoryImpl$submitTestResult$1; L29 L264 0
    LOCALVARIABLE $result Ljava/lang/Object; L44 L263 1
    LOCALVARIABLE $i$a$-forEach-TestRepositoryImpl$submitTestResult$1$1\2\662\0 I L117 L181 15
    LOCALVARIABLE $i$f$forEach\1\271 I L116 L186 11
    MAXSTACK = 14
    MAXLOCALS = 36

File is unknown
The root cause org.jetbrains.kotlin.codegen.CompilationException was thrown at: org.jetbrains.kotlin.codegen.TransformationMethodVisitor.visitEnd(TransformationMethodVisitor.kt:89)
	at org.jetbrains.kotlin.codegen.TransformationMethodVisitor.visitEnd(TransformationMethodVisitor.kt:89)
	at org.jetbrains.org.objectweb.asm.tree.MethodNode.accept(MethodNode.java:772)
	at org.jetbrains.kotlin.backend.jvm.codegen.CoroutineCodegenKt.acceptWithStateMachine(CoroutineCodegen.kt:76)
	at org.jetbrains.kotlin.backend.jvm.codegen.ClassCodegen.generateMethod(ClassCodegen.kt:440)
	at org.jetbrains.kotlin.backend.jvm.codegen.ClassCodegen.generate(ClassCodegen.kt:168)
	at org.jetbrains.kotlin.backend.jvm.codegen.ExpressionCodegen.visitClass(ExpressionCodegen.kt:1000)
	at org.jetbrains.kotlin.backend.jvm.codegen.ExpressionCodegen.visitClass(ExpressionCodegen.kt:138)
	at org.jetbrains.kotlin.ir.declarations.IrClass.accept(IrClass.kt:72)
	at org.jetbrains.kotlin.backend.jvm.codegen.ExpressionCodegen.visitStatementContainer(ExpressionCodegen.kt:579)
	at org.jetbrains.kotlin.backend.jvm.codegen.ExpressionCodegen.visitContainerExpression(ExpressionCodegen.kt:593)
	at org.jetbrains.kotlin.backend.jvm.codegen.ExpressionCodegen.visitContainerExpression(ExpressionCodegen.kt:138)
	at org.jetbrains.kotlin.ir.visitors.IrElementVisitor$DefaultImpls.visitBlock(IrElementVisitor.kt:122)
	at org.jetbrains.kotlin.backend.jvm.codegen.ExpressionCodegen.visitBlock(ExpressionCodegen.kt:413)
	at org.jetbrains.kotlin.backend.jvm.codegen.ExpressionCodegen.visitBlock(ExpressionCodegen.kt:138)
	at org.jetbrains.kotlin.ir.expressions.IrBlock.accept(IrBlock.kt:18)
	at org.jetbrains.kotlin.backend.jvm.codegen.ExpressionCodegen.gen(ExpressionCodegen.kt:217)
	at org.jetbrains.kotlin.backend.jvm.codegen.IrCallGenerator.genValueAndPut(IrCallGenerator.kt:48)
	at org.jetbrains.kotlin.backend.jvm.codegen.ExpressionCodegen.visitCall$handleParameter(ExpressionCodegen.kt:616)
	at org.jetbrains.kotlin.backend.jvm.codegen.ExpressionCodegen.visitCall(ExpressionCodegen.kt:644)
	at org.jetbrains.kotlin.backend.jvm.codegen.ExpressionCodegen.visitCall(ExpressionCodegen.kt:138)
	at org.jetbrains.kotlin.ir.expressions.IrCall.accept(IrCall.kt:24)
	at org.jetbrains.kotlin.backend.jvm.codegen.ExpressionCodegen.visitReturn(ExpressionCodegen.kt:1051)
	at org.jetbrains.kotlin.backend.jvm.codegen.ExpressionCodegen.visitReturn(ExpressionCodegen.kt:138)
	at org.jetbrains.kotlin.ir.expressions.IrReturn.accept(IrReturn.kt:24)
	at org.jetbrains.kotlin.backend.jvm.codegen.ExpressionCodegen.visitStatementContainer(ExpressionCodegen.kt:579)
	at org.jetbrains.kotlin.backend.jvm.codegen.ExpressionCodegen.visitBlockBody(ExpressionCodegen.kt:584)
	at org.jetbrains.kotlin.backend.jvm.codegen.ExpressionCodegen.visitBlockBody(ExpressionCodegen.kt:138)
	at org.jetbrains.kotlin.ir.expressions.IrBlockBody.accept(IrBlockBody.kt:20)
	at org.jetbrains.kotlin.backend.jvm.codegen.ExpressionCodegen.generate(ExpressionCodegen.kt:240)
	at org.jetbrains.kotlin.backend.jvm.codegen.FunctionCodegen.doGenerate(FunctionCodegen.kt:123)
	at org.jetbrains.kotlin.backend.jvm.codegen.FunctionCodegen.generate(FunctionCodegen.kt:44)
	... 53 more
Caused by: org.jetbrains.kotlin.codegen.CompilationException: Back-end (JVM) Internal error: Couldn't transform method node:
invokeSuspend (Ljava/lang/Object;)Ljava/lang/Object;:
    // annotable parameter count: 1 (visible)
    // annotable parameter count: 1 (invisible)
    TRYCATCHBLOCK L0 L1 L2 java/lang/Exception
    TRYCATCHBLOCK L3 L4 L2 java/lang/Exception
    TRYCATCHBLOCK L5 L6 L7 java/lang/Exception
    TRYCATCHBLOCK L8 L9 L7 java/lang/Exception
    TRYCATCHBLOCK L10 L11 L7 java/lang/Exception
    TRYCATCHBLOCK L12 L1 L7 java/lang/Exception
    TRYCATCHBLOCK L3 L13 L7 java/lang/Exception
    TRYCATCHBLOCK L14 L15 L16 java/lang/Exception
    TRYCATCHBLOCK L17 L18 L16 java/lang/Exception
    TRYCATCHBLOCK L19 L20 L16 java/lang/Exception
    TRYCATCHBLOCK L21 L6 L16 java/lang/Exception
    TRYCATCHBLOCK L8 L9 L16 java/lang/Exception
    TRYCATCHBLOCK L10 L11 L16 java/lang/Exception
    TRYCATCHBLOCK L12 L1 L16 java/lang/Exception
    TRYCATCHBLOCK L3 L22 L16 java/lang/Exception
    TRYCATCHBLOCK L23 L24 L16 java/lang/Exception
    TRYCATCHBLOCK L25 L26 L16 java/lang/Exception
    TRYCATCHBLOCK L27 L28 L16 java/lang/Exception
   L29
    INVOKESTATIC kotlin/coroutines/intrinsics/IntrinsicsKt.getCOROUTINE_SUSPENDED ()Ljava/lang/Object;
   L30
    LINENUMBER 252 L30
    ASTORE 35
    ALOAD 0
    GETFIELD com/example/datn/data/repository/impl/TestRepositoryImpl$submitTestResult$1.label : I
    TABLESWITCH
      0: L31
      1: L32
      2: L33
      3: L34
      4: L35
      5: L36
      6: L37
      7: L38
      8: L39
      9: L40
      10: L41
      11: L42
      default: L43
   L31
    ALOAD 1
    INVOKESTATIC kotlin/ResultKt.throwOnFailure (Ljava/lang/Object;)V
   L44
    ALOAD 0
    GETFIELD com/example/datn/data/repository/impl/TestRepositoryImpl$submitTestResult$1.L$0 : Ljava/lang/Object;
    CHECKCAST kotlinx/coroutines/flow/FlowCollector
    ASTORE 2
   L45
    LINENUMBER 253 L45
   L14
    NOP
   L46
    LINENUMBER 254 L46
    ALOAD 2
    NEW com/example/datn/core/utils/Resource$Loading
    DUP
    INVOKESPECIAL com/example/datn/core/utils/Resource$Loading.<init> ()V
    ALOAD 0
    CHECKCAST kotlin/coroutines/Continuation
    ALOAD 0
    ALOAD 2
    PUTFIELD com/example/datn/data/repository/impl/TestRepositoryImpl$submitTestResult$1.L$0 : Ljava/lang/Object;
    ALOAD 0
    ICONST_1
    PUTFIELD com/example/datn/data/repository/impl/TestRepositoryImpl$submitTestResult$1.label : I
    INVOKEINTERFACE kotlinx/coroutines/flow/FlowCollector.emit (Ljava/lang/Object;Lkotlin/coroutines/Continuation;)Ljava/lang/Object; (itf)
   L15
    DUP
    ALOAD 35
    IF_ACMPNE L47
   L48
    LINENUMBER 252 L48
    ALOAD 35
    ARETURN
   L32
    ALOAD 0
    GETFIELD com/example/datn/data/repository/impl/TestRepositoryImpl$submitTestResult$1.L$0 : Ljava/lang/Object;
    CHECKCAST kotlinx/coroutines/flow/FlowCollector
    ASTORE 2
   L17
    NOP
    ALOAD 1
    INVOKESTATIC kotlin/ResultKt.throwOnFailure (Ljava/lang/Object;)V
    ALOAD 1
   L47
    LINENUMBER 255 L47
    POP
    ALOAD 0
    GETFIELD com/example/datn/data/repository/impl/TestRepositoryImpl$submitTestResult$1.$result : Lcom/example/datn/domain/models/StudentTestResult;
    ACONST_NULL
    ACONST_NULL
    ACONST_NULL
    DCONST_0
    ACONST_NULL
   L49
    LINENUMBER 256 L49
    ALOAD 0
    GETFIELD com/example/datn/data/repository/impl/TestRepositoryImpl$submitTestResult$1.$result : Lcom/example/datn/domain/models/StudentTestResult;
    INVOKEVIRTUAL com/example/datn/domain/models/StudentTestResult.getSubmissionTime ()Ljava/time/Instant;
    INVOKEVIRTUAL java/time/Instant.toEpochMilli ()J
    LCONST_0
    LCMP
    IFNE L50
    INVOKESTATIC java/time/Instant.now ()Ljava/time/Instant;
    GOTO L51
   L50
    ALOAD 0
    GETFIELD com/example/datn/data/repository/impl/TestRepositoryImpl$submitTestResult$1.$result : Lcom/example/datn/domain/models/StudentTestResult;
    INVOKEVIRTUAL com/example/datn/domain/models/StudentTestResult.getSubmissionTime ()Ljava/time/Instant;
   L51
    ASTORE 4
    ALOAD 4
    INVOKESTATIC kotlin/jvm/internal/Intrinsics.checkNotNull (Ljava/lang/Object;)V
    ALOAD 4
   L52
    LINENUMBER 255 L52
    LCONST_0
   L53
    LINENUMBER 257 L53
    ALOAD 0
    GETFIELD com/example/datn/data/repository/impl/TestRepositoryImpl$submitTestResult$1.$result : Lcom/example/datn/domain/models/StudentTestResult;
    INVOKEVIRTUAL com/example/datn/domain/models/StudentTestResult.getCreatedAt ()Ljava/time/Instant;
    INVOKEVIRTUAL java/time/Instant.toEpochMilli ()J
    LCONST_0
    LCMP
    IFNE L54
    INVOKESTATIC java/time/Instant.now ()Ljava/time/Instant;
    GOTO L55
   L54
    ALOAD 0
    GETFIELD com/example/datn/data/repository/impl/TestRepositoryImpl$submitTestResult$1.$result : Lcom/example/datn/domain/models/StudentTestResult;
    INVOKEVIRTUAL com/example/datn/domain/models/StudentTestResult.getCreatedAt ()Ljava/time/Instant;
   L55
    ASTORE 4
    ALOAD 4
    INVOKESTATIC kotlin/jvm/internal/Intrinsics.checkNotNull (Ljava/lang/Object;)V
    ALOAD 4
   L56
    LINENUMBER 258 L56
    INVOKESTATIC java/time/Instant.now ()Ljava/time/Instant;
    ASTORE 4
    ALOAD 4
    LDC "now(...)"
    INVOKESTATIC kotlin/jvm/internal/Intrinsics.checkNotNullExpressionValue (Ljava/lang/Object;Ljava/lang/String;)V
    ALOAD 4
   L57
    LINENUMBER 255 L57
    BIPUSH 95
    ACONST_NULL
    INVOKESTATIC com/example/datn/domain/models/StudentTestResult.copy$default (Lcom/example/datn/domain/models/StudentTestResult;Ljava/lang/String;Ljava/lang/String;Ljava/lang/String;DLcom/example/datn/domain/models/TestStatus;Ljava/time/Instant;JLjava/time/Instant;Ljava/time/Instant;ILjava/lang/Object;)Lcom/example/datn/domain/models/StudentTestResult;
    ASTORE 3
   L58
    LINENUMBER 260 L58
    ALOAD 0
    GETFIELD com/example/datn/data/repository/impl/TestRepositoryImpl$submitTestResult$1.this$0 : Lcom/example/datn/data/repository/impl/TestRepositoryImpl;
    INVOKESTATIC com/example/datn/data/repository/impl/TestRepositoryImpl.access$getFirebaseDataSource$p (Lcom/example/datn/data/repository/impl/TestRepositoryImpl;)Lcom/example/datn/data/remote/datasource/FirebaseDataSource;
    ALOAD 3
    ALOAD 0
    CHECKCAST kotlin/coroutines/Continuation
    ALOAD 0
    ALOAD 2
    PUTFIELD com/example/datn/data/repository/impl/TestRepositoryImpl$submitTestResult$1.L$0 : Ljava/lang/Object;
    ALOAD 0
    ALOAD 3
    PUTFIELD com/example/datn/data/repository/impl/TestRepositoryImpl$submitTestResult$1.L$1 : Ljava/lang/Object;
    ALOAD 0
    ICONST_2
    PUTFIELD com/example/datn/data/repository/impl/TestRepositoryImpl$submitTestResult$1.label : I
    INVOKEVIRTUAL com/example/datn/data/remote/datasource/FirebaseDataSource.submitTestResult (Lcom/example/datn/domain/models/StudentTestResult;Lkotlin/coroutines/Continuation;)Ljava/lang/Object;
   L18
    DUP
    ALOAD 35
    IF_ACMPNE L59
   L60
    LINENUMBER 252 L60
    ALOAD 35
    ARETURN
   L33
    ALOAD 0
    GETFIELD com/example/datn/data/repository/impl/TestRepositoryImpl$submitTestResult$1.L$1 : Ljava/lang/Object;
    CHECKCAST com/example/datn/domain/models/StudentTestResult
    ASTORE 3
   L61
    ALOAD 0
    GETFIELD com/example/datn/data/repository/impl/TestRepositoryImpl$submitTestResult$1.L$0 : Ljava/lang/Object;
    CHECKCAST kotlinx/coroutines/flow/FlowCollector
    ASTORE 2
   L19
    NOP
    ALOAD 1
    INVOKESTATIC kotlin/ResultKt.throwOnFailure (Ljava/lang/Object;)V
    ALOAD 1
   L59
    CHECKCAST com/example/datn/core/utils/Resource
    ASTORE 4
   L62
    NOP
   L63
    LINENUMBER 261 L63
    ALOAD 4
    INSTANCEOF com/example/datn/core/utils/Resource$Success
    IFEQ L64
   L65
    LINENUMBER 262 L65
    ALOAD 4
    CHECKCAST com/example/datn/core/utils/Resource$Success
    INVOKEVIRTUAL com/example/datn/core/utils/Resource$Success.getData ()Ljava/lang/Object;
    CHECKCAST com/example/datn/domain/models/StudentTestResult
    ASTORE 6
   L66
    ALOAD 6
    DUP
    IFNULL L67
    GOTO L68
   L67
    POP
    ALOAD 3
   L68
    ASTORE 5
   L69
    LINENUMBER 263 L69
    ALOAD 0
    GETFIELD com/example/datn/data/repository/impl/TestRepositoryImpl$submitTestResult$1.this$0 : Lcom/example/datn/data/repository/impl/TestRepositoryImpl;
    INVOKESTATIC com/example/datn/data/repository/impl/TestRepositoryImpl.access$getStudentTestResultDao$p (Lcom/example/datn/data/repository/impl/TestRepositoryImpl;)Lcom/example/datn/data/local/dao/StudentTestResultDao;
    ALOAD 5
    INVOKESTATIC com/example/datn/data/mapper/StudentTestResultMapperKt.toEntity (Lcom/example/datn/domain/models/StudentTestResult;)Lcom/example/datn/data/local/entities/StudentTestResultEntity;
    ALOAD 0
    CHECKCAST kotlin/coroutines/Continuation
    ALOAD 0
    ALOAD 2
    PUTFIELD com/example/datn/data/repository/impl/TestRepositoryImpl$submitTestResult$1.L$0 : Ljava/lang/Object;
    ALOAD 0
    ALOAD 5
    PUTFIELD com/example/datn/data/repository/impl/TestRepositoryImpl$submitTestResult$1.L$1 : Ljava/lang/Object;
    ALOAD 0
    ICONST_3
    PUTFIELD com/example/datn/data/repository/impl/TestRepositoryImpl$submitTestResult$1.label : I
    INVOKEINTERFACE com/example/datn/data/local/dao/StudentTestResultDao.insert (Ljava/lang/Object;Lkotlin/coroutines/Continuation;)Ljava/lang/Object; (itf)
   L20
    DUP
    ALOAD 35
    IF_ACMPNE L70
   L71
    LINENUMBER 252 L71
    ALOAD 35
    ARETURN
   L34
    ALOAD 0
    GETFIELD com/example/datn/data/repository/impl/TestRepositoryImpl$submitTestResult$1.L$1 : Ljava/lang/Object;
    CHECKCAST com/example/datn/domain/models/StudentTestResult
    ASTORE 5
   L72
    ALOAD 0
    GETFIELD com/example/datn/data/repository/impl/TestRepositoryImpl$submitTestResult$1.L$0 : Ljava/lang/Object;
    CHECKCAST kotlinx/coroutines/flow/FlowCollector
    ASTORE 2
   L21
    NOP
    ALOAD 1
    INVOKESTATIC kotlin/ResultKt.throwOnFailure (Ljava/lang/Object;)V
    ALOAD 1
   L70
    LINENUMBER 266 L70
    POP
   L5
    NOP
   L73
    LINENUMBER 268 L73
    ALOAD 0
    GETFIELD com/example/datn/data/repository/impl/TestRepositoryImpl$submitTestResult$1.this$0 : Lcom/example/datn/data/repository/impl/TestRepositoryImpl;
    INVOKESTATIC com/example/datn/data/repository/impl/TestRepositoryImpl.access$getTestQuestionDao$p (Lcom/example/datn/data/repository/impl/TestRepositoryImpl;)Lcom/example/datn/data/local/dao/TestQuestionDao;
    ALOAD 5
    INVOKEVIRTUAL com/example/datn/domain/models/StudentTestResult.getTestId ()Ljava/lang/String;
    ALOAD 0
    CHECKCAST kotlin/coroutines/Continuation
    ALOAD 0
    ALOAD 2
    PUTFIELD com/example/datn/data/repository/impl/TestRepositoryImpl$submitTestResult$1.L$0 : Ljava/lang/Object;
    ALOAD 0
    ALOAD 5
    PUTFIELD com/example/datn/data/repository/impl/TestRepositoryImpl$submitTestResult$1.L$1 : Ljava/lang/Object;
    ALOAD 0
    ICONST_4
    PUTFIELD com/example/datn/data/repository/impl/TestRepositoryImpl$submitTestResult$1.label : I
    INVOKEINTERFACE com/example/datn/data/local/dao/TestQuestionDao.getQuestionsByTest (Ljava/lang/String;Lkotlin/coroutines/Continuation;)Ljava/lang/Object; (itf)
   L6
    DUP
    ALOAD 35
    IF_ACMPNE L74
   L75
    LINENUMBER 252 L75
    ALOAD 35
    ARETURN
   L35
    ALOAD 0
    GETFIELD com/example/datn/data/repository/impl/TestRepositoryImpl$submitTestResult$1.L$1 : Ljava/lang/Object;
    CHECKCAST com/example/datn/domain/models/StudentTestResult
    ASTORE 5
   L76
    ALOAD 0
    GETFIELD com/example/datn/data/repository/impl/TestRepositoryImpl$submitTestResult$1.L$0 : Ljava/lang/Object;
    CHECKCAST kotlinx/coroutines/flow/FlowCollector
    ASTORE 2
   L8
    NOP
    ALOAD 1
    INVOKESTATIC kotlin/ResultKt.throwOnFailure (Ljava/lang/Object;)V
    ALOAD 1
   L74
    CHECKCAST java/util/List
    ASTORE 6
   L77
    LINENUMBER 269 L77
    NOP
    NEW java/util/ArrayList
    DUP
    INVOKESPECIAL java/util/ArrayList.<init> ()V
    CHECKCAST java/util/List
    GOTO L78
   L78
    LINENUMBER 269 L78
    ASTORE 7
   L79
    LINENUMBER 271 L79
    ALOAD 6
    CHECKCAST java/lang/Iterable
    ASTORE 8
    ALOAD 0
    GETFIELD com/example/datn/data/repository/impl/TestRepositoryImpl$submitTestResult$1.$answers : Ljava/util/Map;
    ASTORE 9
    ALOAD 0
    GETFIELD com/example/datn/data/repository/impl/TestRepositoryImpl$submitTestResult$1.this$0 : Lcom/example/datn/data/repository/impl/TestRepositoryImpl;
    ASTORE 10
   L80
    ICONST_0
    ISTORE 11
   L81
    LINENUMBER 662 L81
    ALOAD 8
    INVOKEINTERFACE java/lang/Iterable.iterator ()Ljava/util/Iterator; (itf)
    ASTORE 12
   L82
    ALOAD 12
    INVOKEINTERFACE java/util/Iterator.hasNext ()Z (itf)
    IFEQ L83
    ALOAD 12
    INVOKEINTERFACE java/util/Iterator.next ()Ljava/lang/Object; (itf)
    ASTORE 13
   L84
    ALOAD 13
    CHECKCAST com/example/datn/data/local/entities/TestQuestionEntity
    ASTORE 14
   L85
    ICONST_0
    ISTORE 15
   L86
    LINENUMBER 272 L86
    ALOAD 14
    INVOKESTATIC com/example/datn/data/mapper/TestQuestionMapperKt.toDomain (Lcom/example/datn/data/local/entities/TestQuestionEntity;)Lcom/example/datn/domain/models/TestQuestion;
    ASTORE 16
   L87
    LINENUMBER 273 L87
    ALOAD 9
    ALOAD 16
    INVOKEVIRTUAL com/example/datn/domain/models/TestQuestion.getId ()Ljava/lang/String;
    INVOKEINTERFACE java/util/Map.get (Ljava/lang/Object;)Ljava/lang/Object; (itf)
    ASTORE 17
   L88
    LINENUMBER 275 L88
    ALOAD 17
    IFNULL L89
   L90
    LINENUMBER 277 L90
    ALOAD 10
    INVOKESTATIC com/example/datn/data/repository/impl/TestRepositoryImpl.access$getTestOptionDao$p (Lcom/example/datn/data/repository/impl/TestRepositoryImpl;)Lcom/example/datn/data/local/dao/TestOptionDao;
    ALOAD 16
    INVOKEVIRTUAL com/example/datn/domain/models/TestQuestion.getId ()Ljava/lang/String;
    ALOAD 0
    ALOAD 0
    ALOAD 2
    PUTFIELD com/example/datn/data/repository/impl/TestRepositoryImpl$submitTestResult$1.L$0 : Ljava/lang/Object;
    ALOAD 0
    ALOAD 5
    PUTFIELD com/example/datn/data/repository/impl/TestRepositoryImpl$submitTestResult$1.L$1 : Ljava/lang/Object;
    ALOAD 0
    ALOAD 7
    PUTFIELD com/example/datn/data/repository/impl/TestRepositoryImpl$submitTestResult$1.L$2 : Ljava/lang/Object;
    ALOAD 0
    ALOAD 9
    PUTFIELD com/example/datn/data/repository/impl/TestRepositoryImpl$submitTestResult$1.L$3 : Ljava/lang/Object;
    ALOAD 0
    ALOAD 10
    PUTFIELD com/example/datn/data/repository/impl/TestRepositoryImpl$submitTestResult$1.L$4 : Ljava/lang/Object;
    ALOAD 0
    ALOAD 12
    PUTFIELD com/example/datn/data/repository/impl/TestRepositoryImpl$submitTestResult$1.L$5 : Ljava/lang/Object;
    ALOAD 0
    ALOAD 16
    PUTFIELD com/example/datn/data/repository/impl/TestRepositoryImpl$submitTestResult$1.L$6 : Ljava/lang/Object;
    ALOAD 0
    ALOAD 17
    PUTFIELD com/example/datn/data/repository/impl/TestRepositoryImpl$submitTestResult$1.L$7 : Ljava/lang/Object;
    ALOAD 0
    ICONST_5
    PUTFIELD com/example/datn/data/repository/impl/TestRepositoryImpl$submitTestResult$1.label : I
    INVOKEINTERFACE com/example/datn/data/local/dao/TestOptionDao.getOptionsByQuestion (Ljava/lang/String;Lkotlin/coroutines/Continuation;)Ljava/lang/Object; (itf)
   L9
    DUP
    ALOAD 35
    IF_ACMPNE L91
   L92
    LINENUMBER 252 L92
    ALOAD 35
    ARETURN
   L36
    ICONST_0
    ISTORE 11
   L93
    ICONST_0
    ISTORE 15
   L94
    ALOAD 0
    GETFIELD com/example/datn/data/repository/impl/TestRepositoryImpl$submitTestResult$1.L$7 : Ljava/lang/Object;
    ASTORE 17
   L95
    ALOAD 0
    GETFIELD com/example/datn/data/repository/impl/TestRepositoryImpl$submitTestResult$1.L$6 : Ljava/lang/Object;
    CHECKCAST com/example/datn/domain/models/TestQuestion
    ASTORE 16
   L96
    ALOAD 0
    GETFIELD com/example/datn/data/repository/impl/TestRepositoryImpl$submitTestResult$1.L$5 : Ljava/lang/Object;
    CHECKCAST java/util/Iterator
    ASTORE 12
    ALOAD 0
    GETFIELD com/example/datn/data/repository/impl/TestRepositoryImpl$submitTestResult$1.L$4 : Ljava/lang/Object;
    CHECKCAST com/example/datn/data/repository/impl/TestRepositoryImpl
    ASTORE 10
    ALOAD 0
    GETFIELD com/example/datn/data/repository/impl/TestRepositoryImpl$submitTestResult$1.L$3 : Ljava/lang/Object;
    CHECKCAST java/util/Map
    ASTORE 9
    ALOAD 0
    GETFIELD com/example/datn/data/repository/impl/TestRepositoryImpl$submitTestResult$1.L$2 : Ljava/lang/Object;
    CHECKCAST java/util/List
    ASTORE 7
   L97
    ALOAD 0
    GETFIELD com/example/datn/data/repository/impl/TestRepositoryImpl$submitTestResult$1.L$1 : Ljava/lang/Object;
    CHECKCAST com/example/datn/domain/models/StudentTestResult
    ASTORE 5
   L98
    ALOAD 0
    GETFIELD com/example/datn/data/repository/impl/TestRepositoryImpl$submitTestResult$1.L$0 : Ljava/lang/Object;
    CHECKCAST kotlinx/coroutines/flow/FlowCollector
    ASTORE 2
   L10
    NOP
    ALOAD 1
    INVOKESTATIC kotlin/ResultKt.throwOnFailure (Ljava/lang/Object;)V
    ALOAD 1
   L91
    CHECKCAST java/lang/Iterable
    ASTORE 18
   L99
    LINENUMBER 278 L99
    NOP
    ICONST_0
    ISTORE 19
   L100
    LINENUMBER 663 L100
    ALOAD 18
    ASTORE 20
    NEW java/util/ArrayList
    DUP
    ALOAD 18
    BIPUSH 10
    INVOKESTATIC kotlin/collections/CollectionsKt.collectionSizeOrDefault (Ljava/lang/Iterable;I)I
    INVOKESPECIAL java/util/ArrayList.<init> (I)V
    CHECKCAST java/util/Collection
    ASTORE 21
   L101
    ICONST_0
    ISTORE 22
   L102
    LINENUMBER 664 L102
    ALOAD 20
    INVOKEINTERFACE java/lang/Iterable.iterator ()Ljava/util/Iterator; (itf)
    ASTORE 23
   L103
    ALOAD 23
    INVOKEINTERFACE java/util/Iterator.hasNext ()Z (itf)
    IFEQ L104
    ALOAD 23
    INVOKEINTERFACE java/util/Iterator.next ()Ljava/lang/Object; (itf)
    ASTORE 24
   L105
    LINENUMBER 665 L105
    ALOAD 21
    ALOAD 24
    CHECKCAST com/example/datn/data/local/entities/TestOptionEntity
    ASTORE 25
    ASTORE 26
   L106
    ICONST_0
    ISTORE 27
   L107
    LINENUMBER 279 L107
    ALOAD 25
    INVOKESTATIC com/example/datn/data/mapper/TestOptionMapperKt.toDomain (Lcom/example/datn/data/local/entities/TestOptionEntity;)Lcom/example/datn/domain/models/TestOption;
    GOTO L108
   L108
    ASTORE 28
    ALOAD 26
    ALOAD 28
   L109
    LINENUMBER 665 L109
    INVOKEINTERFACE java/util/Collection.add (Ljava/lang/Object;)Z (itf)
    POP
   L110
    GOTO L103
   L104
    LINENUMBER 666 L104
    ALOAD 21
   L111
    CHECKCAST java/util/List
   L112
    LINENUMBER 663 L112
    GOTO L113
   L113
    LINENUMBER 278 L113
   L114
    LINENUMBER 277 L114
    ASTORE 29
   L115
    LINENUMBER 283 L115
    ALOAD 10
    ALOAD 16
    ALOAD 29
    ALOAD 17
    INVOKESTATIC com/example/datn/data/repository/impl/TestRepositoryImpl.access$gradeAnswer (Lcom/example/datn/data/repository/impl/TestRepositoryImpl;Lcom/example/datn/domain/models/TestQuestion;Ljava/util/List;Ljava/lang/Object;)Lkotlin/Pair;
    ASTORE 18
   L116
    ALOAD 18
    INVOKEVIRTUAL kotlin/Pair.component1 ()Ljava/lang/Object;
    CHECKCAST java/lang/Boolean
    INVOKEVIRTUAL java/lang/Boolean.booleanValue ()Z
    ISTORE 19
   L117
    ALOAD 18
    INVOKEVIRTUAL kotlin/Pair.component2 ()Ljava/lang/Object;
    CHECKCAST java/lang/Number
    INVOKEVIRTUAL java/lang/Number.doubleValue ()D
    DSTORE 30
   L118
    LINENUMBER 286 L118
    ALOAD 17
    ASTORE 23
    NOP
   L119
    LINENUMBER 287 L119
    ALOAD 23
    INSTANCEOF java/lang/String
    IFEQ L120
    ALOAD 17
    CHECKCAST java/lang/String
    GOTO L121
   L120
    LINENUMBER 288 L120
    ALOAD 23
    INSTANCEOF java/util/List
    IFEQ L122
    ALOAD 17
    CHECKCAST java/lang/Iterable
    LDC ","
    CHECKCAST java/lang/CharSequence
    ACONST_NULL
    ACONST_NULL
    ICONST_0
    ACONST_NULL
    ACONST_NULL
    BIPUSH 62
    ACONST_NULL
    INVOKESTATIC kotlin/collections/CollectionsKt.joinToString$default (Ljava/lang/Iterable;Ljava/lang/CharSequence;Ljava/lang/CharSequence;Ljava/lang/CharSequence;ILjava/lang/CharSequence;Lkotlin/jvm/functions/Function1;ILjava/lang/Object;)Ljava/lang/String;
    GOTO L121
   L122
    LINENUMBER 289 L122
    ALOAD 17
    INVOKEVIRTUAL java/lang/Object.toString ()Ljava/lang/String;
   L121
    LINENUMBER 286 L121
    ASTORE 22
   L123
    LINENUMBER 293 L123
    NEW com/example/datn/domain/models/StudentTestAnswer
    DUP
   L124
    LINENUMBER 294 L124
    INVOKESTATIC java/util/UUID.randomUUID ()Ljava/util/UUID;
    INVOKEVIRTUAL java/util/UUID.toString ()Ljava/lang/String;
    ASTORE 24
    ALOAD 24
    LDC "toString(...)"
    INVOKESTATIC kotlin/jvm/internal/Intrinsics.checkNotNullExpressionValue (Ljava/lang/Object;Ljava/lang/String;)V
    ALOAD 24
   L125
    LINENUMBER 295 L125
    ALOAD 5
    INVOKEVIRTUAL com/example/datn/domain/models/StudentTestResult.getId ()Ljava/lang/String;
   L126
    LINENUMBER 296 L126
    ALOAD 16
    INVOKEVIRTUAL com/example/datn/domain/models/TestQuestion.getId ()Ljava/lang/String;
   L127
    LINENUMBER 297 L127
    ALOAD 22
   L128
    LINENUMBER 298 L128
    ILOAD 19
    IFEQ L129
    ICONST_1
    GOTO L130
   L129
    ICONST_0
   L130
    LINENUMBER 299 L130
    DLOAD 30
   L131
    LINENUMBER 300 L131
    INVOKESTATIC java/time/Instant.now ()Ljava/time/Instant;
    ASTORE 24
    ALOAD 24
    LDC "now(...)"
    INVOKESTATIC kotlin/jvm/internal/Intrinsics.checkNotNullExpressionValue (Ljava/lang/Object;Ljava/lang/String;)V
    ALOAD 24
   L132
    LINENUMBER 301 L132
    INVOKESTATIC java/time/Instant.now ()Ljava/time/Instant;
    ASTORE 24
    ALOAD 24
    LDC "now(...)"
    INVOKESTATIC kotlin/jvm/internal/Intrinsics.checkNotNullExpressionValue (Ljava/lang/Object;Ljava/lang/String;)V
    ALOAD 24
   L133
    LINENUMBER 293 L133
    INVOKESPECIAL com/example/datn/domain/models/StudentTestAnswer.<init> (Ljava/lang/String;Ljava/lang/String;Ljava/lang/String;Ljava/lang/String;ZDLjava/time/Instant;Ljava/time/Instant;)V
    ASTORE 23
   L134
    LINENUMBER 304 L134
    LDC "TestRepository"
   L135
    LINENUMBER 306 L135
    ALOAD 16
    INVOKEVIRTUAL com/example/datn/domain/models/TestQuestion.getContent ()Ljava/lang/String;
   L136
    LINENUMBER 307 L136
    ALOAD 22
   L137
    LINENUMBER 308 L137
    ILOAD 19
    IFEQ L138
    ICONST_1
    GOTO L139
   L138
    ICONST_0
   L139
    LINENUMBER 309 L139
    DLOAD 30
    INVOKEDYNAMIC makeConcatWithConstants(Ljava/lang/String;Ljava/lang/String;ZD)Ljava/lang/String; [
      // handle kind 0x6 : INVOKESTATIC
      java/lang/invoke/StringConcatFactory.makeConcatWithConstants(Ljava/lang/invoke/MethodHandles$Lookup;Ljava/lang/String;Ljava/lang/invoke/MethodType;Ljava/lang/String;[Ljava/lang/Object;)Ljava/lang/invoke/CallSite;
      // arguments:
      "\n                                    [SAVE ANSWER]\n                                    Question: \u0001\n                                    AnswerString: \u0001\n                                    isCorrect: \u0001\n                                    earnedScore: \u0001\n                                "
    ]
   L140
    LINENUMBER 310 L140
    INVOKESTATIC kotlin/text/StringsKt.trimIndent (Ljava/lang/String;)Ljava/lang/String;
   L141
    LINENUMBER 304 L141
    INVOKESTATIC android/util/Log.d (Ljava/lang/String;Ljava/lang/String;)I
    POP
   L142
    LINENUMBER 312 L142
    ALOAD 7
    ALOAD 23
    INVOKEINTERFACE java/util/List.add (Ljava/lang/Object;)Z (itf)
   L143
    POP
   L89
    LINENUMBER 314 L89
    GOTO L144
   L144
    LINENUMBER 662 L144
    GOTO L82
   L83
    LINENUMBER 667 L83
    GOTO L145
   L145
    LINENUMBER 317 L145
    ALOAD 0
    GETFIELD com/example/datn/data/repository/impl/TestRepositoryImpl$submitTestResult$1.this$0 : Lcom/example/datn/data/repository/impl/TestRepositoryImpl;
    INVOKESTATIC com/example/datn/data/repository/impl/TestRepositoryImpl.access$getStudentTestAnswerDao$p (Lcom/example/datn/data/repository/impl/TestRepositoryImpl;)Lcom/example/datn/data/local/dao/StudentTestAnswerDao;
    ALOAD 7
    CHECKCAST java/lang/Iterable
    ASTORE 8
    ASTORE 32
   L146
    ICONST_0
    ISTORE 9
   L147
    LINENUMBER 668 L147
    ALOAD 8
    ASTORE 10
    NEW java/util/ArrayList
    DUP
    ALOAD 8
    BIPUSH 10
    INVOKESTATIC kotlin/collections/CollectionsKt.collectionSizeOrDefault (Ljava/lang/Iterable;I)I
    INVOKESPECIAL java/util/ArrayList.<init> (I)V
    CHECKCAST java/util/Collection
    ASTORE 11
   L148
    ICONST_0
    ISTORE 12
   L149
    LINENUMBER 669 L149
    ALOAD 10
    INVOKEINTERFACE java/lang/Iterable.iterator ()Ljava/util/Iterator; (itf)
    ASTORE 13
   L150
    ALOAD 13
    INVOKEINTERFACE java/util/Iterator.hasNext ()Z (itf)
    IFEQ L151
    ALOAD 13
    INVOKEINTERFACE java/util/Iterator.next ()Ljava/lang/Object; (itf)
    ASTORE 14
   L152
    LINENUMBER 670 L152
    ALOAD 11
    ALOAD 14
    CHECKCAST com/example/datn/domain/models/StudentTestAnswer
    ASTORE 15
    ASTORE 33
   L153
    ICONST_0
    ISTORE 16
   L154
    LINENUMBER 317 L154
    ALOAD 15
    INVOKESTATIC com/example/datn/data/local/entities/StudentTestAnswerEntityKt.toEntity (Lcom/example/datn/domain/models/StudentTestAnswer;)Lcom/example/datn/data/local/entities/StudentTestAnswerEntity;
    GOTO L155
   L155
    ASTORE 34
    ALOAD 33
    ALOAD 34
   L156
    LINENUMBER 670 L156
    INVOKEINTERFACE java/util/Collection.add (Ljava/lang/Object;)Z (itf)
    POP
   L157
    GOTO L150
   L151
    LINENUMBER 671 L151
    ALOAD 11
   L158
    CHECKCAST java/util/List
   L159
    LINENUMBER 668 L159
    GOTO L160
   L160
    ASTORE 33
    ALOAD 32
    ALOAD 33
    ALOAD 0
    CHECKCAST kotlin/coroutines/Continuation
   L161
    LINENUMBER 317 L161
    ALOAD 0
    ALOAD 2
    PUTFIELD com/example/datn/data/repository/impl/TestRepositoryImpl$submitTestResult$1.L$0 : Ljava/lang/Object;
    ALOAD 0
    ALOAD 5
    PUTFIELD com/example/datn/data/repository/impl/TestRepositoryImpl$submitTestResult$1.L$1 : Ljava/lang/Object;
    ALOAD 0
    ALOAD 7
    PUTFIELD com/example/datn/data/repository/impl/TestRepositoryImpl$submitTestResult$1.L$2 : Ljava/lang/Object;
    ALOAD 0
    ACONST_NULL
    PUTFIELD com/example/datn/data/repository/impl/TestRepositoryImpl$submitTestResult$1.L$3 : Ljava/lang/Object;
    ALOAD 0
    ACONST_NULL
    PUTFIELD com/example/datn/data/repository/impl/TestRepositoryImpl$submitTestResult$1.L$4 : Ljava/lang/Object;
    ALOAD 0
    ACONST_NULL
    PUTFIELD com/example/datn/data/repository/impl/TestRepositoryImpl$submitTestResult$1.L$5 : Ljava/lang/Object;
    ALOAD 0
    ACONST_NULL
    PUTFIELD com/example/datn/data/repository/impl/TestRepositoryImpl$submitTestResult$1.L$6 : Ljava/lang/Object;
    ALOAD 0
    ACONST_NULL
    PUTFIELD com/example/datn/data/repository/impl/TestRepositoryImpl$submitTestResult$1.L$7 : Ljava/lang/Object;
    ALOAD 0
    BIPUSH 6
    PUTFIELD com/example/datn/data/repository/impl/TestRepositoryImpl$submitTestResult$1.label : I
    INVOKEINTERFACE com/example/datn/data/local/dao/StudentTestAnswerDao.insertAll (Ljava/util/List;Lkotlin/coroutines/Continuation;)Ljava/lang/Object; (itf)
   L11
    DUP
    ALOAD 35
    IF_ACMPNE L162
   L163
    LINENUMBER 252 L163
    ALOAD 35
    ARETURN
   L37
    ALOAD 0
    GETFIELD com/example/datn/data/repository/impl/TestRepositoryImpl$submitTestResult$1.L$2 : Ljava/lang/Object;
    CHECKCAST java/util/List
    ASTORE 7
   L164
    ALOAD 0
    GETFIELD com/example/datn/data/repository/impl/TestRepositoryImpl$submitTestResult$1.L$1 : Ljava/lang/Object;
    CHECKCAST com/example/datn/domain/models/StudentTestResult
    ASTORE 5
   L165
    ALOAD 0
    GETFIELD com/example/datn/data/repository/impl/TestRepositoryImpl$submitTestResult$1.L$0 : Ljava/lang/Object;
    CHECKCAST kotlinx/coroutines/flow/FlowCollector
    ASTORE 2
   L12
    NOP
    ALOAD 1
    INVOKESTATIC kotlin/ResultKt.throwOnFailure (Ljava/lang/Object;)V
    ALOAD 1
   L162
    LINENUMBER 320 L162
    POP
   L0
    NOP
   L166
    LINENUMBER 321 L166
    ALOAD 0
    GETFIELD com/example/datn/data/repository/impl/TestRepositoryImpl$submitTestResult$1.this$0 : Lcom/example/datn/data/repository/impl/TestRepositoryImpl;
    INVOKESTATIC com/example/datn/data/repository/impl/TestRepositoryImpl.access$getFirebaseDataSource$p (Lcom/example/datn/data/repository/impl/TestRepositoryImpl;)Lcom/example/datn/data/remote/datasource/FirebaseDataSource;
    ALOAD 7
    ALOAD 0
    CHECKCAST kotlin/coroutines/Continuation
    ALOAD 0
    ALOAD 2
    PUTFIELD com/example/datn/data/repository/impl/TestRepositoryImpl$submitTestResult$1.L$0 : Ljava/lang/Object;
    ALOAD 0
    ALOAD 5
    PUTFIELD com/example/datn/data/repository/impl/TestRepositoryImpl$submitTestResult$1.L$1 : Ljava/lang/Object;
    ALOAD 0
    ALOAD 7
    PUTFIELD com/example/datn/data/repository/impl/TestRepositoryImpl$submitTestResult$1.L$2 : Ljava/lang/Object;
    ALOAD 0
    BIPUSH 7
    PUTFIELD com/example/datn/data/repository/impl/TestRepositoryImpl$submitTestResult$1.label : I
    INVOKEVIRTUAL com/example/datn/data/remote/datasource/FirebaseDataSource.saveStudentAnswers (Ljava/util/List;Lkotlin/coroutines/Continuation;)Ljava/lang/Object;
   L1
    DUP
    ALOAD 35
    IF_ACMPNE L167
   L168
    LINENUMBER 252 L168
    ALOAD 35
    ARETURN
   L38
    ALOAD 0
    GETFIELD com/example/datn/data/repository/impl/TestRepositoryImpl$submitTestResult$1.L$2 : Ljava/lang/Object;
    CHECKCAST java/util/List
    ASTORE 7
   L169
    ALOAD 0
    GETFIELD com/example/datn/data/repository/impl/TestRepositoryImpl$submitTestResult$1.L$1 : Ljava/lang/Object;
    CHECKCAST com/example/datn/domain/models/StudentTestResult
    ASTORE 5
   L170
    ALOAD 0
    GETFIELD com/example/datn/data/repository/impl/TestRepositoryImpl$submitTestResult$1.L$0 : Ljava/lang/Object;
    CHECKCAST kotlinx/coroutines/flow/FlowCollector
    ASTORE 2
   L3
    NOP
    ALOAD 1
    INVOKESTATIC kotlin/ResultKt.throwOnFailure (Ljava/lang/Object;)V
    ALOAD 1
   L167
    LINENUMBER 322 L167
    POP
    LDC "TestRepository"
    ALOAD 7
    INVOKEINTERFACE java/util/List.size ()I (itf)
    INVOKEDYNAMIC makeConcatWithConstants(I)Ljava/lang/String; [
      // handle kind 0x6 : INVOKESTATIC
      java/lang/invoke/StringConcatFactory.makeConcatWithConstants(Ljava/lang/invoke/MethodHandles$Lookup;Ljava/lang/String;Ljava/lang/invoke/MethodType;Ljava/lang/String;[Ljava/lang/Object;)Ljava/lang/invoke/CallSite;
      // arguments:
      "Synced \u0001 answers to Firebase"
    ]
    INVOKESTATIC android/util/Log.d (Ljava/lang/String;Ljava/lang/String;)I
    ISTORE 8
   L4
    GOTO L171
   L2
    LINENUMBER 323 L2
    ASTORE 9
   L172
    LINENUMBER 324 L172
    LDC "TestRepository"
    ALOAD 9
    INVOKEVIRTUAL java/lang/Exception.getMessage ()Ljava/lang/String;
    INVOKEDYNAMIC makeConcatWithConstants(Ljava/lang/String;)Ljava/lang/String; [
      // handle kind 0x6 : INVOKESTATIC
      java/lang/invoke/StringConcatFactory.makeConcatWithConstants(Ljava/lang/invoke/MethodHandles$Lookup;Ljava/lang/String;Ljava/lang/invoke/MethodType;Ljava/lang/String;[Ljava/lang/Object;)Ljava/lang/invoke/CallSite;
      // arguments:
      "Error syncing to Firebase: \u0001"
    ]
    INVOKESTATIC android/util/Log.e (Ljava/lang/String;Ljava/lang/String;)I
    ISTORE 8
   L171
    ILOAD 8
    ISTORE 6
   L13
    GOTO L173
   L7
    LINENUMBER 327 L7
    ASTORE 7
   L174
    LINENUMBER 329 L174
    LDC "TestRepository"
    ALOAD 7
    INVOKEVIRTUAL java/lang/Exception.getMessage ()Ljava/lang/String;
    INVOKEDYNAMIC makeConcatWithConstants(Ljava/lang/String;)Ljava/lang/String; [
      // handle kind 0x6 : INVOKESTATIC
      java/lang/invoke/StringConcatFactory.makeConcatWithConstants(Ljava/lang/invoke/MethodHandles$Lookup;Ljava/lang/String;Ljava/lang/invoke/MethodType;Ljava/lang/String;[Ljava/lang/Object;)Ljava/lang/invoke/CallSite;
      // arguments:
      "Error saving answers: \u0001"
    ]
    INVOKESTATIC android/util/Log.e (Ljava/lang/String;Ljava/lang/String;)I
    ISTORE 6
   L173
    LINENUMBER 333 L173
    ALOAD 2
    NEW com/example/datn/core/utils/Resource$Success
    DUP
    ALOAD 5
    INVOKESPECIAL com/example/datn/core/utils/Resource$Success.<init> (Ljava/lang/Object;)V
    ALOAD 0
    CHECKCAST kotlin/coroutines/Continuation
    ALOAD 0
    ALOAD 2
    PUTFIELD com/example/datn/data/repository/impl/TestRepositoryImpl$submitTestResult$1.L$0 : Ljava/lang/Object;
    ALOAD 0
    ACONST_NULL
    PUTFIELD com/example/datn/data/repository/impl/TestRepositoryImpl$submitTestResult$1.L$1 : Ljava/lang/Object;
    ALOAD 0
    ACONST_NULL
    PUTFIELD com/example/datn/data/repository/impl/TestRepositoryImpl$submitTestResult$1.L$2 : Ljava/lang/Object;
    ALOAD 0
    ACONST_NULL
    PUTFIELD com/example/datn/data/repository/impl/TestRepositoryImpl$submitTestResult$1.L$3 : Ljava/lang/Object;
    ALOAD 0
    ACONST_NULL
    PUTFIELD com/example/datn/data/repository/impl/TestRepositoryImpl$submitTestResult$1.L$4 : Ljava/lang/Object;
    ALOAD 0
    ACONST_NULL
    PUTFIELD com/example/datn/data/repository/impl/TestRepositoryImpl$submitTestResult$1.L$5 : Ljava/lang/Object;
    ALOAD 0
    ACONST_NULL
    PUTFIELD com/example/datn/data/repository/impl/TestRepositoryImpl$submitTestResult$1.L$6 : Ljava/lang/Object;
    ALOAD 0
    ACONST_NULL
    PUTFIELD com/example/datn/data/repository/impl/TestRepositoryImpl$submitTestResult$1.L$7 : Ljava/lang/Object;
    ALOAD 0
    BIPUSH 8
    PUTFIELD com/example/datn/data/repository/impl/TestRepositoryImpl$submitTestResult$1.label : I
    INVOKEINTERFACE kotlinx/coroutines/flow/FlowCollector.emit (Ljava/lang/Object;Lkotlin/coroutines/Continuation;)Ljava/lang/Object; (itf)
   L22
    DUP
    ALOAD 35
    IF_ACMPNE L175
   L176
    LINENUMBER 252 L176
    ALOAD 35
    ARETURN
   L39
    ALOAD 0
    GETFIELD com/example/datn/data/repository/impl/TestRepositoryImpl$submitTestResult$1.L$0 : Ljava/lang/Object;
    CHECKCAST kotlinx/coroutines/flow/FlowCollector
    ASTORE 2
   L23
    NOP
    ALOAD 1
    INVOKESTATIC kotlin/ResultKt.throwOnFailure (Ljava/lang/Object;)V
    ALOAD 1
   L175
    LINENUMBER 333 L175
    POP
    GOTO L28
   L64
    LINENUMBER 335 L64
    ALOAD 4
    INSTANCEOF com/example/datn/core/utils/Resource$Error
    IFEQ L177
    ALOAD 2
    NEW com/example/datn/core/utils/Resource$Error
    DUP
    ALOAD 4
    CHECKCAST com/example/datn/core/utils/Resource$Error
    INVOKEVIRTUAL com/example/datn/core/utils/Resource$Error.getMessage ()Ljava/lang/String;
    INVOKESPECIAL com/example/datn/core/utils/Resource$Error.<init> (Ljava/lang/String;)V
    ALOAD 0
    CHECKCAST kotlin/coroutines/Continuation
    ALOAD 0
    ALOAD 2
    PUTFIELD com/example/datn/data/repository/impl/TestRepositoryImpl$submitTestResult$1.L$0 : Ljava/lang/Object;
    ALOAD 0
    ACONST_NULL
    PUTFIELD com/example/datn/data/repository/impl/TestRepositoryImpl$submitTestResult$1.L$1 : Ljava/lang/Object;
    ALOAD 0
    BIPUSH 9
    PUTFIELD com/example/datn/data/repository/impl/TestRepositoryImpl$submitTestResult$1.label : I
    INVOKEINTERFACE kotlinx/coroutines/flow/FlowCollector.emit (Ljava/lang/Object;Lkotlin/coroutines/Continuation;)Ljava/lang/Object; (itf)
   L24
    DUP
    ALOAD 35
    IF_ACMPNE L178
   L179
    LINENUMBER 252 L179
    ALOAD 35
    ARETURN
   L40
    ALOAD 0
    GETFIELD com/example/datn/data/repository/impl/TestRepositoryImpl$submitTestResult$1.L$0 : Ljava/lang/Object;
    CHECKCAST kotlinx/coroutines/flow/FlowCollector
    ASTORE 2
   L25
    NOP
    ALOAD 1
    INVOKESTATIC kotlin/ResultKt.throwOnFailure (Ljava/lang/Object;)V
    ALOAD 1
   L178
    LINENUMBER 335 L178
    POP
    GOTO L28
   L177
    LINENUMBER 336 L177
    ALOAD 4
    INSTANCEOF com/example/datn/core/utils/Resource$Loading
    IFEQ L180
    ALOAD 2
    NEW com/example/datn/core/utils/Resource$Loading
    DUP
    INVOKESPECIAL com/example/datn/core/utils/Resource$Loading.<init> ()V
    ALOAD 0
    CHECKCAST kotlin/coroutines/Continuation
    ALOAD 0
    ALOAD 2
    PUTFIELD com/example/datn/data/repository/impl/TestRepositoryImpl$submitTestResult$1.L$0 : Ljava/lang/Object;
    ALOAD 0
    ACONST_NULL
    PUTFIELD com/example/datn/data/repository/impl/TestRepositoryImpl$submitTestResult$1.L$1 : Ljava/lang/Object;
    ALOAD 0
    BIPUSH 10
    PUTFIELD com/example/datn/data/repository/impl/TestRepositoryImpl$submitTestResult$1.label : I
    INVOKEINTERFACE kotlinx/coroutines/flow/FlowCollector.emit (Ljava/lang/Object;Lkotlin/coroutines/Continuation;)Ljava/lang/Object; (itf)
   L26
    DUP
    ALOAD 35
    IF_ACMPNE L181
   L182
    LINENUMBER 252 L182
    ALOAD 35
    ARETURN
   L41
    ALOAD 0
    GETFIELD com/example/datn/data/repository/impl/TestRepositoryImpl$submitTestResult$1.L$0 : Ljava/lang/Object;
    CHECKCAST kotlinx/coroutines/flow/FlowCollector
    ASTORE 2
   L27
    NOP
    ALOAD 1
    INVOKESTATIC kotlin/ResultKt.throwOnFailure (Ljava/lang/Object;)V
    ALOAD 1
   L181
    LINENUMBER 336 L181
    POP
    GOTO L28
   L180
    LINENUMBER 260 L180
    NEW kotlin/NoWhenBranchMatchedException
    DUP
    INVOKESPECIAL kotlin/NoWhenBranchMatchedException.<init> ()V
    ATHROW
   L28
    GOTO L183
   L16
    LINENUMBER 338 L16
    ASTORE 3
   L184
    LINENUMBER 339 L184
    ALOAD 2
    NEW com/example/datn/core/utils/Resource$Error
    DUP
    ALOAD 3
    INVOKEVIRTUAL java/lang/Exception.getMessage ()Ljava/lang/String;
    INVOKEDYNAMIC makeConcatWithConstants(Ljava/lang/String;)Ljava/lang/String; [
      // handle kind 0x6 : INVOKESTATIC
      java/lang/invoke/StringConcatFactory.makeConcatWithConstants(Ljava/lang/invoke/MethodHandles$Lookup;Ljava/lang/String;Ljava/lang/invoke/MethodType;Ljava/lang/String;[Ljava/lang/Object;)Ljava/lang/invoke/CallSite;
      // arguments:
      "L\u1ed7i khi n\u1ed9p b\u00e0i ki\u1ec3m tra: \u0001"
    ]
    INVOKESPECIAL com/example/datn/core/utils/Resource$Error.<init> (Ljava/lang/String;)V
    ALOAD 0
    CHECKCAST kotlin/coroutines/Continuation
    ALOAD 0
    ACONST_NULL
    PUTFIELD com/example/datn/data/repository/impl/TestRepositoryImpl$submitTestResult$1.L$0 : Ljava/lang/Object;
    ALOAD 0
    ACONST_NULL
    PUTFIELD com/example/datn/data/repository/impl/TestRepositoryImpl$submitTestResult$1.L$1 : Ljava/lang/Object;
    ALOAD 0
    ACONST_NULL
    PUTFIELD com/example/datn/data/repository/impl/TestRepositoryImpl$submitTestResult$1.L$2 : Ljava/lang/Object;
    ALOAD 0
    ACONST_NULL
    PUTFIELD com/example/datn/data/repository/impl/TestRepositoryImpl$submitTestResult$1.L$3 : Ljava/lang/Object;
    ALOAD 0
    ACONST_NULL
    PUTFIELD com/example/datn/data/repository/impl/TestRepositoryImpl$submitTestResult$1.L$4 : Ljava/lang/Object;
    ALOAD 0
    ACONST_NULL
    PUTFIELD com/example/datn/data/repository/impl/TestRepositoryImpl$submitTestResult$1.L$5 : Ljava/lang/Object;
    ALOAD 0
    ACONST_NULL
    PUTFIELD com/example/datn/data/repository/impl/TestRepositoryImpl$submitTestResult$1.L$6 : Ljava/lang/Object;
    ALOAD 0
    ACONST_NULL
    PUTFIELD com/example/datn/data/repository/impl/TestRepositoryImpl$submitTestResult$1.L$7 : Ljava/lang/Object;
    ALOAD 0
    BIPUSH 11
    PUTFIELD com/example/datn/data/repository/impl/TestRepositoryImpl$submitTestResult$1.label : I
    INVOKEINTERFACE kotlinx/coroutines/flow/FlowCollector.emit (Ljava/lang/Object;Lkotlin/coroutines/Continuation;)Ljava/lang/Object; (itf)
   L185
    DUP
    ALOAD 35
    IF_ACMPNE L186
   L187
    LINENUMBER 252 L187
    ALOAD 35
    ARETURN
   L42
    ALOAD 1
    INVOKESTATIC kotlin/ResultKt.throwOnFailure (Ljava/lang/Object;)V
    ALOAD 1
   L186
    LINENUMBER 341 L186
    POP
   L183
    GETSTATIC kotlin/Unit.INSTANCE : Lkotlin/Unit;
    ARETURN
   L43
    LINENUMBER 252 L43
    NEW java/lang/IllegalStateException
    DUP
    LDC "call to 'resume' before 'invoke' with coroutine"
    INVOKESPECIAL java/lang/IllegalStateException.<init> (Ljava/lang/String;)V
    ATHROW
   L188
    LOCALVARIABLE $this$flow Lkotlinx/coroutines/flow/FlowCollector; L45 L32 2
    LOCALVARIABLE $this$flow Lkotlinx/coroutines/flow/FlowCollector; L17 L33 2
    LOCALVARIABLE $this$flow Lkotlinx/coroutines/flow/FlowCollector; L19 L34 2
    LOCALVARIABLE $this$flow Lkotlinx/coroutines/flow/FlowCollector; L21 L35 2
    LOCALVARIABLE $this$flow Lkotlinx/coroutines/flow/FlowCollector; L8 L78 2
    LOCALVARIABLE $this$flow Lkotlinx/coroutines/flow/FlowCollector; L78 L36 2
    LOCALVARIABLE $this$flow Lkotlinx/coroutines/flow/FlowCollector; L10 L144 2
    LOCALVARIABLE $this$flow Lkotlinx/coroutines/flow/FlowCollector; L144 L145 2
    LOCALVARIABLE $this$flow Lkotlinx/coroutines/flow/FlowCollector; L145 L37 2
    LOCALVARIABLE $this$flow Lkotlinx/coroutines/flow/FlowCollector; L12 L38 2
    LOCALVARIABLE $this$flow Lkotlinx/coroutines/flow/FlowCollector; L3 L39 2
    LOCALVARIABLE $this$flow Lkotlinx/coroutines/flow/FlowCollector; L23 L40 2
    LOCALVARIABLE $this$flow Lkotlinx/coroutines/flow/FlowCollector; L25 L41 2
    LOCALVARIABLE $this$flow Lkotlinx/coroutines/flow/FlowCollector; L27 L28 2
    LOCALVARIABLE $this$flow Lkotlinx/coroutines/flow/FlowCollector; L28 L28 2
    LOCALVARIABLE $this$flow Lkotlinx/coroutines/flow/FlowCollector; L16 L185 2
    LOCALVARIABLE withTimestamps Lcom/example/datn/domain/models/StudentTestResult; L58 L33 3
    LOCALVARIABLE withTimestamps Lcom/example/datn/domain/models/StudentTestResult; L61 L67 3
    LOCALVARIABLE withTimestamps Lcom/example/datn/domain/models/StudentTestResult; L67 L68 3
    LOCALVARIABLE e Ljava/lang/Exception; L184 L185 3
    LOCALVARIABLE remote Lcom/example/datn/core/utils/Resource; L62 L66 4
    LOCALVARIABLE remote Lcom/example/datn/core/utils/Resource; L64 L24 4
    LOCALVARIABLE remote Lcom/example/datn/core/utils/Resource; L177 L26 4
    LOCALVARIABLE saved Lcom/example/datn/domain/models/StudentTestResult; L69 L34 5
    LOCALVARIABLE saved Lcom/example/datn/domain/models/StudentTestResult; L72 L35 5
    LOCALVARIABLE saved Lcom/example/datn/domain/models/StudentTestResult; L76 L78 5
    LOCALVARIABLE saved Lcom/example/datn/domain/models/StudentTestResult; L78 L36 5
    LOCALVARIABLE saved Lcom/example/datn/domain/models/StudentTestResult; L98 L144 5
    LOCALVARIABLE saved Lcom/example/datn/domain/models/StudentTestResult; L144 L145 5
    LOCALVARIABLE saved Lcom/example/datn/domain/models/StudentTestResult; L145 L37 5
    LOCALVARIABLE saved Lcom/example/datn/domain/models/StudentTestResult; L165 L38 5
    LOCALVARIABLE saved Lcom/example/datn/domain/models/StudentTestResult; L170 L22 5
    LOCALVARIABLE questions Ljava/util/List; L77 L78 6
    LOCALVARIABLE questions Ljava/util/List; L78 L80 6
    LOCALVARIABLE studentAnswers Ljava/util/List; L79 L36 7
    LOCALVARIABLE studentAnswers Ljava/util/List; L97 L144 7
    LOCALVARIABLE studentAnswers Ljava/util/List; L144 L145 7
    LOCALVARIABLE studentAnswers Ljava/util/List; L145 L37 7
    LOCALVARIABLE studentAnswers Ljava/util/List; L164 L38 7
    LOCALVARIABLE studentAnswers Ljava/util/List; L169 L4 7
    LOCALVARIABLE e Ljava/lang/Exception; L174 L173 7
    LOCALVARIABLE $this$forEach\1 Ljava/lang/Iterable; L80 L82 8
    LOCALVARIABLE $this$map\6 Ljava/lang/Iterable; L146 L148 8
    LOCALVARIABLE e Ljava/lang/Exception; L172 L171 9
    LOCALVARIABLE $this$mapTo\7 Ljava/lang/Iterable; L148 L150 10
    LOCALVARIABLE destination\7 Ljava/util/Collection; L148 L158 11
    LOCALVARIABLE element\1 Ljava/lang/Object; L84 L85 13
    LOCALVARIABLE questionEntity\2 Lcom/example/datn/data/local/entities/TestQuestionEntity; L85 L87 14
    LOCALVARIABLE item\7 Ljava/lang/Object; L152 L157 14
    LOCALVARIABLE it\8 Lcom/example/datn/domain/models/StudentTestAnswer; L153 L155 15
    LOCALVARIABLE question\2 Lcom/example/datn/domain/models/TestQuestion; L87 L36 16
    LOCALVARIABLE question\2 Lcom/example/datn/domain/models/TestQuestion; L96 L136 16
    LOCALVARIABLE answerValue\2 Ljava/lang/Object; L88 L36 17
    LOCALVARIABLE answerValue\2 Ljava/lang/Object; L95 L120 17
    LOCALVARIABLE answerValue\2 Ljava/lang/Object; L120 L122 17
    LOCALVARIABLE answerValue\2 Ljava/lang/Object; L122 L121 17
    LOCALVARIABLE $this$map\3 Ljava/lang/Iterable; L99 L101 18
    LOCALVARIABLE isCorrect\2 Z L117 L138 19
    LOCALVARIABLE $this$mapTo\4 Ljava/lang/Iterable; L101 L103 20
    LOCALVARIABLE destination\4 Ljava/util/Collection; L101 L111 21
    LOCALVARIABLE answerString\2 Ljava/lang/String; L123 L137 22
    LOCALVARIABLE studentAnswer\2 Lcom/example/datn/domain/models/StudentTestAnswer; L134 L143 23
    LOCALVARIABLE item\4 Ljava/lang/Object; L105 L110 24
    LOCALVARIABLE optionEntity\5 Lcom/example/datn/data/local/entities/TestOptionEntity; L106 L108 25
    LOCALVARIABLE options\2 Ljava/util/List; L115 L116 29
    LOCALVARIABLE earnedScore\2 D L118 L143 30
    LOCALVARIABLE $i$a$-map-TestRepositoryImpl$submitTestResult$1$1$options$1\5\665\2 I L107 L108 27
    LOCALVARIABLE $i$f$mapTo\4\663 I L102 L111 22
    LOCALVARIABLE $i$f$map\3\278 I L100 L113 19
    LOCALVARIABLE $i$a$-forEach-TestRepositoryImpl$submitTestResult$1$1\2\662\0 I L86 L36 15
    LOCALVARIABLE $i$f$forEach\1\271 I L81 L36 11
    LOCALVARIABLE $i$a$-map-TestRepositoryImpl$submitTestResult$1$2\8\670\0 I L154 L155 16
    LOCALVARIABLE $i$f$mapTo\7\668 I L149 L158 12
    LOCALVARIABLE $i$f$map\6\317 I L147 L160 9
    LOCALVARIABLE this Lcom/example/datn/data/repository/impl/TestRepositoryImpl$submitTestResult$1; L29 L188 0
    LOCALVARIABLE $result Ljava/lang/Object; L44 L43 1
    LOCALVARIABLE $i$a$-forEach-TestRepositoryImpl$submitTestResult$1$1\2\662\0 I L94 L144 15
    LOCALVARIABLE $i$f$forEach\1\271 I L93 L145 11
    MAXSTACK = 15
    MAXLOCALS = 36

File is unknown
The root cause java.lang.OutOfMemoryError was thrown at: unknown
	at org.jetbrains.kotlin.codegen.TransformationMethodVisitor.visitEnd(TransformationMethodVisitor.kt:89)
	at org.jetbrains.org.objectweb.asm.MethodVisitor.visitEnd(MethodVisitor.java:783)
	at org.jetbrains.kotlin.codegen.TransformationMethodVisitor.visitEnd(TransformationMethodVisitor.kt:87)
	... 83 more
Caused by: java.lang.OutOfMemoryError: GC overhead limit exceeded


